Workbook

Sheet Start here
A1: CBS Talks Partnerships
A2: Spreadsheet MVP of docs/lean-spec.md. Two scores only: Fit (0–10) and Access (0–4). No budget estimates.
A4: How to use it
A5: 1. Delete the example rows: every row whose company or name ends in '(example)', in all tabs.
A6: 2. Fill in the 'CBS Talks' tab: semester dates and target, then Team, Packages, Themes and Events.
A7: 3. Import past and current partners: Companies + Opportunities (Won, with renewal date and satisfaction) + Commercial Evidence.
A8: 4. Rate companies in 'Companies' (F1, F2, F3, F5 with a reason; a source for every 2) and add at least one Commercial Evidence row.
A9: 5. Every week (30 min): open 'Work Queue', work it top to bottom, log contacts in 'Interactions', update stages and next actions.
A11: Colours
A12: Yellow cells: type here. Grey cells: calculated, don't edit. Dark-blue headers: input columns. Grey headers: calculated columns.
A13: Hover a header in 'Companies' to see the rating anchors.
A15: The rules in one place
... A28: All example companies, people and amounts are fictional.

Sheet Work Queue
A1: Work Queue
A2: ="As of "&TEXT(S_Today,"d mmm yyyy")&" · Work from the top: renewals → follow-ups → Priority prospects → building paths. Calculated, don't edit: update the Opportunities and Companies tabs instead." -> As of 12 Oct 2026 · Work from the top: renewals → follow-ups → Priority prospects → building paths. Calculated, don't edit: update the Opportunities and Companies tabs instead.
A4: 1–2 · Renewals and follow-ups (from Opportunities)
A5: # | B5: Why it's here | C5: Company | D5: Type | E5: Stage | F5: Owner | G5: Next action | H5: Due | I5: Renewal date | J5: key
A6: =IF($J6="","",1) -> 1 | B6: =IF($J6="","",INDEX(Opportunities!$Y$3:$Y$502,MATCH($J6,Opportunities!$Z$3:$Z$502,0))) -> Renewal due | C6: =IF($J6="","",INDEX(Opportunities!$A$3:$A$502,MATCH($J6,Opportunities!$Z$3:$Z$502,0))) -> ProServ (example) | D6: =IF($J6="","",INDEX(Opportunities!$B$3:$B$502,MATCH($J6,Opportunities!$Z$3:$Z$502,0))) -> Recurring sponsor | E6: =IF($J6="","",INDEX(Opportunities!$C$3:$C$502,MATCH($J6,Opportunities!$Z$3:$Z$502,0))) -> Won | F6: =IF($J6="","",IF(INDEX(Opportunities!$D$3:$D$502,MATCH($J6,Opportunities!$Z$3:$Z$502,0))="","(no owner)",INDEX(Opportunities!$D$3:$D$502,MATCH($J6,Opportunities!$Z$3:$Z$502,0)))) -> J.H. (example) | G6: =IF($J6="","",IF(INDEX(Opportunities!$L$3:$L$502,MATCH($J6,Opportunities!$Z$3:$Z$502,0))="","(add a next action)",INDEX(Opportunities!$L$3:$L$502,MATCH($J6,Opportunities!$Z$3:$Z$502,0)))) -> (add a next action) | H6: =IF($J6="","",IF(INDEX(Opportunities!$M$3:$M$502,MATCH($J6,Opportunities!$Z$3:$Z$502,0))="","",INDEX(Opportunities!$M$3:$M$502,MATCH($J6,Opportunities!$Z$3:$Z$502,0)))) | I6: =IF($J6="","",IF(INDEX(Opportunities!$P$3:$P$502,MATCH($J6,Opportunities!$Z$3:$Z$502,0))="","",INDEX(Opportunities!$P$3:$P$502,MATCH($J6,Opportunities!$Z$3:$Z$502,0)))) -> 46337 | J6: =IFERROR(SMALL(Opportunities!$Z$3:$Z$502,1),"") -> 106337
A7: =IF($J7="","",2) -> 2 | B7: =IF($J7="","",INDEX(Opportunities!$Y$3:$Y$502,MATCH($J7,Opportunities!$Z$3:$Z$502,0))) -> Overdue | C7: =IF($J7="","",INDEX(Opportunities!$A$3:$A$502,MATCH($J7,Opportunities!$Z$3:$Z$502,0))) -> MegaBrand A/S (example) | D7: =IF($J7="","",INDEX(Opportunities!$B$3:$B$502,MATCH($J7,Opportunities!$Z$3:$Z$502,0))) -> Recruitment | E7: =IF($J7="","",INDEX(Opportunities!$C$3:$C$502,MATCH($J7,Opportunities!$Z$3:$Z$502,0))) -> Contacted | F7: =IF($J7="","",IF(INDEX(Opportunities!$D$3:$D$502,MATCH($J7,Opportunities!$Z$3:$Z$502,0))="","(no owner)",INDEX(Opportunities!$D$3:$D$502,MATCH($J7,Opportunities!$Z$3:$Z$502,0)))) -> M.S. (example) | G7: =IF($J7="","",IF(INDEX(Opportunities!$L$3:$L$502,MATCH($J7,Opportunities!$Z$3:$Z$502,0))="","(add a next action)",INDEX(Opportunities!$L$3:$L$502,MATCH($J7,Opportunities!$Z$3:$Z$502,0)))) -> Second follow-up email | H7: =IF($J7="","",IF(INDEX(Opportunities!$M$3:$M$502,MATCH($J7,Opportunities!$Z$3:$Z$502,0))="","",INDEX(Opportunities!$M$3:$M$502,MATCH($J7,Opportunities!$Z$3:$Z$502,0)))) -> 46304 | I7: =IF($J7="","",IF(INDEX(Opportunities!$P$3:$P$502,MATCH($J7,Opportunities!$Z$3:$Z$502,0))="","",INDEX(Opportunities!$P$3:$P$502,MATCH($J7,Opportunities!$Z$3:$Z$502,0)))) | J7: =IFERROR(SMALL(Opportunities!$Z$3:$Z$502,2),"") -> 206304
A8: =IF($J8="","",3) -> 3 | B8: =IF($J8="","",INDEX(Opportunities!$Y$3:$Y$502,MATCH($J8,Opportunities!$Z$3:$Z$502,0))) -> Due this week | C8: =IF($J8="","",INDEX(Opportunities!$A$3:$A$502,MATCH($J8,Opportunities!$Z$3:$Z$502,0))) -> Fjord Ventures (example) | D8: =IF($J8="","",INDEX(Opportunities!$B$3:$B$502,MATCH($J8,Opportunities!$Z$3:$Z$502,0))) -> Speaker | E8: =IF($J8="","",INDEX(Opportunities!$C$3:$C$502,MATCH($J8,Opportunities!$Z$3:$Z$502,0))) -> Meeting | F8: =IF($J8="","",IF(INDEX(Opportunities!$D$3:$D$502,MATCH($J8,Opportunities!$Z$3:$Z$502,0))="","(no owner)",INDEX(Opportunities!$D$3:$D$502,MATCH($J8,Opportunities!$Z$3:$Z$502,0)))) -> A.K. (example) | G8: =IF($J8="","",IF(INDEX(Opportunities!$L$3:$L$502,MATCH($J8,Opportunities!$Z$3:$Z$502,0))="","(add a next action)",INDEX(Opportunities!$L$3:$L$502,MATCH($J8,Opportunities!$Z$3:$Z$502,0)))) -> Meeting: confirm keynote date | H8: =IF($J8="","",IF(INDEX(Opportunities!$M$3:$M$502,MATCH($J8,Opportunities!$Z$3:$Z$502,0))="","",INDEX(Opportunities!$M$3:$M$502,MATCH($J8,Opportunities!$Z$3:$Z$502,0)))) -> 46311 | I8: =IF($J8="","",IF(INDEX(Opportunities!$P$3:$P$502,MATCH($J8,Opportunities!$Z$3:$Z$502,0))="","",INDEX(Opportunities!$P$3:$P$502,MATCH($J8,Opportunities!$Z$3:$Z$502,0)))) | J8: =IFERROR(SMALL(Opportunities!$Z$3:$Z$502,3),"") -> 406311
A9: =IF($J9="","",4) -> 4 | B9: =IF($J9="","",INDEX(Opportunities!$Y$3:$Y$502,MATCH($J9,Opportunities!$Z$3:$Z$502,0))) -> Due this week | C9: =IF($J9="","",INDEX(Opportunities!$A$3:$A$502,MATCH($J9,Opportunities!$Z$3:$Z$502,0))) -> Kobber Hotels (example) | D9: =IF($J9="","",INDEX(Opportunities!$B$3:$B$502,MATCH($J9,Opportunities!$Z$3:$Z$502,0))) -> In-kind | E9: =IF($J9="","",INDEX(Opportunities!$C$3:$C$502,MATCH($J9,Opportunities!$Z$3:$Z$502,0))) -> Proposal sent | F9: =IF($J9="","",IF(INDEX(Opportunities!$D$3:$D$502,MATCH($J9,Opportunities!$Z$3:$Z$502,0))="","(no owner)",INDEX(Opportunities!$D$3:$D$502,MATCH($J9,Opportunities!$Z$3:$Z$502,0)))) -> L.M. (example) | G9: =IF($J9="","",IF(INDEX(Opportunities!$L$3:$L$502,MATCH($J9,Opportunities!$Z$3:$Z$502,0))="","(add a next action)",INDEX(Opportunities!$L$3:$L$502,MATCH($J9,Opportunities!$Z$3:$Z$502,0)))) -> Check venue availability | H9: =IF($J9="","",IF(INDEX(Opportunities!$M$3:$M$502,MATCH($J9,Opportunities!$Z$3:$Z$502,0))="","",INDEX(Opportunities!$M$3:$M$502,MATCH($J9,Opportunities!$Z$3:$Z$502,0)))) -> 46313 | I9: =IF($J9="","",IF(INDEX(Opportunities!$P$3:$P$502,MATCH($J9,Opportunities!$Z$3:$Z$502,0))="","",INDEX(Opportunities!$P$3:$P$502,MATCH($J9,Opportunities!$Z$3:$Z$502,0)))) | J9: =IFERROR(SMALL(Opportunities!$Z$3:$Z$502,4),"") -> 406313
A10: =IF($J10="","",5) | B10: =IF($J10="","",INDEX(Opportunities!$Y$3:$Y$502,MATCH($J10,Opportunities!$Z$3:$Z$502,0))) | C10: =IF($J10="","",INDEX(Opportunities!$A$3:$A$502,MATCH($J10,Opportunities!$Z$3:$Z$502,0))) | D10: =IF($J10="","",INDEX(Opportunities!$B$3:$B$502,MATCH($J10,Opportunities!$Z$3:$Z$502,0))) | E10: =IF($J10="","",INDEX(Opportunities!$C$3:$C$502,MATCH($J10,Opportunities!$Z$3:$Z$502,0))) | F10: =IF($J10="","",IF(INDEX(Opportunities!$D$3:$D$502,MATCH($J10,Opportunities!$Z$3:$Z$502,0))="","(no owner)",INDEX(Opportunities!$D$3:$D$502,MATCH($J10,Opportunities!$Z$3:$Z$502,0)))) | G10: =IF($J10="","",IF(INDEX(Opportunities!$L$3:$L$502,MATCH($J10,Opportunities!$Z$3:$Z$502,0))="","(add a next action)",INDEX(Opportunities!$L$3:$L$502,MATCH($J10,Opportunities!$Z$3:$Z$502,0)))) | H10: =IF($J10="","",IF(INDEX(Opportunities!$M$3:$M$502,MATCH($J10,Opportunities!$Z$3:$Z$502,0))="","",INDEX(Opportunities!$M$3:$M$502,MATCH($J10,Opportunities!$Z$3:$Z$502,0)))) | I10: =IF($J10="","",IF(INDEX(Opportunities!$P$3:$P$502,MATCH($J10,Opportunities!$Z$3:$Z$502,0))="","",INDEX(Opportunities!$P$3:$P$502,MATCH($J10,Opportunities!$Z$3:$Z$502,0)))) | J10: =IFERROR(SMALL(Opportunities!$Z$3:$Z$502,5),"")
A11: =IF($J11="","",6) | B11: =IF($J11="","",INDEX(Opportunities!$Y$3:$Y$502,MATCH($J11,Opportunities!$Z$3:$Z$502,0))) | C11: =IF($J11="","",INDEX(Opportunities!$A$3:$A$502,MATCH($J11,Opportunities!$Z$3:$Z$502,0))) | D11: =IF($J11="","",INDEX(Opportunities!$B$3:$B$502,MATCH($J11,Opportunities!$Z$3:$Z$502,0))) | E11: =IF($J11="","",INDEX(Opportunities!$C$3:$C$502,MATCH($J11,Opportunities!$Z$3:$Z$502,0))) | F11: =IF($J11="","",IF(INDEX(Opportunities!$D$3:$D$502,MATCH($J11,Opportunities!$Z$3:$Z$502,0))="","(no owner)",INDEX(Opportunities!$D$3:$D$502,MATCH($J11,Opportunities!$Z$3:$Z$502,0)))) | G11: =IF($J11="","",IF(INDEX(Opportunities!$L$3:$L$502,MATCH($J11,Opportunities!$Z$3:$Z$502,0))="","(add a next action)",INDEX(Opportunities!$L$3:$L$502,MATCH($J11,Opportunities!$Z$3:$Z$502,0)))) | H11: =IF($J11="","",IF(INDEX(Opportunities!$M$3:$M$502,MATCH($J11,Opportunities!$Z$3:$Z$502,0))="","",INDEX(Opportunities!$M$3:$M$502,MATCH($J11,Opportunities!$Z$3:$Z$502,0)))) | I11: =IF($J11="","",IF(INDEX(Opportunities!$P$3:$P$502,MATCH($J11,Opportunities!$Z$3:$Z$502,0))="","",INDEX(Opportunities!$P$3:$P$502,MATCH($J11,Opportunities!$Z$3:$Z$502,0)))) | J11: =IFERROR(SMALL(Opportunities!$Z$3:$Z$502,6),"")
A12: =IF($J12="","",7) | B12: =IF($J12="","",INDEX(Opportunities!$Y$3:$Y$502,MATCH($J12,Opportunities!$Z$3:$Z$502,0))) | C12: =IF($J12="","",INDEX(Opportunities!$A$3:$A$502,MATCH($J12,Opportunities!$Z$3:$Z$502,0))) | D12: =IF($J12="","",INDEX(Opportunities!$B$3:$B$502,MATCH($J12,Opportunities!$Z$3:$Z$502,0))) | E12: =IF($J12="","",INDEX(Opportunities!$C$3:$C$502,MATCH($J12,Opportunities!$Z$3:$Z$502,0))) | F12: =IF($J12="","",IF(INDEX(Opportunities!$D$3:$D$502,MATCH($J12,Opportunities!$Z$3:$Z$502,0))="","(no owner)",INDEX(Opportunities!$D$3:$D$502,MATCH($J12,Opportunities!$Z$3:$Z$502,0)))) | G12: =IF($J12="","",IF(INDEX(Opportunities!$L$3:$L$502,MATCH($J12,Opportunities!$Z$3:$Z$502,0))="","(add a next action)",INDEX(Opportunities!$L$3:$L$502,MATCH($J12,Opportunities!$Z$3:$Z$502,0)))) | H12: =IF($J12="","",IF(INDEX(Opportunities!$M$3:$M$502,MATCH($J12,Opportunities!$Z$3:$Z$502,0))="","",INDEX(Opportunities!$M$3:$M$502,MATCH($J12,Opportunities!$Z$3:$Z$502,0)))) | I12: =IF($J12="","",IF(INDEX(Opportunities!$P$3:$P$502,MATCH($J12,Opportunities!$Z$3:$Z$502,0))="","",INDEX(Opportunities!$P$3:$P$502,MATCH($J12,Opportunities!$Z$3:$Z$502,0)))) | J12: =IFERROR(SMALL(Opportunities!$Z$3:$Z$502,7),"")
A13: =IF($J13="","",8) | B13: =IF($J13="","",INDEX(Opportunities!$Y$3:$Y$502,MATCH($J13,Opportunities!$Z$3:$Z$502,0))) | C13: =IF($J13="","",INDEX(Opportunities!$A$3:$A$502,MATCH($J13,Opportunities!$Z$3:$Z$502,0))) | D13: =IF($J13="","",INDEX(Opportunities!$B$3:$B$502,MATCH($J13,Opportunities!$Z$3:$Z$502,0))) | E13: =IF($J13="","",INDEX(Opportunities!$C$3:$C$502,MATCH($J13,Opportunities!$Z$3:$Z$502,0))) | F13: =IF($J13="","",IF(INDEX(Opportunities!$D$3:$D$502,MATCH($J13,Opportunities!$Z$3:$Z$502,0))="","(no owner)",INDEX(Opportunities!$D$3:$D$502,MATCH($J13,Opportunities!$Z$3:$Z$502,0)))) | G13: =IF($J13="","",IF(INDEX(Opportunities!$L$3:$L$502,MATCH($J13,Opportunities!$Z$3:$Z$502,0))="","(add a next action)",INDEX(Opportunities!$L$3:$L$502,MATCH($J13,Opportunities!$Z$3:$Z$502,0)))) | H13: =IF($J13="","",IF(INDEX(Opportunities!$M$3:$M$502,MATCH($J13,Opportunities!$Z$3:$Z$502,0))="","",INDEX(Opportunities!$M$3:$M$502,MATCH($J13,Opportunities!$Z$3:$Z$502,0)))) | I13: =IF($J13="","",IF(INDEX(Opportunities!$P$3:$P$502,MATCH($J13,Opportunities!$Z$3:$Z$502,0))="","",INDEX(Opportunities!$P$3:$P$502,MATCH($J13,Opportunities!$Z$3:$Z$502,0)))) | J13: =IFERROR(SMALL(Opportunities!$Z$3:$Z$502,8),"")
A14: =IF($J14="","",9) | B14: =IF($J14="","",INDEX(Opportunities!$Y$3:$Y$502,MATCH($J14,Opportunities!$Z$3:$Z$502,0))) | C14: =IF($J14="","",INDEX(Opportunities!$A$3:$A$502,MATCH($J14,Opportunities!$Z$3:$Z$502,0))) | D14: =IF($J14="","",INDEX(Opportunities!$B$3:$B$502,MATCH($J14,Opportunities!$Z$3:$Z$502,0))) | E14: =IF($J14="","",INDEX(Opportunities!$C$3:$C$502,MATCH($J14,Opportunities!$Z$3:$Z$502,0))) | F14: =IF($J14="","",IF(INDEX(Opportunities!$D$3:$D$502,MATCH($J14,Opportunities!$Z$3:$Z$502,0))="","(no owner)",INDEX(Opportunities!$D$3:$D$502,MATCH($J14,Opportunities!$Z$3:$Z$502,0)))) | G14: =IF($J14="","",IF(INDEX(Opportunities!$L$3:$L$502,MATCH($J14,Opportunities!$Z$3:$Z$502,0))="","(add a next action)",INDEX(Opportunities!$L$3:$L$502,MATCH($J14,Opportunities!$Z$3:$Z$502,0)))) | H14: =IF($J14="","",IF(INDEX(Opportunities!$M$3:$M$502,MATCH($J14,Opportunities!$Z$3:$Z$502,0))="","",INDEX(Opportunities!$M$3:$M$502,MATCH($J14,Opportunities!$Z$3:$Z$502,0)))) | I14: =IF($J14="","",IF(INDEX(Opportunities!$P$3:$P$502,MATCH($J14,Opportunities!$Z$3:$Z$502,0))="","",INDEX(Opportunities!$P$3:$P$502,MATCH($J14,Opportunities!$Z$3:$Z$502,0)))) | J14: =IFERROR(SMALL(Opportunities!$Z$3:$Z$502,9),"")
A15: =IF($J15="","",10) | B15: =IF($J15="","",INDEX(Opportunities!$Y$3:$Y$502,MATCH($J15,Opportunities!$Z$3:$Z$502,0))) | C15: =IF($J15="","",INDEX(Opportunities!$A$3:$A$502,MATCH($J15,Opportunities!$Z$3:$Z$502,0))) | D15: =IF($J15="","",INDEX(Opportunities!$B$3:$B$502,MATCH($J15,Opportunities!$Z$3:$Z$502,0))) | E15: =IF($J15="","",INDEX(Opportunities!$C$3:$C$502,MATCH($J15,Opportunities!$Z$3:$Z$502,0))) | F15: =IF($J15="","",IF(INDEX(Opportunities!$D$3:$D$502,MATCH($J15,Opportunities!$Z$3:$Z$502,0))="","(no owner)",INDEX(Opportunities!$D$3:$D$502,MATCH($J15,Opportunities!$Z$3:$Z$502,0)))) | G15: =IF($J15="","",IF(INDEX(Opportunities!$L$3:$L$502,MATCH($J15,Opportunities!$Z$3:$Z$502,0))="","(add a next action)",INDEX(Opportunities!$L$3:$L$502,MATCH($J15,Opportunities!$Z$3:$Z$502,0)))) | H15: =IF($J15="","",IF(INDEX(Opportunities!$M$3:$M$502,MATCH($J15,Opportunities!$Z$3:$Z$502,0))="","",INDEX(Opportunities!$M$3:$M$502,MATCH($J15,Opportunities!$Z$3:$Z$502,0)))) | I15: =IF($J15="","",IF(INDEX(Opportunities!$P$3:$P$502,MATCH($J15,Opportunities!$Z$3:$Z$502,0))="","",INDEX(Opportunities!$P$3:$P$502,MATCH($J15,Opportunities!$Z$3:$Z$502,0)))) | J15: =IFERROR(SMALL(Opportunities!$Z$3:$Z$502,10),"")
A16: =IF($J16="","",11) | B16: =IF($J16="","",INDEX(Opportunities!$Y$3:$Y$502,MATCH($J16,Opportunities!$Z$3:$Z$502,0))) | C16: =IF($J16="","",INDEX(Opportunities!$A$3:$A$502,MATCH($J16,Opportunities!$Z$3:$Z$502,0))) | D16: =IF($J16="","",INDEX(Opportunities!$B$3:$B$502,MATCH($J16,Opportunities!$Z$3:$Z$502,0))) | E16: =IF($J16="","",INDEX(Opportunities!$C$3:$C$502,MATCH($J16,Opportunities!$Z$3:$Z$502,0))) | F16: =IF($J16="","",IF(INDEX(Opportunities!$D$3:$D$502,MATCH($J16,Opportunities!$Z$3:$Z$502,0))="","(no owner)",INDEX(Opportunities!$D$3:$D$502,MATCH($J16,Opportunities!$Z$3:$Z$502,0)))) | G16: =IF($J16="","",IF(INDEX(Opportunities!$L$3:$L$502,MATCH($J16,Opportunities!$Z$3:$Z$502,0))="","(add a next action)",INDEX(Opportunities!$L$3:$L$502,MATCH($J16,Opportunities!$Z$3:$Z$502,0)))) | H16: =IF($J16="","",IF(INDEX(Opportunities!$M$3:$M$502,MATCH($J16,Opportunities!$Z$3:$Z$502,0))="","",INDEX(Opportunities!$M$3:$M$502,MATCH($J16,Opportunities!$Z$3:$Z$502,0)))) | I16: =IF($J16="","",IF(INDEX(Opportunities!$P$3:$P$502,MATCH($J16,Opportunities!$Z$3:$Z$502,0))="","",INDEX(Opportunities!$P$3:$P$502,MATCH($J16,Opportunities!$Z$3:$Z$502,0)))) | J16: =IFERROR(SMALL(Opportunities!$Z$3:$Z$502,11),"")
A17: =IF($J17="","",12) | B17: =IF($J17="","",INDEX(Opportunities!$Y$3:$Y$502,MATCH($J17,Opportunities!$Z$3:$Z$502,0))) | C17: =IF($J17="","",INDEX(Opportunities!$A$3:$A$502,MATCH($J17,Opportunities!$Z$3:$Z$502,0))) | D17: =IF($J17="","",INDEX(Opportunities!$B$3:$B$502,MATCH($J17,Opportunities!$Z$3:$Z$502,0))) | E17: =IF($J17="","",INDEX(Opportunities!$C$3:$C$502,MATCH($J17,Opportunities!$Z$3:$Z$502,0))) | F17: =IF($J17="","",IF(INDEX(Opportunities!$D$3:$D$502,MATCH($J17,Opportunities!$Z$3:$Z$502,0))="","(no owner)",INDEX(Opportunities!$D$3:$D$502,MATCH($J17,Opportunities!$Z$3:$Z$502,0)))) | G17: =IF($J17="","",IF(INDEX(Opportunities!$L$3:$L$502,MATCH($J17,Opportunities!$Z$3:$Z$502,0))="","(add a next action)",INDEX(Opportunities!$L$3:$L$502,MATCH($J17,Opportunities!$Z$3:$Z$502,0)))) | H17: =IF($J17="","",IF(INDEX(Opportunities!$M$3:$M$502,MATCH($J17,Opportunities!$Z$3:$Z$502,0))="","",INDEX(Opportunities!$M$3:$M$502,MATCH($J17,Opportunities!$Z$3:$Z$502,0)))) | I17: =IF($J17="","",IF(INDEX(Opportunities!$P$3:$P$502,MATCH($J17,Opportunities!$Z$3:$Z$502,0))="","",INDEX(Opportunities!$P$3:$P$502,MATCH($J17,Opportunities!$Z$3:$Z$502,0)))) | J17: =IFERROR(SMALL(Opportunities!$Z$3:$Z$502,12),"")
A18: =IF($J18="","",13) | B18: =IF($J18="","",INDEX(Opportunities!$Y$3:$Y$502,MATCH($J18,Opportunities!$Z$3:$Z$502,0))) | C18: =IF($J18="","",INDEX(Opportunities!$A$3:$A$502,MATCH($J18,Opportunities!$Z$3:$Z$502,0))) | D18: =IF($J18="","",INDEX(Opportunities!$B$3:$B$502,MATCH($J18,Opportunities!$Z$3:$Z$502,0))) | E18: =IF($J18="","",INDEX(Opportunities!$C$3:$C$502,MATCH($J18,Opportunities!$Z$3:$Z$502,0))) | F18: =IF($J18="","",IF(INDEX(Opportunities!$D$3:$D$502,MATCH($J18,Opportunities!$Z$3:$Z$502,0))="","(no owner)",INDEX(Opportunities!$D$3:$D$502,MATCH($J18,Opportunities!$Z$3:$Z$502,0)))) | G18: =IF($J18="","",IF(INDEX(Opportunities!$L$3:$L$502,MATCH($J18,Opportunities!$Z$3:$Z$502,0))="","(add a next action)",INDEX(Opportunities!$L$3:$L$502,MATCH($J18,Opportunities!$Z$3:$Z$502,0)))) | H18: =IF($J18="","",IF(INDEX(Opportunities!$M$3:$M$502,MATCH($J18,Opportunities!$Z$3:$Z$502,0))="","",INDEX(Opportunities!$M$3:$M$502,MATCH($J18,Opportunities!$Z$3:$Z$502,0)))) | I18: =IF($J18="","",IF(INDEX(Opportunities!$P$3:$P$502,MATCH($J18,Opportunities!$Z$3:$Z$502,0))="","",INDEX(Opportunities!$P$3:$P$502,MATCH($J18,Opportunities!$Z$3:$Z$502,0)))) | J18: =IFERROR(SMALL(Opportunities!$Z$3:$Z$502,13),"")
A19: =IF($J19="","",14) | B19: =IF($J19="","",INDEX(Opportunities!$Y$3:$Y$502,MATCH($J19,Opportunities!$Z$3:$Z$502,0))) | C19: =IF($J19="","",INDEX(Opportunities!$A$3:$A$502,MATCH($J19,Opportunities!$Z$3:$Z$502,0))) | D19: =IF($J19="","",INDEX(Opportunities!$B$3:$B$502,MATCH($J19,Opportunities!$Z$3:$Z$502,0))) | E19: =IF($J19="","",INDEX(Opportunities!$C$3:$C$502,MATCH($J19,Opportunities!$Z$3:$Z$502,0))) | F19: =IF($J19="","",IF(INDEX(Opportunities!$D$3:$D$502,MATCH($J19,Opportunities!$Z$3:$Z$502,0))="","(no owner)",INDEX(Opportunities!$D$3:$D$502,MATCH($J19,Opportunities!$Z$3:$Z$502,0)))) | G19: =IF($J19="","",IF(INDEX(Opportunities!$L$3:$L$502,MATCH($J19,Opportunities!$Z$3:$Z$502,0))="","(add a next action)",INDEX(Opportunities!$L$3:$L$502,MATCH($J19,Opportunities!$Z$3:$Z$502,0)))) | H19: =IF($J19="","",IF(INDEX(Opportunities!$M$3:$M$502,MATCH($J19,Opportunities!$Z$3:$Z$502,0))="","",INDEX(Opportunities!$M$3:$M$502,MATCH($J19,Opportunities!$Z$3:$Z$502,0)))) | I19: =IF($J19="","",IF(INDEX(Opportunities!$P$3:$P$502,MATCH($J19,Opportunities!$Z$3:$Z$502,0))="","",INDEX(Opportunities!$P$3:$P$502,MATCH($J19,Opportunities!$Z$3:$Z$502,0)))) | J19: =IFERROR(SMALL(Opportunities!$Z$3:$Z$502,14),"")
A20: =IF($J20="","",15) | B20: =IF($J20="","",INDEX(Opportunities!$Y$3:$Y$502,MATCH($J20,Opportunities!$Z$3:$Z$502,0))) | C20: =IF($J20="","",INDEX(Opportunities!$A$3:$A$502,MATCH($J20,Opportunities!$Z$3:$Z$502,0))) | D20: =IF($J20="","",INDEX(Opportunities!$B$3:$B$502,MATCH($J20,Opportunities!$Z$3:$Z$502,0))) | E20: =IF($J20="","",INDEX(Opportunities!$C$3:$C$502,MATCH($J20,Opportunities!$Z$3:$Z$502,0))) | F20: =IF($J20="","",IF(INDEX(Opportunities!$D$3:$D$502,MATCH($J20,Opportunities!$Z$3:$Z$502,0))="","(no owner)",INDEX(Opportunities!$D$3:$D$502,MATCH($J20,Opportunities!$Z$3:$Z$502,0)))) | G20: =IF($J20="","",IF(INDEX(Opportunities!$L$3:$L$502,MATCH($J20,Opportunities!$Z$3:$Z$502,0))="","(add a next action)",INDEX(Opportunities!$L$3:$L$502,MATCH($J20,Opportunities!$Z$3:$Z$502,0)))) | H20: =IF($J20="","",IF(INDEX(Opportunities!$M$3:$M$502,MATCH($J20,Opportunities!$Z$3:$Z$502,0))="","",INDEX(Opportunities!$M$3:$M$502,MATCH($J20,Opportunities!$Z$3:$Z$502,0)))) | I20: =IF($J20="","",IF(INDEX(Opportunities!$P$3:$P$502,MATCH($J20,Opportunities!$Z$3:$Z$502,0))="","",INDEX(Opportunities!$P$3:$P$502,MATCH($J20,Opportunities!$Z$3:$Z$502,0)))) | J20: =IFERROR(SMALL(Opportunities!$Z$3:$Z$502,15),"")
A21: =IF($J21="","",16) | B21: =IF($J21="","",INDEX(Opportunities!$Y$3:$Y$502,MATCH($J21,Opportunities!$Z$3:$Z$502,0))) | C21: =IF($J21="","",INDEX(Opportunities!$A$3:$A$502,MATCH($J21,Opportunities!$Z$3:$Z$502,0))) | D21: =IF($J21="","",INDEX(Opportunities!$B$3:$B$502,MATCH($J21,Opportunities!$Z$3:$Z$502,0))) | E21: =IF($J21="","",INDEX(Opportunities!$C$3:$C$502,MATCH($J21,Opportunities!$Z$3:$Z$502,0))) | F21: =IF($J21="","",IF(INDEX(Opportunities!$D$3:$D$502,MATCH($J21,Opportunities!$Z$3:$Z$502,0))="","(no owner)",INDEX(Opportunities!$D$3:$D$502,MATCH($J21,Opportunities!$Z$3:$Z$502,0)))) | G21: =IF($J21="","",IF(INDEX(Opportunities!$L$3:$L$502,MATCH($J21,Opportunities!$Z$3:$Z$502,0))="","(add a next action)",INDEX(Opportunities!$L$3:$L$502,MATCH($J21,Opportunities!$Z$3:$Z$502,0)))) | H21: =IF($J21="","",IF(INDEX(Opportunities!$M$3:$M$502,MATCH($J21,Opportunities!$Z$3:$Z$502,0))="","",INDEX(Opportunities!$M$3:$M$502,MATCH($J21,Opportunities!$Z$3:$Z$502,0)))) | I21: =IF($J21="","",IF(INDEX(Opportunities!$P$3:$P$502,MATCH($J21,Opportunities!$Z$3:$Z$502,0))="","",INDEX(Opportunities!$P$3:$P$502,MATCH($J21,Opportunities!$Z$3:$Z$502,0)))) | J21: =IFERROR(SMALL(Opportunities!$Z$3:$Z$502,16),"")
A22: =IF($J22="","",17) | B22: =IF($J22="","",INDEX(Opportunities!$Y$3:$Y$502,MATCH($J22,Opportunities!$Z$3:$Z$502,0))) | C22: =IF($J22="","",INDEX(Opportunities!$A$3:$A$502,MATCH($J22,Opportunities!$Z$3:$Z$502,0))) | D22: =IF($J22="","",INDEX(Opportunities!$B$3:$B$502,MATCH($J22,Opportunities!$Z$3:$Z$502,0))) | E22: =IF($J22="","",INDEX(Opportunities!$C$3:$C$502,MATCH($J22,Opportunities!$Z$3:$Z$502,0))) | F22: =IF($J22="","",IF(INDEX(Opportunities!$D$3:$D$502,MATCH($J22,Opportunities!$Z$3:$Z$502,0))="","(no owner)",INDEX(Opportunities!$D$3:$D$502,MATCH($J22,Opportunities!$Z$3:$Z$502,0)))) | G22: =IF($J22="","",IF(INDEX(Opportunities!$L$3:$L$502,MATCH($J22,Opportunities!$Z$3:$Z$502,0))="","(add a next action)",INDEX(Opportunities!$L$3:$L$502,MATCH($J22,Opportunities!$Z$3:$Z$502,0)))) | H22: =IF($J22="","",IF(INDEX(Opportunities!$M$3:$M$502,MATCH($J22,Opportunities!$Z$3:$Z$502,0))="","",INDEX(Opportunities!$M$3:$M$502,MATCH($J22,Opportunities!$Z$3:$Z$502,0)))) | I22: =IF($J22="","",IF(INDEX(Opportunities!$P$3:$P$502,MATCH($J22,Opportunities!$Z$3:$Z$502,0))="","",INDEX(Opportunities!$P$3:$P$502,MATCH($J22,Opportunities!$Z$3:$Z$502,0)))) | J22: =IFERROR(SMALL(Opportunities!$Z$3:$Z$502,17),"")
A23: =IF($J23="","",18) | B23: =IF($J23="","",INDEX(Opportunities!$Y$3:$Y$502,MATCH($J23,Opportunities!$Z$3:$Z$502,0))) | C23: =IF($J23="","",INDEX(Opportunities!$A$3:$A$502,MATCH($J23,Opportunities!$Z$3:$Z$502,0))) | D23: =IF($J23="","",INDEX(Opportunities!$B$3:$B$502,MATCH($J23,Opportunities!$Z$3:$Z$502,0))) | E23: =IF($J23="","",INDEX(Opportunities!$C$3:$C$502,MATCH($J23,Opportunities!$Z$3:$Z$502,0))) | F23: =IF($J23="","",IF(INDEX(Opportunities!$D$3:$D$502,MATCH($J23,Opportunities!$Z$3:$Z$502,0))="","(no owner)",INDEX(Opportunities!$D$3:$D$502,MATCH($J23,Opportunities!$Z$3:$Z$502,0)))) | G23: =IF($J23="","",IF(INDEX(Opportunities!$L$3:$L$502,MATCH($J23,Opportunities!$Z$3:$Z$502,0))="","(add a next action)",INDEX(Opportunities!$L$3:$L$502,MATCH($J23,Opportunities!$Z$3:$Z$502,0)))) | H23: =IF($J23="","",IF(INDEX(Opportunities!$M$3:$M$502,MATCH($J23,Opportunities!$Z$3:$Z$502,0))="","",INDEX(Opportunities!$M$3:$M$502,MATCH($J23,Opportunities!$Z$3:$Z$502,0)))) | I23: =IF($J23="","",IF(INDEX(Opportunities!$P$3:$P$502,MATCH($J23,Opportunities!$Z$3:$Z$502,0))="","",INDEX(Opportunities!$P$3:$P$502,MATCH($J23,Opportunities!$Z$3:$Z$502,0)))) | J23: =IFERROR(SMALL(Opportunities!$Z$3:$Z$502,18),"")
A24: =IF($J24="","",19) | B24: =IF($J24="","",INDEX(Opportunities!$Y$3:$Y$502,MATCH($J24,Opportunities!$Z$3:$Z$502,0))) | C24: =IF($J24="","",INDEX(Opportunities!$A$3:$A$502,MATCH($J24,Opportunities!$Z$3:$Z$502,0))) | D24: =IF($J24="","",INDEX(Opportunities!$B$3:$B$502,MATCH($J24,Opportunities!$Z$3:$Z$502,0))) | E24: =IF($J24="","",INDEX(Opportunities!$C$3:$C$502,MATCH($J24,Opportunities!$Z$3:$Z$502,0))) | F24: =IF($J24="","",IF(INDEX(Opportunities!$D$3:$D$502,MATCH($J24,Opportunities!$Z$3:$Z$502,0))="","(no owner)",INDEX(Opportunities!$D$3:$D$502,MATCH($J24,Opportunities!$Z$3:$Z$502,0)))) | G24: =IF($J24="","",IF(INDEX(Opportunities!$L$3:$L$502,MATCH($J24,Opportunities!$Z$3:$Z$502,0))="","(add a next action)",INDEX(Opportunities!$L$3:$L$502,MATCH($J24,Opportunities!$Z$3:$Z$502,0)))) | H24: =IF($J24="","",IF(INDEX(Opportunities!$M$3:$M$502,MATCH($J24,Opportunities!$Z$3:$Z$502,0))="","",INDEX(Opportunities!$M$3:$M$502,MATCH($J24,Opportunities!$Z$3:$Z$502,0)))) | I24: =IF($J24="","",IF(INDEX(Opportunities!$P$3:$P$502,MATCH($J24,Opportunities!$Z$3:$Z$502,0))="","",INDEX(Opportunities!$P$3:$P$502,MATCH($J24,Opportunities!$Z$3:$Z$502,0)))) | J24: =IFERROR(SMALL(Opportunities!$Z$3:$Z$502,19),"")
A25: =IF($J25="","",20) | B25: =IF($J25="","",INDEX(Opportunities!$Y$3:$Y$502,MATCH($J25,Opportunities!$Z$3:$Z$502,0))) | C25: =IF($J25="","",INDEX(Opportunities!$A$3:$A$502,MATCH($J25,Opportunities!$Z$3:$Z$502,0))) | D25: =IF($J25="","",INDEX(Opportunities!$B$3:$B$502,MATCH($J25,Opportunities!$Z$3:$Z$502,0))) | E25: =IF($J25="","",INDEX(Opportunities!$C$3:$C$502,MATCH($J25,Opportunities!$Z$3:$Z$502,0))) | F25: =IF($J25="","",IF(INDEX(Opportunities!$D$3:$D$502,MATCH($J25,Opportunities!$Z$3:$Z$502,0))="","(no owner)",INDEX(Opportunities!$D$3:$D$502,MATCH($J25,Opportunities!$Z$3:$Z$502,0)))) | G25: =IF($J25="","",IF(INDEX(Opportunities!$L$3:$L$502,MATCH($J25,Opportunities!$Z$3:$Z$502,0))="","(add a next action)",INDEX(Opportunities!$L$3:$L$502,MATCH($J25,Opportunities!$Z$3:$Z$502,0)))) | H25: =IF($J25="","",IF(INDEX(Opportunities!$M$3:$M$502,MATCH($J25,Opportunities!$Z$3:$Z$502,0))="","",INDEX(Opportunities!$M$3:$M$502,MATCH($J25,Opportunities!$Z$3:$Z$502,0)))) | I25: =IF($J25="","",IF(INDEX(Opportunities!$P$3:$P$502,MATCH($J25,Opportunities!$Z$3:$Z$502,0))="","",INDEX(Opportunities!$P$3:$P$502,MATCH($J25,Opportunities!$Z$3:$Z$502,0)))) | J25: =IFERROR(SMALL(Opportunities!$Z$3:$Z$502,20),"")
A26: =IF($J26="","",21) | B26: =IF($J26="","",INDEX(Opportunities!$Y$3:$Y$502,MATCH($J26,Opportunities!$Z$3:$Z$502,0))) | C26: =IF($J26="","",INDEX(Opportunities!$A$3:$A$502,MATCH($J26,Opportunities!$Z$3:$Z$502,0))) | D26: =IF($J26="","",INDEX(Opportunities!$B$3:$B$502,MATCH($J26,Opportunities!$Z$3:$Z$502,0))) | E26: =IF($J26="","",INDEX(Opportunities!$C$3:$C$502,MATCH($J26,Opportunities!$Z$3:$Z$502,0))) | F26: =IF($J26="","",IF(INDEX(Opportunities!$D$3:$D$502,MATCH($J26,Opportunities!$Z$3:$Z$502,0))="","(no owner)",INDEX(Opportunities!$D$3:$D$502,MATCH($J26,Opportunities!$Z$3:$Z$502,0)))) | G26: =IF($J26="","",IF(INDEX(Opportunities!$L$3:$L$502,MATCH($J26,Opportunities!$Z$3:$Z$502,0))="","(add a next action)",INDEX(Opportunities!$L$3:$L$502,MATCH($J26,Opportunities!$Z$3:$Z$502,0)))) | H26: =IF($J26="","",IF(INDEX(Opportunities!$M$3:$M$502,MATCH($J26,Opportunities!$Z$3:$Z$502,0))="","",INDEX(Opportunities!$M$3:$M$502,MATCH($J26,Opportunities!$Z$3:$Z$502,0)))) | I26: =IF($J26="","",IF(INDEX(Opportunities!$P$3:$P$502,MATCH($J26,Opportunities!$Z$3:$Z$502,0))="","",INDEX(Opportunities!$P$3:$P$502,MATCH($J26,Opportunities!$Z$3:$Z$502,0)))) | J26: =IFERROR(SMALL(Opportunities!$Z$3:$Z$502,21),"")
A27: =IF($J27="","",22) | B27: =IF($J27="","",INDEX(Opportunities!$Y$3:$Y$502,MATCH($J27,Opportunities!$Z$3:$Z$502,0))) | C27: =IF($J27="","",INDEX(Opportunities!$A$3:$A$502,MATCH($J27,Opportunities!$Z$3:$Z$502,0))) | D27: =IF($J27="","",INDEX(Opportunities!$B$3:$B$502,MATCH($J27,Opportunities!$Z$3:$Z$502,0))) | E27: =IF($J27="","",INDEX(Opportunities!$C$3:$C$502,MATCH($J27,Opportunities!$Z$3:$Z$502,0))) | F27: =IF($J27="","",IF(INDEX(Opportunities!$D$3:$D$502,MATCH($J27,Opportunities!$Z$3:$Z$502,0))="","(no owner)",INDEX(Opportunities!$D$3:$D$502,MATCH($J27,Opportunities!$Z$3:$Z$502,0)))) | G27: =IF($J27="","",IF(INDEX(Opportunities!$L$3:$L$502,MATCH($J27,Opportunities!$Z$3:$Z$502,0))="","(add a next action)",INDEX(Opportunities!$L$3:$L$502,MATCH($J27,Opportunities!$Z$3:$Z$502,0)))) | H27: =IF($J27="","",IF(INDEX(Opportunities!$M$3:$M$502,MATCH($J27,Opportunities!$Z$3:$Z$502,0))="","",INDEX(Opportunities!$M$3:$M$502,MATCH($J27,Opportunities!$Z$3:$Z$502,0)))) | I27: =IF($J27="","",IF(INDEX(Opportunities!$P$3:$P$502,MATCH($J27,Opportunities!$Z$3:$Z$502,0))="","",INDEX(Opportunities!$P$3:$P$502,MATCH($J27,Opportunities!$Z$3:$Z$502,0)))) | J27: =IFERROR(SMALL(Opportunities!$Z$3:$Z$502,22),"")
A28: =IF($J28="","",23) | B28: =IF($J28="","",INDEX(Opportunities!$Y$3:$Y$502,MATCH($J28,Opportunities!$Z$3:$Z$502,0))) | C28: =IF($J28="","",INDEX(Opportunities!$A$3:$A$502,MATCH($J28,Opportunities!$Z$3:$Z$502,0))) | D28: =IF($J28="","",INDEX(Opportunities!$B$3:$B$502,MATCH($J28,Opportunities!$Z$3:$Z$502,0))) | E28: =IF($J28="","",INDEX(Opportunities!$C$3:$C$502,MATCH($J28,Opportunities!$Z$3:$Z$502,0))) | F28: =IF($J28="","",IF(INDEX(Opportunities!$D$3:$D$502,MATCH($J28,Opportunities!$Z$3:$Z$502,0))="","(no owner)",INDEX(Opportunities!$D$3:$D$502,MATCH($J28,Opportunities!$Z$3:$Z$502,0)))) | G28: =IF($J28="","",IF(INDEX(Opportunities!$L$3:$L$502,MATCH($J28,Opportunities!$Z$3:$Z$502,0))="","(add a next action)",INDEX(Opportunities!$L$3:$L$502,MATCH($J28,Opportunities!$Z$3:$Z$502,0)))) | H28: =IF($J28="","",IF(INDEX(Opportunities!$M$3:$M$502,MATCH($J28,Opportunities!$Z$3:$Z$502,0))="","",INDEX(Opportunities!$M$3:$M$502,MATCH($J28,Opportunities!$Z$3:$Z$502,0)))) | I28: =IF($J28="","",IF(INDEX(Opportunities!$P$3:$P$502,MATCH($J28,Opportunities!$Z$3:$Z$502,0))="","",INDEX(Opportunities!$P$3:$P$502,MATCH($J28,Opportunities!$Z$3:$Z$502,0)))) | J28: =IFERROR(SMALL(Opportunities!$Z$3:$Z$502,23),"")
A29: =IF($J29="","",24) | B29: =IF($J29="","",INDEX(Opportunities!$Y$3:$Y$502,MATCH($J29,Opportunities!$Z$3:$Z$502,0))) | C29: =IF($J29="","",INDEX(Opportunities!$A$3:$A$502,MATCH($J29,Opportunities!$Z$3:$Z$502,0))) | D29: =IF($J29="","",INDEX(Opportunities!$B$3:$B$502,MATCH($J29,Opportunities!$Z$3:$Z$502,0))) | E29: =IF($J29="","",INDEX(Opportunities!$C$3:$C$502,MATCH($J29,Opportunities!$Z$3:$Z$502,0))) | F29: =IF($J29="","",IF(INDEX(Opportunities!$D$3:$D$502,MATCH($J29,Opportunities!$Z$3:$Z$502,0))="","(no owner)",INDEX(Opportunities!$D$3:$D$502,MATCH($J29,Opportunities!$Z$3:$Z$502,0)))) | G29: =IF($J29="","",IF(INDEX(Opportunities!$L$3:$L$502,MATCH($J29,Opportunities!$Z$3:$Z$502,0))="","(add a next action)",INDEX(Opportunities!$L$3:$L$502,MATCH($J29,Opportunities!$Z$3:$Z$502,0)))) | H29: =IF($J29="","",IF(INDEX(Opportunities!$M$3:$M$502,MATCH($J29,Opportunities!$Z$3:$Z$502,0))="","",INDEX(Opportunities!$M$3:$M$502,MATCH($J29,Opportunities!$Z$3:$Z$502,0)))) | I29: =IF($J29="","",IF(INDEX(Opportunities!$P$3:$P$502,MATCH($J29,Opportunities!$Z$3:$Z$502,0))="","",INDEX(Opportunities!$P$3:$P$502,MATCH($J29,Opportunities!$Z$3:$Z$502,0)))) | J29: =IFERROR(SMALL(Opportunities!$Z$3:$Z$502,24),"")
A30: =IF($J30="","",25) | B30: =IF($J30="","",INDEX(Opportunities!$Y$3:$Y$502,MATCH($J30,Opportunities!$Z$3:$Z$502,0))) | C30: =IF($J30="","",INDEX(Opportunities!$A$3:$A$502,MATCH($J30,Opportunities!$Z$3:$Z$502,0))) | D30: =IF($J30="","",INDEX(Opportunities!$B$3:$B$502,MATCH($J30,Opportunities!$Z$3:$Z$502,0))) | E30: =IF($J30="","",INDEX(Opportunities!$C$3:$C$502,MATCH($J30,Opportunities!$Z$3:$Z$502,0))) | F30: =IF($J30="","",IF(INDEX(Opportunities!$D$3:$D$502,MATCH($J30,Opportunities!$Z$3:$Z$502,0))="","(no owner)",INDEX(Opportunities!$D$3:$D$502,MATCH($J30,Opportunities!$Z$3:$Z$502,0)))) | G30: =IF($J30="","",IF(INDEX(Opportunities!$L$3:$L$502,MATCH($J30,Opportunities!$Z$3:$Z$502,0))="","(add a next action)",INDEX(Opportunities!$L$3:$L$502,MATCH($J30,Opportunities!$Z$3:$Z$502,0)))) | H30: =IF($J30="","",IF(INDEX(Opportunities!$M$3:$M$502,MATCH($J30,Opportunities!$Z$3:$Z$502,0))="","",INDEX(Opportunities!$M$3:$M$502,MATCH($J30,Opportunities!$Z$3:$Z$502,0)))) | I30: =IF($J30="","",IF(INDEX(Opportunities!$P$3:$P$502,MATCH($J30,Opportunities!$Z$3:$Z$502,0))="","",INDEX(Opportunities!$P$3:$P$502,MATCH($J30,Opportunities!$Z$3:$Z$502,0)))) | J30: =IFERROR(SMALL(Opportunities!$Z$3:$Z$502,25),"")
A31: =IF($J31="","",26) | B31: =IF($J31="","",INDEX(Opportunities!$Y$3:$Y$502,MATCH($J31,Opportunities!$Z$3:$Z$502,0))) | C31: =IF($J31="","",INDEX(Opportunities!$A$3:$A$502,MATCH($J31,Opportunities!$Z$3:$Z$502,0))) | D31: =IF($J31="","",INDEX(Opportunities!$B$3:$B$502,MATCH($J31,Opportunities!$Z$3:$Z$502,0))) | E31: =IF($J31="","",INDEX(Opportunities!$C$3:$C$502,MATCH($J31,Opportunities!$Z$3:$Z$502,0))) | F31: =IF($J31="","",IF(INDEX(Opportunities!$D$3:$D$502,MATCH($J31,Opportunities!$Z$3:$Z$502,0))="","(no owner)",INDEX(Opportunities!$D$3:$D$502,MATCH($J31,Opportunities!$Z$3:$Z$502,0)))) | G31: =IF($J31="","",IF(INDEX(Opportunities!$L$3:$L$502,MATCH($J31,Opportunities!$Z$3:$Z$502,0))="","(add a next action)",INDEX(Opportunities!$L$3:$L$502,MATCH($J31,Opportunities!$Z$3:$Z$502,0)))) | H31: =IF($J31="","",IF(INDEX(Opportunities!$M$3:$M$502,MATCH($J31,Opportunities!$Z$3:$Z$502,0))="","",INDEX(Opportunities!$M$3:$M$502,MATCH($J31,Opportunities!$Z$3:$Z$502,0)))) | I31: =IF($J31="","",IF(INDEX(Opportunities!$P$3:$P$502,MATCH($J31,Opportunities!$Z$3:$Z$502,0))="","",INDEX(Opportunities!$P$3:$P$502,MATCH($J31,Opportunities!$Z$3:$Z$502,0)))) | J31: =IFERROR(SMALL(Opportunities!$Z$3:$Z$502,26),"")
A32: =IF($J32="","",27) | B32: =IF($J32="","",INDEX(Opportunities!$Y$3:$Y$502,MATCH($J32,Opportunities!$Z$3:$Z$502,0))) | C32: =IF($J32="","",INDEX(Opportunities!$A$3:$A$502,MATCH($J32,Opportunities!$Z$3:$Z$502,0))) | D32: =IF($J32="","",INDEX(Opportunities!$B$3:$B$502,MATCH($J32,Opportunities!$Z$3:$Z$502,0))) | E32: =IF($J32="","",INDEX(Opportunities!$C$3:$C$502,MATCH($J32,Opportunities!$Z$3:$Z$502,0))) | F32: =IF($J32="","",IF(INDEX(Opportunities!$D$3:$D$502,MATCH($J32,Opportunities!$Z$3:$Z$502,0))="","(no owner)",INDEX(Opportunities!$D$3:$D$502,MATCH($J32,Opportunities!$Z$3:$Z$502,0)))) | G32: =IF($J32="","",IF(INDEX(Opportunities!$L$3:$L$502,MATCH($J32,Opportunities!$Z$3:$Z$502,0))="","(add a next action)",INDEX(Opportunities!$L$3:$L$502,MATCH($J32,Opportunities!$Z$3:$Z$502,0)))) | H32: =IF($J32="","",IF(INDEX(Opportunities!$M$3:$M$502,MATCH($J32,Opportunities!$Z$3:$Z$502,0))="","",INDEX(Opportunities!$M$3:$M$502,MATCH($J32,Opportunities!$Z$3:$Z$502,0)))) | I32: =IF($J32="","",IF(INDEX(Opportunities!$P$3:$P$502,MATCH($J32,Opportunities!$Z$3:$Z$502,0))="","",INDEX(Opportunities!$P$3:$P$502,MATCH($J32,Opportunities!$Z$3:$Z$502,0)))) | J32: =IFERROR(SMALL(Opportunities!$Z$3:$Z$502,27),"")
A33: =IF($J33="","",28) | B33: =IF($J33="","",INDEX(Opportunities!$Y$3:$Y$502,MATCH($J33,Opportunities!$Z$3:$Z$502,0))) | C33: =IF($J33="","",INDEX(Opportunities!$A$3:$A$502,MATCH($J33,Opportunities!$Z$3:$Z$502,0))) | D33: =IF($J33="","",INDEX(Opportunities!$B$3:$B$502,MATCH($J33,Opportunities!$Z$3:$Z$502,0))) | E33: =IF($J33="","",INDEX(Opportunities!$C$3:$C$502,MATCH($J33,Opportunities!$Z$3:$Z$502,0))) | F33: =IF($J33="","",IF(INDEX(Opportunities!$D$3:$D$502,MATCH($J33,Opportunities!$Z$3:$Z$502,0))="","(no owner)",INDEX(Opportunities!$D$3:$D$502,MATCH($J33,Opportunities!$Z$3:$Z$502,0)))) | G33: =IF($J33="","",IF(INDEX(Opportunities!$L$3:$L$502,MATCH($J33,Opportunities!$Z$3:$Z$502,0))="","(add a next action)",INDEX(Opportunities!$L$3:$L$502,MATCH($J33,Opportunities!$Z$3:$Z$502,0)))) | H33: =IF($J33="","",IF(INDEX(Opportunities!$M$3:$M$502,MATCH($J33,Opportunities!$Z$3:$Z$502,0))="","",INDEX(Opportunities!$M$3:$M$502,MATCH($J33,Opportunities!$Z$3:$Z$502,0)))) | I33: =IF($J33="","",IF(INDEX(Opportunities!$P$3:$P$502,MATCH($J33,Opportunities!$Z$3:$Z$502,0))="","",INDEX(Opportunities!$P$3:$P$502,MATCH($J33,Opportunities!$Z$3:$Z$502,0)))) | J33: =IFERROR(SMALL(Opportunities!$Z$3:$Z$502,28),"")
A34: =IF($J34="","",29) | B34: =IF($J34="","",INDEX(Opportunities!$Y$3:$Y$502,MATCH($J34,Opportunities!$Z$3:$Z$502,0))) | C34: =IF($J34="","",INDEX(Opportunities!$A$3:$A$502,MATCH($J34,Opportunities!$Z$3:$Z$502,0))) | D34: =IF($J34="","",INDEX(Opportunities!$B$3:$B$502,MATCH($J34,Opportunities!$Z$3:$Z$502,0))) | E34: =IF($J34="","",INDEX(Opportunities!$C$3:$C$502,MATCH($J34,Opportunities!$Z$3:$Z$502,0))) | F34: =IF($J34="","",IF(INDEX(Opportunities!$D$3:$D$502,MATCH($J34,Opportunities!$Z$3:$Z$502,0))="","(no owner)",INDEX(Opportunities!$D$3:$D$502,MATCH($J34,Opportunities!$Z$3:$Z$502,0)))) | G34: =IF($J34="","",IF(INDEX(Opportunities!$L$3:$L$502,MATCH($J34,Opportunities!$Z$3:$Z$502,0))="","(add a next action)",INDEX(Opportunities!$L$3:$L$502,MATCH($J34,Opportunities!$Z$3:$Z$502,0)))) | H34: =IF($J34="","",IF(INDEX(Opportunities!$M$3:$M$502,MATCH($J34,Opportunities!$Z$3:$Z$502,0))="","",INDEX(Opportunities!$M$3:$M$502,MATCH($J34,Opportunities!$Z$3:$Z$502,0)))) | I34: =IF($J34="","",IF(INDEX(Opportunities!$P$3:$P$502,MATCH($J34,Opportunities!$Z$3:$Z$502,0))="","",INDEX(Opportunities!$P$3:$P$502,MATCH($J34,Opportunities!$Z$3:$Z$502,0)))) | J34: =IFERROR(SMALL(Opportunities!$Z$3:$Z$502,29),"")
A35: =IF($J35="","",30) | B35: =IF($J35="","",INDEX(Opportunities!$Y$3:$Y$502,MATCH($J35,Opportunities!$Z$3:$Z$502,0))) | C35: =IF($J35="","",INDEX(Opportunities!$A$3:$A$502,MATCH($J35,Opportunities!$Z$3:$Z$502,0))) | D35: =IF($J35="","",INDEX(Opportunities!$B$3:$B$502,MATCH($J35,Opportunities!$Z$3:$Z$502,0))) | E35: =IF($J35="","",INDEX(Opportunities!$C$3:$C$502,MATCH($J35,Opportunities!$Z$3:$Z$502,0))) | F35: =IF($J35="","",IF(INDEX(Opportunities!$D$3:$D$502,MATCH($J35,Opportunities!$Z$3:$Z$502,0))="","(no owner)",INDEX(Opportunities!$D$3:$D$502,MATCH($J35,Opportunities!$Z$3:$Z$502,0)))) | G35: =IF($J35="","",IF(INDEX(Opportunities!$L$3:$L$502,MATCH($J35,Opportunities!$Z$3:$Z$502,0))="","(add a next action)",INDEX(Opportunities!$L$3:$L$502,MATCH($J35,Opportunities!$Z$3:$Z$502,0)))) | H35: =IF($J35="","",IF(INDEX(Opportunities!$M$3:$M$502,MATCH($J35,Opportunities!$Z$3:$Z$502,0))="","",INDEX(Opportunities!$M$3:$M$502,MATCH($J35,Opportunities!$Z$3:$Z$502,0)))) | I35: =IF($J35="","",IF(INDEX(Opportunities!$P$3:$P$502,MATCH($J35,Opportunities!$Z$3:$Z$502,0))="","",INDEX(Opportunities!$P$3:$P$502,MATCH($J35,Opportunities!$Z$3:$Z$502,0)))) | J35: =IFERROR(SMALL(Opportunities!$Z$3:$Z$502,30),"")
A37: 3–4 · Priority prospects, building paths and quick wins (from Companies)
A38: # | B38: Why it's here | C38: Company | D38: Fit | E38: Access | F38: Owner | G38: Next step | H38: Quadrant | I38: Last contact | J38: key
A39: =IF($J39="","",1) -> 1 | B39: =IF($J39="","",IF($J39<700000,"Priority: no deal yet",IF($J39<800000,"Building a path",IF($J39<900000,"Quick win for a need","Path candidate (space for one more)")))) -> Priority: no deal yet | C39: =IF($J39="","",INDEX(Companies!$A$3:$A$502,MATCH($J39,Companies!$AI$3:$AI$502,0))) -> Nordlys Logistics (example) | D39: =IF($J39="","",INDEX(Companies!$AC$3:$AC$502,MATCH($J39,Companies!$AI$3:$AI$502,0))) -> 6 | E39: =IF($J39="","",INDEX(Companies!$AD$3:$AD$502,MATCH($J39,Companies!$AI$3:$AI$502,0))) -> 2 | F39: =IF($J39="","",IF(INDEX(Companies!$F$3:$F$502,MATCH($J39,Companies!$AI$3:$AI$502,0))="","(no owner)",INDEX(Companies!$F$3:$F$502,MATCH($J39,Companies!$AI$3:$AI$502,0)))) -> A.K. (example) | G39: =IF($J39="","",IF($J39<700000,"Plan the first ask (partnership type cheat sheet) and create an opportunity",IF($J39<800000,IF(INDEX(Companies!$W$3:$W$502,MATCH($J39,Companies!$AI$3:$AI$502,0))="","(add a path action)",INDEX(Companies!$W$3:$W$502,MATCH($J39,Companies!$AI$3:$AI$502,0))),IF($J39<900000,"Need: "&INDEX(Companies!$U$3:$U$502,MATCH($J39,Companies!$AI$3:$AI$502,0)),"Decide whether to start a path")))) -> Plan the first ask (partnership type cheat sheet) and create an opportunity | H39: =IF($J39="","",INDEX(Companies!$AE$3:$AE$502,MATCH($J39,Companies!$AI$3:$AI$502,0))) -> Priority | I39: =IF($J39="","",IF(INDEX(Companies!$AF$3:$AF$502,MATCH($J39,Companies!$AI$3:$AI$502,0))="","",INDEX(Companies!$AF$3:$AF$502,MATCH($J39,Companies!$AI$3:$AI$502,0)))) | J39: =IFERROR(SMALL(Companies!$AI$3:$AI$502,1),"") -> 604200
A40: =IF($J40="","",2) -> 2 | B40: =IF($J40="","",IF($J40<700000,"Priority: no deal yet",IF($J40<800000,"Building a path",IF($J40<900000,"Quick win for a need","Path candidate (space for one more)")))) -> Building a path | C40: =IF($J40="","",INDEX(Companies!$A$3:$A$502,MATCH($J40,Companies!$AI$3:$AI$502,0))) -> MegaBrand A/S (example) | D40: =IF($J40="","",INDEX(Companies!$AC$3:$AC$502,MATCH($J40,Companies!$AI$3:$AI$502,0))) -> 7 | E40: =IF($J40="","",INDEX(Companies!$AD$3:$AD$502,MATCH($J40,Companies!$AI$3:$AI$502,0))) -> 1 | F40: =IF($J40="","",IF(INDEX(Companies!$F$3:$F$502,MATCH($J40,Companies!$AI$3:$AI$502,0))="","(no owner)",INDEX(Companies!$F$3:$F$502,MATCH($J40,Companies!$AI$3:$AI$502,0)))) -> M.S. (example) | G40: =IF($J40="","",IF($J40<700000,"Plan the first ask (partnership type cheat sheet) and create an opportunity",IF($J40<800000,IF(INDEX(Companies!$W$3:$W$502,MATCH($J40,Companies!$AI$3:$AI$502,0))="","(add a path action)",INDEX(Companies!$W$3:$W$502,MATCH($J40,Companies!$AI$3:$AI$502,0))),IF($J40<900000,"Need: "&INDEX(Companies!$U$3:$U$502,MATCH($J40,Companies!$AI$3:$AI$502,0)),"Decide whether to start a path")))) -> Ask board alumni network for an introduction | H40: =IF($J40="","",INDEX(Companies!$AE$3:$AE$502,MATCH($J40,Companies!$AI$3:$AI$502,0))) -> Build a Path | I40: =IF($J40="","",IF(INDEX(Companies!$AF$3:$AF$502,MATCH($J40,Companies!$AI$3:$AI$502,0))="","",INDEX(Companies!$AF$3:$AF$502,MATCH($J40,Companies!$AI$3:$AI$502,0)))) -> 46295 | J40: =IFERROR(SMALL(Companies!$AI$3:$AI$502,2),"") -> 700628.2
A41: =IF($J41="","",3) | B41: =IF($J41="","",IF($J41<700000,"Priority: no deal yet",IF($J41<800000,"Building a path",IF($J41<900000,"Quick win for a need","Path candidate (space for one more)")))) | C41: =IF($J41="","",INDEX(Companies!$A$3:$A$502,MATCH($J41,Companies!$AI$3:$AI$502,0))) | D41: =IF($J41="","",INDEX(Companies!$AC$3:$AC$502,MATCH($J41,Companies!$AI$3:$AI$502,0))) | E41: =IF($J41="","",INDEX(Companies!$AD$3:$AD$502,MATCH($J41,Companies!$AI$3:$AI$502,0))) | F41: =IF($J41="","",IF(INDEX(Companies!$F$3:$F$502,MATCH($J41,Companies!$AI$3:$AI$502,0))="","(no owner)",INDEX(Companies!$F$3:$F$502,MATCH($J41,Companies!$AI$3:$AI$502,0)))) | G41: =IF($J41="","",IF($J41<700000,"Plan the first ask (partnership type cheat sheet) and create an opportunity",IF($J41<800000,IF(INDEX(Companies!$W$3:$W$502,MATCH($J41,Companies!$AI$3:$AI$502,0))="","(add a path action)",INDEX(Companies!$W$3:$W$502,MATCH($J41,Companies!$AI$3:$AI$502,0))),IF($J41<900000,"Need: "&INDEX(Companies!$U$3:$U$502,MATCH($J41,Companies!$AI$3:$AI$502,0)),"Decide whether to start a path")))) | H41: =IF($J41="","",INDEX(Companies!$AE$3:$AE$502,MATCH($J41,Companies!$AI$3:$AI$502,0))) | I41: =IF($J41="","",IF(INDEX(Companies!$AF$3:$AF$502,MATCH($J41,Companies!$AI$3:$AI$502,0))="","",INDEX(Companies!$AF$3:$AF$502,MATCH($J41,Companies!$AI$3:$AI$502,0)))) | J41: =IFERROR(SMALL(Companies!$AI$3:$AI$502,3),"")
A42: =IF($J42="","",4) | B42: =IF($J42="","",IF($J42<700000,"Priority: no deal yet",IF($J42<800000,"Building a path",IF($J42<900000,"Quick win for a need","Path candidate (space for one more)")))) | C42: =IF($J42="","",INDEX(Companies!$A$3:$A$502,MATCH($J42,Companies!$AI$3:$AI$502,0))) | D42: =IF($J42="","",INDEX(Companies!$AC$3:$AC$502,MATCH($J42,Companies!$AI$3:$AI$502,0))) | E42: =IF($J42="","",INDEX(Companies!$AD$3:$AD$502,MATCH($J42,Companies!$AI$3:$AI$502,0))) | F42: =IF($J42="","",IF(INDEX(Companies!$F$3:$F$502,MATCH($J42,Companies!$AI$3:$AI$502,0))="","(no owner)",INDEX(Companies!$F$3:$F$502,MATCH($J42,Companies!$AI$3:$AI$502,0)))) | G42: =IF($J42="","",IF($J42<700000,"Plan the first ask (partnership type cheat sheet) and create an opportunity",IF($J42<800000,IF(INDEX(Companies!$W$3:$W$502,MATCH($J42,Companies!$AI$3:$AI$502,0))="","(add a path action)",INDEX(Companies!$W$3:$W$502,MATCH($J42,Companies!$AI$3:$AI$502,0))),IF($J42<900000,"Need: "&INDEX(Companies!$U$3:$U$502,MATCH($J42,Companies!$AI$3:$AI$502,0)),"Decide whether to start a path")))) | H42: =IF($J42="","",INDEX(Companies!$AE$3:$AE$502,MATCH($J42,Companies!$AI$3:$AI$502,0))) | I42: =IF($J42="","",IF(INDEX(Companies!$AF$3:$AF$502,MATCH($J42,Companies!$AI$3:$AI$502,0))="","",INDEX(Companies!$AF$3:$AF$502,MATCH($J42,Companies!$AI$3:$AI$502,0)))) | J42: =IFERROR(SMALL(Companies!$AI$3:$AI$502,4),"")
A43: =IF($J43="","",5) | B43: =IF($J43="","",IF($J43<700000,"Priority: no deal yet",IF($J43<800000,"Building a path",IF($J43<900000,"Quick win for a need","Path candidate (space for one more)")))) | C43: =IF($J43="","",INDEX(Companies!$A$3:$A$502,MATCH($J43,Companies!$AI$3:$AI$502,0))) | D43: =IF($J43="","",INDEX(Companies!$AC$3:$AC$502,MATCH($J43,Companies!$AI$3:$AI$502,0))) | E43: =IF($J43="","",INDEX(Companies!$AD$3:$AD$502,MATCH($J43,Companies!$AI$3:$AI$502,0))) | F43: =IF($J43="","",IF(INDEX(Companies!$F$3:$F$502,MATCH($J43,Companies!$AI$3:$AI$502,0))="","(no owner)",INDEX(Companies!$F$3:$F$502,MATCH($J43,Companies!$AI$3:$AI$502,0)))) | G43: =IF($J43="","",IF($J43<700000,"Plan the first ask (partnership type cheat sheet) and create an opportunity",IF($J43<800000,IF(INDEX(Companies!$W$3:$W$502,MATCH($J43,Companies!$AI$3:$AI$502,0))="","(add a path action)",INDEX(Companies!$W$3:$W$502,MATCH($J43,Companies!$AI$3:$AI$502,0))),IF($J43<900000,"Need: "&INDEX(Companies!$U$3:$U$502,MATCH($J43,Companies!$AI$3:$AI$502,0)),"Decide whether to start a path")))) | H43: =IF($J43="","",INDEX(Companies!$AE$3:$AE$502,MATCH($J43,Companies!$AI$3:$AI$502,0))) | I43: =IF($J43="","",IF(INDEX(Companies!$AF$3:$AF$502,MATCH($J43,Companies!$AI$3:$AI$502,0))="","",INDEX(Companies!$AF$3:$AF$502,MATCH($J43,Companies!$AI$3:$AI$502,0)))) | J43: =IFERROR(SMALL(Companies!$AI$3:$AI$502,5),"")
A44: =IF($J44="","",6) | B44: =IF($J44="","",IF($J44<700000,"Priority: no deal yet",IF($J44<800000,"Building a path",IF($J44<900000,"Quick win for a need","Path candidate (space for one more)")))) | C44: =IF($J44="","",INDEX(Companies!$A$3:$A$502,MATCH($J44,Companies!$AI$3:$AI$502,0))) | D44: =IF($J44="","",INDEX(Companies!$AC$3:$AC$502,MATCH($J44,Companies!$AI$3:$AI$502,0))) | E44: =IF($J44="","",INDEX(Companies!$AD$3:$AD$502,MATCH($J44,Companies!$AI$3:$AI$502,0))) | F44: =IF($J44="","",IF(INDEX(Companies!$F$3:$F$502,MATCH($J44,Companies!$AI$3:$AI$502,0))="","(no owner)",INDEX(Companies!$F$3:$F$502,MATCH($J44,Companies!$AI$3:$AI$502,0)))) | G44: =IF($J44="","",IF($J44<700000,"Plan the first ask (partnership type cheat sheet) and create an opportunity",IF($J44<800000,IF(INDEX(Companies!$W$3:$W$502,MATCH($J44,Companies!$AI$3:$AI$502,0))="","(add a path action)",INDEX(Companies!$W$3:$W$502,MATCH($J44,Companies!$AI$3:$AI$502,0))),IF($J44<900000,"Need: "&INDEX(Companies!$U$3:$U$502,MATCH($J44,Companies!$AI$3:$AI$502,0)),"Decide whether to start a path")))) | H44: =IF($J44="","",INDEX(Companies!$AE$3:$AE$502,MATCH($J44,Companies!$AI$3:$AI$502,0))) | I44: =IF($J44="","",IF(INDEX(Companies!$AF$3:$AF$502,MATCH($J44,Companies!$AI$3:$AI$502,0))="","",INDEX(Companies!$AF$3:$AF$502,MATCH($J44,Companies!$AI$3:$AI$502,0)))) | J44: =IFERROR(SMALL(Companies!$AI$3:$AI$502,6),"")
A45: =IF($J45="","",7) | B45: =IF($J45="","",IF($J45<700000,"Priority: no deal yet",IF($J45<800000,"Building a path",IF($J45<900000,"Quick win for a need","Path candidate (space for one more)")))) | C45: =IF($J45="","",INDEX(Companies!$A$3:$A$502,MATCH($J45,Companies!$AI$3:$AI$502,0))) | D45: =IF($J45="","",INDEX(Companies!$AC$3:$AC$502,MATCH($J45,Companies!$AI$3:$AI$502,0))) | E45: =IF($J45="","",INDEX(Companies!$AD$3:$AD$502,MATCH($J45,Companies!$AI$3:$AI$502,0))) | F45: =IF($J45="","",IF(INDEX(Companies!$F$3:$F$502,MATCH($J45,Companies!$AI$3:$AI$502,0))="","(no owner)",INDEX(Companies!$F$3:$F$502,MATCH($J45,Companies!$AI$3:$AI$502,0)))) | G45: =IF($J45="","",IF($J45<700000,"Plan the first ask (partnership type cheat sheet) and create an opportunity",IF($J45<800000,IF(INDEX(Companies!$W$3:$W$502,MATCH($J45,Companies!$AI$3:$AI$502,0))="","(add a path action)",INDEX(Companies!$W$3:$W$502,MATCH($J45,Companies!$AI$3:$AI$502,0))),IF($J45<900000,"Need: "&INDEX(Companies!$U$3:$U$502,MATCH($J45,Companies!$AI$3:$AI$502,0)),"Decide whether to start a path")))) | H45: =IF($J45="","",INDEX(Companies!$AE$3:$AE$502,MATCH($J45,Companies!$AI$3:$AI$502,0))) | I45: =IF($J45="","",IF(INDEX(Companies!$AF$3:$AF$502,MATCH($J45,Companies!$AI$3:$AI$502,0))="","",INDEX(Companies!$AF$3:$AF$502,MATCH($J45,Companies!$AI$3:$AI$502,0)))) | J45: =IFERROR(SMALL(Companies!$AI$3:$AI$502,7),"")
A46: =IF($J46="","",8) | B46: =IF($J46="","",IF($J46<700000,"Priority: no deal yet",IF($J46<800000,"Building a path",IF($J46<900000,"Quick win for a need","Path candidate (space for one more)")))) | C46: =IF($J46="","",INDEX(Companies!$A$3:$A$502,MATCH($J46,Companies!$AI$3:$AI$502,0))) | D46: =IF($J46="","",INDEX(Companies!$AC$3:$AC$502,MATCH($J46,Companies!$AI$3:$AI$502,0))) | E46: =IF($J46="","",INDEX(Companies!$AD$3:$AD$502,MATCH($J46,Companies!$AI$3:$AI$502,0))) | F46: =IF($J46="","",IF(INDEX(Companies!$F$3:$F$502,MATCH($J46,Companies!$AI$3:$AI$502,0))="","(no owner)",INDEX(Companies!$F$3:$F$502,MATCH($J46,Companies!$AI$3:$AI$502,0)))) | G46: =IF($J46="","",IF($J46<700000,"Plan the first ask (partnership type cheat sheet) and create an opportunity",IF($J46<800000,IF(INDEX(Companies!$W$3:$W$502,MATCH($J46,Companies!$AI$3:$AI$502,0))="","(add a path action)",INDEX(Companies!$W$3:$W$502,MATCH($J46,Companies!$AI$3:$AI$502,0))),IF($J46<900000,"Need: "&INDEX(Companies!$U$3:$U$502,MATCH($J46,Companies!$AI$3:$AI$502,0)),"Decide whether to start a path")))) | H46: =IF($J46="","",INDEX(Companies!$AE$3:$AE$502,MATCH($J46,Companies!$AI$3:$AI$502,0))) | I46: =IF($J46="","",IF(INDEX(Companies!$AF$3:$AF$502,MATCH($J46,Companies!$AI$3:$AI$502,0))="","",INDEX(Companies!$AF$3:$AF$502,MATCH($J46,Companies!$AI$3:$AI$502,0)))) | J46: =IFERROR(SMALL(Companies!$AI$3:$AI$502,8),"")
A47: =IF($J47="","",9) | B47: =IF($J47="","",IF($J47<700000,"Priority: no deal yet",IF($J47<800000,"Building a path",IF($J47<900000,"Quick win for a need","Path candidate (space for one more)")))) | C47: =IF($J47="","",INDEX(Companies!$A$3:$A$502,MATCH($J47,Companies!$AI$3:$AI$502,0))) | D47: =IF($J47="","",INDEX(Companies!$AC$3:$AC$502,MATCH($J47,Companies!$AI$3:$AI$502,0))) | E47: =IF($J47="","",INDEX(Companies!$AD$3:$AD$502,MATCH($J47,Companies!$AI$3:$AI$502,0))) | F47: =IF($J47="","",IF(INDEX(Companies!$F$3:$F$502,MATCH($J47,Companies!$AI$3:$AI$502,0))="","(no owner)",INDEX(Companies!$F$3:$F$502,MATCH($J47,Companies!$AI$3:$AI$502,0)))) | G47: =IF($J47="","",IF($J47<700000,"Plan the first ask (partnership type cheat sheet) and create an opportunity",IF($J47<800000,IF(INDEX(Companies!$W$3:$W$502,MATCH($J47,Companies!$AI$3:$AI$502,0))="","(add a path action)",INDEX(Companies!$W$3:$W$502,MATCH($J47,Companies!$AI$3:$AI$502,0))),IF($J47<900000,"Need: "&INDEX(Companies!$U$3:$U$502,MATCH($J47,Companies!$AI$3:$AI$502,0)),"Decide whether to start a path")))) | H47: =IF($J47="","",INDEX(Companies!$AE$3:$AE$502,MATCH($J47,Companies!$AI$3:$AI$502,0))) | I47: =IF($J47="","",IF(INDEX(Companies!$AF$3:$AF$502,MATCH($J47,Companies!$AI$3:$AI$502,0))="","",INDEX(Companies!$AF$3:$AF$502,MATCH($J47,Companies!$AI$3:$AI$502,0)))) | J47: =IFERROR(SMALL(Companies!$AI$3:$AI$502,9),"")
A48: =IF($J48="","",10) | B48: =IF($J48="","",IF($J48<700000,"Priority: no deal yet",IF($J48<800000,"Building a path",IF($J48<900000,"Quick win for a need","Path candidate (space for one more)")))) | C48: =IF($J48="","",INDEX(Companies!$A$3:$A$502,MATCH($J48,Companies!$AI$3:$AI$502,0))) | D48: =IF($J48="","",INDEX(Companies!$AC$3:$AC$502,MATCH($J48,Companies!$AI$3:$AI$502,0))) | E48: =IF($J48="","",INDEX(Companies!$AD$3:$AD$502,MATCH($J48,Companies!$AI$3:$AI$502,0))) | F48: =IF($J48="","",IF(INDEX(Companies!$F$3:$F$502,MATCH($J48,Companies!$AI$3:$AI$502,0))="","(no owner)",INDEX(Companies!$F$3:$F$502,MATCH($J48,Companies!$AI$3:$AI$502,0)))) | G48: =IF($J48="","",IF($J48<700000,"Plan the first ask (partnership type cheat sheet) and create an opportunity",IF($J48<800000,IF(INDEX(Companies!$W$3:$W$502,MATCH($J48,Companies!$AI$3:$AI$502,0))="","(add a path action)",INDEX(Companies!$W$3:$W$502,MATCH($J48,Companies!$AI$3:$AI$502,0))),IF($J48<900000,"Need: "&INDEX(Companies!$U$3:$U$502,MATCH($J48,Companies!$AI$3:$AI$502,0)),"Decide whether to start a path")))) | H48: =IF($J48="","",INDEX(Companies!$AE$3:$AE$502,MATCH($J48,Companies!$AI$3:$AI$502,0))) | I48: =IF($J48="","",IF(INDEX(Companies!$AF$3:$AF$502,MATCH($J48,Companies!$AI$3:$AI$502,0))="","",INDEX(Companies!$AF$3:$AF$502,MATCH($J48,Companies!$AI$3:$AI$502,0)))) | J48: =IFERROR(SMALL(Companies!$AI$3:$AI$502,10),"")
A49: =IF($J49="","",11) | B49: =IF($J49="","",IF($J49<700000,"Priority: no deal yet",IF($J49<800000,"Building a path",IF($J49<900000,"Quick win for a need","Path candidate (space for one more)")))) | C49: =IF($J49="","",INDEX(Companies!$A$3:$A$502,MATCH($J49,Companies!$AI$3:$AI$502,0))) | D49: =IF($J49="","",INDEX(Companies!$AC$3:$AC$502,MATCH($J49,Companies!$AI$3:$AI$502,0))) | E49: =IF($J49="","",INDEX(Companies!$AD$3:$AD$502,MATCH($J49,Companies!$AI$3:$AI$502,0))) | F49: =IF($J49="","",IF(INDEX(Companies!$F$3:$F$502,MATCH($J49,Companies!$AI$3:$AI$502,0))="","(no owner)",INDEX(Companies!$F$3:$F$502,MATCH($J49,Companies!$AI$3:$AI$502,0)))) | G49: =IF($J49="","",IF($J49<700000,"Plan the first ask (partnership type cheat sheet) and create an opportunity",IF($J49<800000,IF(INDEX(Companies!$W$3:$W$502,MATCH($J49,Companies!$AI$3:$AI$502,0))="","(add a path action)",INDEX(Companies!$W$3:$W$502,MATCH($J49,Companies!$AI$3:$AI$502,0))),IF($J49<900000,"Need: "&INDEX(Companies!$U$3:$U$502,MATCH($J49,Companies!$AI$3:$AI$502,0)),"Decide whether to start a path")))) | H49: =IF($J49="","",INDEX(Companies!$AE$3:$AE$502,MATCH($J49,Companies!$AI$3:$AI$502,0))) | I49: =IF($J49="","",IF(INDEX(Companies!$AF$3:$AF$502,MATCH($J49,Companies!$AI$3:$AI$502,0))="","",INDEX(Companies!$AF$3:$AF$502,MATCH($J49,Companies!$AI$3:$AI$502,0)))) | J49: =IFERROR(SMALL(Companies!$AI$3:$AI$502,11),"")
A50: =IF($J50="","",12) | B50: =IF($J50="","",IF($J50<700000,"Priority: no deal yet",IF($J50<800000,"Building a path",IF($J50<900000,"Quick win for a need","Path candidate (space for one more)")))) | C50: =IF($J50="","",INDEX(Companies!$A$3:$A$502,MATCH($J50,Companies!$AI$3:$AI$502,0))) | D50: =IF($J50="","",INDEX(Companies!$AC$3:$AC$502,MATCH($J50,Companies!$AI$3:$AI$502,0))) | E50: =IF($J50="","",INDEX(Companies!$AD$3:$AD$502,MATCH($J50,Companies!$AI$3:$AI$502,0))) | F50: =IF($J50="","",IF(INDEX(Companies!$F$3:$F$502,MATCH($J50,Companies!$AI$3:$AI$502,0))="","(no owner)",INDEX(Companies!$F$3:$F$502,MATCH($J50,Companies!$AI$3:$AI$502,0)))) | G50: =IF($J50="","",IF($J50<700000,"Plan the first ask (partnership type cheat sheet) and create an opportunity",IF($J50<800000,IF(INDEX(Companies!$W$3:$W$502,MATCH($J50,Companies!$AI$3:$AI$502,0))="","(add a path action)",INDEX(Companies!$W$3:$W$502,MATCH($J50,Companies!$AI$3:$AI$502,0))),IF($J50<900000,"Need: "&INDEX(Companies!$U$3:$U$502,MATCH($J50,Companies!$AI$3:$AI$502,0)),"Decide whether to start a path")))) | H50: =IF($J50="","",INDEX(Companies!$AE$3:$AE$502,MATCH($J50,Companies!$AI$3:$AI$502,0))) | I50: =IF($J50="","",IF(INDEX(Companies!$AF$3:$AF$502,MATCH($J50,Companies!$AI$3:$AI$502,0))="","",INDEX(Companies!$AF$3:$AF$502,MATCH($J50,Companies!$AI$3:$AI$502,0)))) | J50: =IFERROR(SMALL(Companies!$AI$3:$AI$502,12),"")
A51: =IF($J51="","",13) | B51: =IF($J51="","",IF($J51<700000,"Priority: no deal yet",IF($J51<800000,"Building a path",IF($J51<900000,"Quick win for a need","Path candidate (space for one more)")))) | C51: =IF($J51="","",INDEX(Companies!$A$3:$A$502,MATCH($J51,Companies!$AI$3:$AI$502,0))) | D51: =IF($J51="","",INDEX(Companies!$AC$3:$AC$502,MATCH($J51,Companies!$AI$3:$AI$502,0))) | E51: =IF($J51="","",INDEX(Companies!$AD$3:$AD$502,MATCH($J51,Companies!$AI$3:$AI$502,0))) | F51: =IF($J51="","",IF(INDEX(Companies!$F$3:$F$502,MATCH($J51,Companies!$AI$3:$AI$502,0))="","(no owner)",INDEX(Companies!$F$3:$F$502,MATCH($J51,Companies!$AI$3:$AI$502,0)))) | G51: =IF($J51="","",IF($J51<700000,"Plan the first ask (partnership type cheat sheet) and create an opportunity",IF($J51<800000,IF(INDEX(Companies!$W$3:$W$502,MATCH($J51,Companies!$AI$3:$AI$502,0))="","(add a path action)",INDEX(Companies!$W$3:$W$502,MATCH($J51,Companies!$AI$3:$AI$502,0))),IF($J51<900000,"Need: "&INDEX(Companies!$U$3:$U$502,MATCH($J51,Companies!$AI$3:$AI$502,0)),"Decide whether to start a path")))) | H51: =IF($J51="","",INDEX(Companies!$AE$3:$AE$502,MATCH($J51,Companies!$AI$3:$AI$502,0))) | I51: =IF($J51="","",IF(INDEX(Companies!$AF$3:$AF$502,MATCH($J51,Companies!$AI$3:$AI$502,0))="","",INDEX(Companies!$AF$3:$AF$502,MATCH($J51,Companies!$AI$3:$AI$502,0)))) | J51: =IFERROR(SMALL(Companies!$AI$3:$AI$502,13),"")
A52: =IF($J52="","",14) | B52: =IF($J52="","",IF($J52<700000,"Priority: no deal yet",IF($J52<800000,"Building a path",IF($J52<900000,"Quick win for a need","Path candidate (space for one more)")))) | C52: =IF($J52="","",INDEX(Companies!$A$3:$A$502,MATCH($J52,Companies!$AI$3:$AI$502,0))) | D52: =IF($J52="","",INDEX(Companies!$AC$3:$AC$502,MATCH($J52,Companies!$AI$3:$AI$502,0))) | E52: =IF($J52="","",INDEX(Companies!$AD$3:$AD$502,MATCH($J52,Companies!$AI$3:$AI$502,0))) | F52: =IF($J52="","",IF(INDEX(Companies!$F$3:$F$502,MATCH($J52,Companies!$AI$3:$AI$502,0))="","(no owner)",INDEX(Companies!$F$3:$F$502,MATCH($J52,Companies!$AI$3:$AI$502,0)))) | G52: =IF($J52="","",IF($J52<700000,"Plan the first ask (partnership type cheat sheet) and create an opportunity",IF($J52<800000,IF(INDEX(Companies!$W$3:$W$502,MATCH($J52,Companies!$AI$3:$AI$502,0))="","(add a path action)",INDEX(Companies!$W$3:$W$502,MATCH($J52,Companies!$AI$3:$AI$502,0))),IF($J52<900000,"Need: "&INDEX(Companies!$U$3:$U$502,MATCH($J52,Companies!$AI$3:$AI$502,0)),"Decide whether to start a path")))) | H52: =IF($J52="","",INDEX(Companies!$AE$3:$AE$502,MATCH($J52,Companies!$AI$3:$AI$502,0))) | I52: =IF($J52="","",IF(INDEX(Companies!$AF$3:$AF$502,MATCH($J52,Companies!$AI$3:$AI$502,0))="","",INDEX(Companies!$AF$3:$AF$502,MATCH($J52,Companies!$AI$3:$AI$502,0)))) | J52: =IFERROR(SMALL(Companies!$AI$3:$AI$502,14),"")
A53: =IF($J53="","",15) | B53: =IF($J53="","",IF($J53<700000,"Priority: no deal yet",IF($J53<800000,"Building a path",IF($J53<900000,"Quick win for a need","Path candidate (space for one more)")))) | C53: =IF($J53="","",INDEX(Companies!$A$3:$A$502,MATCH($J53,Companies!$AI$3:$AI$502,0))) | D53: =IF($J53="","",INDEX(Companies!$AC$3:$AC$502,MATCH($J53,Companies!$AI$3:$AI$502,0))) | E53: =IF($J53="","",INDEX(Companies!$AD$3:$AD$502,MATCH($J53,Companies!$AI$3:$AI$502,0))) | F53: =IF($J53="","",IF(INDEX(Companies!$F$3:$F$502,MATCH($J53,Companies!$AI$3:$AI$502,0))="","(no owner)",INDEX(Companies!$F$3:$F$502,MATCH($J53,Companies!$AI$3:$AI$502,0)))) | G53: =IF($J53="","",IF($J53<700000,"Plan the first ask (partnership type cheat sheet) and create an opportunity",IF($J53<800000,IF(INDEX(Companies!$W$3:$W$502,MATCH($J53,Companies!$AI$3:$AI$502,0))="","(add a path action)",INDEX(Companies!$W$3:$W$502,MATCH($J53,Companies!$AI$3:$AI$502,0))),IF($J53<900000,"Need: "&INDEX(Companies!$U$3:$U$502,MATCH($J53,Companies!$AI$3:$AI$502,0)),"Decide whether to start a path")))) | H53: =IF($J53="","",INDEX(Companies!$AE$3:$AE$502,MATCH($J53,Companies!$AI$3:$AI$502,0))) | I53: =IF($J53="","",IF(INDEX(Companies!$AF$3:$AF$502,MATCH($J53,Companies!$AI$3:$AI$502,0))="","",INDEX(Companies!$AF$3:$AF$502,MATCH($J53,Companies!$AI$3:$AI$502,0)))) | J53: =IFERROR(SMALL(Companies!$AI$3:$AI$502,15),"")
A54: =IF($J54="","",16) | B54: =IF($J54="","",IF($J54<700000,"Priority: no deal yet",IF($J54<800000,"Building a path",IF($J54<900000,"Quick win for a need","Path candidate (space for one more)")))) | C54: =IF($J54="","",INDEX(Companies!$A$3:$A$502,MATCH($J54,Companies!$AI$3:$AI$502,0))) | D54: =IF($J54="","",INDEX(Companies!$AC$3:$AC$502,MATCH($J54,Companies!$AI$3:$AI$502,0))) | E54: =IF($J54="","",INDEX(Companies!$AD$3:$AD$502,MATCH($J54,Companies!$AI$3:$AI$502,0))) | F54: =IF($J54="","",IF(INDEX(Companies!$F$3:$F$502,MATCH($J54,Companies!$AI$3:$AI$502,0))="","(no owner)",INDEX(Companies!$F$3:$F$502,MATCH($J54,Companies!$AI$3:$AI$502,0)))) | G54: =IF($J54="","",IF($J54<700000,"Plan the first ask (partnership type cheat sheet) and create an opportunity",IF($J54<800000,IF(INDEX(Companies!$W$3:$W$502,MATCH($J54,Companies!$AI$3:$AI$502,0))="","(add a path action)",INDEX(Companies!$W$3:$W$502,MATCH($J54,Companies!$AI$3:$AI$502,0))),IF($J54<900000,"Need: "&INDEX(Companies!$U$3:$U$502,MATCH($J54,Companies!$AI$3:$AI$502,0)),"Decide whether to start a path")))) | H54: =IF($J54="","",INDEX(Companies!$AE$3:$AE$502,MATCH($J54,Companies!$AI$3:$AI$502,0))) | I54: =IF($J54="","",IF(INDEX(Companies!$AF$3:$AF$502,MATCH($J54,Companies!$AI$3:$AI$502,0))="","",INDEX(Companies!$AF$3:$AF$502,MATCH($J54,Companies!$AI$3:$AI$502,0)))) | J54: =IFERROR(SMALL(Companies!$AI$3:$AI$502,16),"")
A55: =IF($J55="","",17) | B55: =IF($J55="","",IF($J55<700000,"Priority: no deal yet",IF($J55<800000,"Building a path",IF($J55<900000,"Quick win for a need","Path candidate (space for one more)")))) | C55: =IF($J55="","",INDEX(Companies!$A$3:$A$502,MATCH($J55,Companies!$AI$3:$AI$502,0))) | D55: =IF($J55="","",INDEX(Companies!$AC$3:$AC$502,MATCH($J55,Companies!$AI$3:$AI$502,0))) | E55: =IF($J55="","",INDEX(Companies!$AD$3:$AD$502,MATCH($J55,Companies!$AI$3:$AI$502,0))) | F55: =IF($J55="","",IF(INDEX(Companies!$F$3:$F$502,MATCH($J55,Companies!$AI$3:$AI$502,0))="","(no owner)",INDEX(Companies!$F$3:$F$502,MATCH($J55,Companies!$AI$3:$AI$502,0)))) | G55: =IF($J55="","",IF($J55<700000,"Plan the first ask (partnership type cheat sheet) and create an opportunity",IF($J55<800000,IF(INDEX(Companies!$W$3:$W$502,MATCH($J55,Companies!$AI$3:$AI$502,0))="","(add a path action)",INDEX(Companies!$W$3:$W$502,MATCH($J55,Companies!$AI$3:$AI$502,0))),IF($J55<900000,"Need: "&INDEX(Companies!$U$3:$U$502,MATCH($J55,Companies!$AI$3:$AI$502,0)),"Decide whether to start a path")))) | H55: =IF($J55="","",INDEX(Companies!$AE$3:$AE$502,MATCH($J55,Companies!$AI$3:$AI$502,0))) | I55: =IF($J55="","",IF(INDEX(Companies!$AF$3:$AF$502,MATCH($J55,Companies!$AI$3:$AI$502,0))="","",INDEX(Companies!$AF$3:$AF$502,MATCH($J55,Companies!$AI$3:$AI$502,0)))) | J55: =IFERROR(SMALL(Companies!$AI$3:$AI$502,17),"")
A56: =IF($J56="","",18) | B56: =IF($J56="","",IF($J56<700000,"Priority: no deal yet",IF($J56<800000,"Building a path",IF($J56<900000,"Quick win for a need","Path candidate (space for one more)")))) | C56: =IF($J56="","",INDEX(Companies!$A$3:$A$502,MATCH($J56,Companies!$AI$3:$AI$502,0))) | D56: =IF($J56="","",INDEX(Companies!$AC$3:$AC$502,MATCH($J56,Companies!$AI$3:$AI$502,0))) | E56: =IF($J56="","",INDEX(Companies!$AD$3:$AD$502,MATCH($J56,Companies!$AI$3:$AI$502,0))) | F56: =IF($J56="","",IF(INDEX(Companies!$F$3:$F$502,MATCH($J56,Companies!$AI$3:$AI$502,0))="","(no owner)",INDEX(Companies!$F$3:$F$502,MATCH($J56,Companies!$AI$3:$AI$502,0)))) | G56: =IF($J56="","",IF($J56<700000,"Plan the first ask (partnership type cheat sheet) and create an opportunity",IF($J56<800000,IF(INDEX(Companies!$W$3:$W$502,MATCH($J56,Companies!$AI$3:$AI$502,0))="","(add a path action)",INDEX(Companies!$W$3:$W$502,MATCH($J56,Companies!$AI$3:$AI$502,0))),IF($J56<900000,"Need: "&INDEX(Companies!$U$3:$U$502,MATCH($J56,Companies!$AI$3:$AI$502,0)),"Decide whether to start a path")))) | H56: =IF($J56="","",INDEX(Companies!$AE$3:$AE$502,MATCH($J56,Companies!$AI$3:$AI$502,0))) | I56: =IF($J56="","",IF(INDEX(Companies!$AF$3:$AF$502,MATCH($J56,Companies!$AI$3:$AI$502,0))="","",INDEX(Companies!$AF$3:$AF$502,MATCH($J56,Companies!$AI$3:$AI$502,0)))) | J56: =IFERROR(SMALL(Companies!$AI$3:$AI$502,18),"")
A57: =IF($J57="","",19) | B57: =IF($J57="","",IF($J57<700000,"Priority: no deal yet",IF($J57<800000,"Building a path",IF($J57<900000,"Quick win for a need","Path candidate (space for one more)")))) | C57: =IF($J57="","",INDEX(Companies!$A$3:$A$502,MATCH($J57,Companies!$AI$3:$AI$502,0))) | D57: =IF($J57="","",INDEX(Companies!$AC$3:$AC$502,MATCH($J57,Companies!$AI$3:$AI$502,0))) | E57: =IF($J57="","",INDEX(Companies!$AD$3:$AD$502,MATCH($J57,Companies!$AI$3:$AI$502,0))) | F57: =IF($J57="","",IF(INDEX(Companies!$F$3:$F$502,MATCH($J57,Companies!$AI$3:$AI$502,0))="","(no owner)",INDEX(Companies!$F$3:$F$502,MATCH($J57,Companies!$AI$3:$AI$502,0)))) | G57: =IF($J57="","",IF($J57<700000,"Plan the first ask (partnership type cheat sheet) and create an opportunity",IF($J57<800000,IF(INDEX(Companies!$W$3:$W$502,MATCH($J57,Companies!$AI$3:$AI$502,0))="","(add a path action)",INDEX(Companies!$W$3:$W$502,MATCH($J57,Companies!$AI$3:$AI$502,0))),IF($J57<900000,"Need: "&INDEX(Companies!$U$3:$U$502,MATCH($J57,Companies!$AI$3:$AI$502,0)),"Decide whether to start a path")))) | H57: =IF($J57="","",INDEX(Companies!$AE$3:$AE$502,MATCH($J57,Companies!$AI$3:$AI$502,0))) | I57: =IF($J57="","",IF(INDEX(Companies!$AF$3:$AF$502,MATCH($J57,Companies!$AI$3:$AI$502,0))="","",INDEX(Companies!$AF$3:$AF$502,MATCH($J57,Companies!$AI$3:$AI$502,0)))) | J57: =IFERROR(SMALL(Companies!$AI$3:$AI$502,19),"")
A58: =IF($J58="","",20) | B58: =IF($J58="","",IF($J58<700000,"Priority: no deal yet",IF($J58<800000,"Building a path",IF($J58<900000,"Quick win for a need","Path candidate (space for one more)")))) | C58: =IF($J58="","",INDEX(Companies!$A$3:$A$502,MATCH($J58,Companies!$AI$3:$AI$502,0))) | D58: =IF($J58="","",INDEX(Companies!$AC$3:$AC$502,MATCH($J58,Companies!$AI$3:$AI$502,0))) | E58: =IF($J58="","",INDEX(Companies!$AD$3:$AD$502,MATCH($J58,Companies!$AI$3:$AI$502,0))) | F58: =IF($J58="","",IF(INDEX(Companies!$F$3:$F$502,MATCH($J58,Companies!$AI$3:$AI$502,0))="","(no owner)",INDEX(Companies!$F$3:$F$502,MATCH($J58,Companies!$AI$3:$AI$502,0)))) | G58: =IF($J58="","",IF($J58<700000,"Plan the first ask (partnership type cheat sheet) and create an opportunity",IF($J58<800000,IF(INDEX(Companies!$W$3:$W$502,MATCH($J58,Companies!$AI$3:$AI$502,0))="","(add a path action)",INDEX(Companies!$W$3:$W$502,MATCH($J58,Companies!$AI$3:$AI$502,0))),IF($J58<900000,"Need: "&INDEX(Companies!$U$3:$U$502,MATCH($J58,Companies!$AI$3:$AI$502,0)),"Decide whether to start a path")))) | H58: =IF($J58="","",INDEX(Companies!$AE$3:$AE$502,MATCH($J58,Companies!$AI$3:$AI$502,0))) | I58: =IF($J58="","",IF(INDEX(Companies!$AF$3:$AF$502,MATCH($J58,Companies!$AI$3:$AI$502,0))="","",INDEX(Companies!$AF$3:$AF$502,MATCH($J58,Companies!$AI$3:$AI$502,0)))) | J58: =IFERROR(SMALL(Companies!$AI$3:$AI$502,20),"")
A59: =IF($J59="","",21) | B59: =IF($J59="","",IF($J59<700000,"Priority: no deal yet",IF($J59<800000,"Building a path",IF($J59<900000,"Quick win for a need","Path candidate (space for one more)")))) | C59: =IF($J59="","",INDEX(Companies!$A$3:$A$502,MATCH($J59,Companies!$AI$3:$AI$502,0))) | D59: =IF($J59="","",INDEX(Companies!$AC$3:$AC$502,MATCH($J59,Companies!$AI$3:$AI$502,0))) | E59: =IF($J59="","",INDEX(Companies!$AD$3:$AD$502,MATCH($J59,Companies!$AI$3:$AI$502,0))) | F59: =IF($J59="","",IF(INDEX(Companies!$F$3:$F$502,MATCH($J59,Companies!$AI$3:$AI$502,0))="","(no owner)",INDEX(Companies!$F$3:$F$502,MATCH($J59,Companies!$AI$3:$AI$502,0)))) | G59: =IF($J59="","",IF($J59<700000,"Plan the first ask (partnership type cheat sheet) and create an opportunity",IF($J59<800000,IF(INDEX(Companies!$W$3:$W$502,MATCH($J59,Companies!$AI$3:$AI$502,0))="","(add a path action)",INDEX(Companies!$W$3:$W$502,MATCH($J59,Companies!$AI$3:$AI$502,0))),IF($J59<900000,"Need: "&INDEX(Companies!$U$3:$U$502,MATCH($J59,Companies!$AI$3:$AI$502,0)),"Decide whether to start a path")))) | H59: =IF($J59="","",INDEX(Companies!$AE$3:$AE$502,MATCH($J59,Companies!$AI$3:$AI$502,0))) | I59: =IF($J59="","",IF(INDEX(Companies!$AF$3:$AF$502,MATCH($J59,Companies!$AI$3:$AI$502,0))="","",INDEX(Companies!$AF$3:$AF$502,MATCH($J59,Companies!$AI$3:$AI$502,0)))) | J59: =IFERROR(SMALL(Companies!$AI$3:$AI$502,21),"")
A60: =IF($J60="","",22) | B60: =IF($J60="","",IF($J60<700000,"Priority: no deal yet",IF($J60<800000,"Building a path",IF($J60<900000,"Quick win for a need","Path candidate (space for one more)")))) | C60: =IF($J60="","",INDEX(Companies!$A$3:$A$502,MATCH($J60,Companies!$AI$3:$AI$502,0))) | D60: =IF($J60="","",INDEX(Companies!$AC$3:$AC$502,MATCH($J60,Companies!$AI$3:$AI$502,0))) | E60: =IF($J60="","",INDEX(Companies!$AD$3:$AD$502,MATCH($J60,Companies!$AI$3:$AI$502,0))) | F60: =IF($J60="","",IF(INDEX(Companies!$F$3:$F$502,MATCH($J60,Companies!$AI$3:$AI$502,0))="","(no owner)",INDEX(Companies!$F$3:$F$502,MATCH($J60,Companies!$AI$3:$AI$502,0)))) | G60: =IF($J60="","",IF($J60<700000,"Plan the first ask (partnership type cheat sheet) and create an opportunity",IF($J60<800000,IF(INDEX(Companies!$W$3:$W$502,MATCH($J60,Companies!$AI$3:$AI$502,0))="","(add a path action)",INDEX(Companies!$W$3:$W$502,MATCH($J60,Companies!$AI$3:$AI$502,0))),IF($J60<900000,"Need: "&INDEX(Companies!$U$3:$U$502,MATCH($J60,Companies!$AI$3:$AI$502,0)),"Decide whether to start a path")))) | H60: =IF($J60="","",INDEX(Companies!$AE$3:$AE$502,MATCH($J60,Companies!$AI$3:$AI$502,0))) | I60: =IF($J60="","",IF(INDEX(Companies!$AF$3:$AF$502,MATCH($J60,Companies!$AI$3:$AI$502,0))="","",INDEX(Companies!$AF$3:$AF$502,MATCH($J60,Companies!$AI$3:$AI$502,0)))) | J60: =IFERROR(SMALL(Companies!$AI$3:$AI$502,22),"")
A61: =IF($J61="","",23) | B61: =IF($J61="","",IF($J61<700000,"Priority: no deal yet",IF($J61<800000,"Building a path",IF($J61<900000,"Quick win for a need","Path candidate (space for one more)")))) | C61: =IF($J61="","",INDEX(Companies!$A$3:$A$502,MATCH($J61,Companies!$AI$3:$AI$502,0))) | D61: =IF($J61="","",INDEX(Companies!$AC$3:$AC$502,MATCH($J61,Companies!$AI$3:$AI$502,0))) | E61: =IF($J61="","",INDEX(Companies!$AD$3:$AD$502,MATCH($J61,Companies!$AI$3:$AI$502,0))) | F61: =IF($J61="","",IF(INDEX(Companies!$F$3:$F$502,MATCH($J61,Companies!$AI$3:$AI$502,0))="","(no owner)",INDEX(Companies!$F$3:$F$502,MATCH($J61,Companies!$AI$3:$AI$502,0)))) | G61: =IF($J61="","",IF($J61<700000,"Plan the first ask (partnership type cheat sheet) and create an opportunity",IF($J61<800000,IF(INDEX(Companies!$W$3:$W$502,MATCH($J61,Companies!$AI$3:$AI$502,0))="","(add a path action)",INDEX(Companies!$W$3:$W$502,MATCH($J61,Companies!$AI$3:$AI$502,0))),IF($J61<900000,"Need: "&INDEX(Companies!$U$3:$U$502,MATCH($J61,Companies!$AI$3:$AI$502,0)),"Decide whether to start a path")))) | H61: =IF($J61="","",INDEX(Companies!$AE$3:$AE$502,MATCH($J61,Companies!$AI$3:$AI$502,0))) | I61: =IF($J61="","",IF(INDEX(Companies!$AF$3:$AF$502,MATCH($J61,Companies!$AI$3:$AI$502,0))="","",INDEX(Companies!$AF$3:$AF$502,MATCH($J61,Companies!$AI$3:$AI$502,0)))) | J61: =IFERROR(SMALL(Companies!$AI$3:$AI$502,23),"")
A62: =IF($J62="","",24) | B62: =IF($J62="","",IF($J62<700000,"Priority: no deal yet",IF($J62<800000,"Building a path",IF($J62<900000,"Quick win for a need","Path candidate (space for one more)")))) | C62: =IF($J62="","",INDEX(Companies!$A$3:$A$502,MATCH($J62,Companies!$AI$3:$AI$502,0))) | D62: =IF($J62="","",INDEX(Companies!$AC$3:$AC$502,MATCH($J62,Companies!$AI$3:$AI$502,0))) | E62: =IF($J62="","",INDEX(Companies!$AD$3:$AD$502,MATCH($J62,Companies!$AI$3:$AI$502,0))) | F62: =IF($J62="","",IF(INDEX(Companies!$F$3:$F$502,MATCH($J62,Companies!$AI$3:$AI$502,0))="","(no owner)",INDEX(Companies!$F$3:$F$502,MATCH($J62,Companies!$AI$3:$AI$502,0)))) | G62: =IF($J62="","",IF($J62<700000,"Plan the first ask (partnership type cheat sheet) and create an opportunity",IF($J62<800000,IF(INDEX(Companies!$W$3:$W$502,MATCH($J62,Companies!$AI$3:$AI$502,0))="","(add a path action)",INDEX(Companies!$W$3:$W$502,MATCH($J62,Companies!$AI$3:$AI$502,0))),IF($J62<900000,"Need: "&INDEX(Companies!$U$3:$U$502,MATCH($J62,Companies!$AI$3:$AI$502,0)),"Decide whether to start a path")))) | H62: =IF($J62="","",INDEX(Companies!$AE$3:$AE$502,MATCH($J62,Companies!$AI$3:$AI$502,0))) | I62: =IF($J62="","",IF(INDEX(Companies!$AF$3:$AF$502,MATCH($J62,Companies!$AI$3:$AI$502,0))="","",INDEX(Companies!$AF$3:$AF$502,MATCH($J62,Companies!$AI$3:$AI$502,0)))) | J62: =IFERROR(SMALL(Companies!$AI$3:$AI$502,24),"")
A63: =IF($J63="","",25) | B63: =IF($J63="","",IF($J63<700000,"Priority: no deal yet",IF($J63<800000,"Building a path",IF($J63<900000,"Quick win for a need","Path candidate (space for one more)")))) | C63: =IF($J63="","",INDEX(Companies!$A$3:$A$502,MATCH($J63,Companies!$AI$3:$AI$502,0))) | D63: =IF($J63="","",INDEX(Companies!$AC$3:$AC$502,MATCH($J63,Companies!$AI$3:$AI$502,0))) | E63: =IF($J63="","",INDEX(Companies!$AD$3:$AD$502,MATCH($J63,Companies!$AI$3:$AI$502,0))) | F63: =IF($J63="","",IF(INDEX(Companies!$F$3:$F$502,MATCH($J63,Companies!$AI$3:$AI$502,0))="","(no owner)",INDEX(Companies!$F$3:$F$502,MATCH($J63,Companies!$AI$3:$AI$502,0)))) | G63: =IF($J63="","",IF($J63<700000,"Plan the first ask (partnership type cheat sheet) and create an opportunity",IF($J63<800000,IF(INDEX(Companies!$W$3:$W$502,MATCH($J63,Companies!$AI$3:$AI$502,0))="","(add a path action)",INDEX(Companies!$W$3:$W$502,MATCH($J63,Companies!$AI$3:$AI$502,0))),IF($J63<900000,"Need: "&INDEX(Companies!$U$3:$U$502,MATCH($J63,Companies!$AI$3:$AI$502,0)),"Decide whether to start a path")))) | H63: =IF($J63="","",INDEX(Companies!$AE$3:$AE$502,MATCH($J63,Companies!$AI$3:$AI$502,0))) | I63: =IF($J63="","",IF(INDEX(Companies!$AF$3:$AF$502,MATCH($J63,Companies!$AI$3:$AI$502,0))="","",INDEX(Companies!$AF$3:$AF$502,MATCH($J63,Companies!$AI$3:$AI$502,0)))) | J63: =IFERROR(SMALL(Companies!$AI$3:$AI$502,25),"")
A64: =IF($J64="","",26) | B64: =IF($J64="","",IF($J64<700000,"Priority: no deal yet",IF($J64<800000,"Building a path",IF($J64<900000,"Quick win for a need","Path candidate (space for one more)")))) | C64: =IF($J64="","",INDEX(Companies!$A$3:$A$502,MATCH($J64,Companies!$AI$3:$AI$502,0))) | D64: =IF($J64="","",INDEX(Companies!$AC$3:$AC$502,MATCH($J64,Companies!$AI$3:$AI$502,0))) | E64: =IF($J64="","",INDEX(Companies!$AD$3:$AD$502,MATCH($J64,Companies!$AI$3:$AI$502,0))) | F64: =IF($J64="","",IF(INDEX(Companies!$F$3:$F$502,MATCH($J64,Companies!$AI$3:$AI$502,0))="","(no owner)",INDEX(Companies!$F$3:$F$502,MATCH($J64,Companies!$AI$3:$AI$502,0)))) | G64: =IF($J64="","",IF($J64<700000,"Plan the first ask (partnership type cheat sheet) and create an opportunity",IF($J64<800000,IF(INDEX(Companies!$W$3:$W$502,MATCH($J64,Companies!$AI$3:$AI$502,0))="","(add a path action)",INDEX(Companies!$W$3:$W$502,MATCH($J64,Companies!$AI$3:$AI$502,0))),IF($J64<900000,"Need: "&INDEX(Companies!$U$3:$U$502,MATCH($J64,Companies!$AI$3:$AI$502,0)),"Decide whether to start a path")))) | H64: =IF($J64="","",INDEX(Companies!$AE$3:$AE$502,MATCH($J64,Companies!$AI$3:$AI$502,0))) | I64: =IF($J64="","",IF(INDEX(Companies!$AF$3:$AF$502,MATCH($J64,Companies!$AI$3:$AI$502,0))="","",INDEX(Companies!$AF$3:$AF$502,MATCH($J64,Companies!$AI$3:$AI$502,0)))) | J64: =IFERROR(SMALL(Companies!$AI$3:$AI$502,26),"")
A65: =IF($J65="","",27) | B65: =IF($J65="","",IF($J65<700000,"Priority: no deal yet",IF($J65<800000,"Building a path",IF($J65<900000,"Quick win for a need","Path candidate (space for one more)")))) | C65: =IF($J65="","",INDEX(Companies!$A$3:$A$502,MATCH($J65,Companies!$AI$3:$AI$502,0))) | D65: =IF($J65="","",INDEX(Companies!$AC$3:$AC$502,MATCH($J65,Companies!$AI$3:$AI$502,0))) | E65: =IF($J65="","",INDEX(Companies!$AD$3:$AD$502,MATCH($J65,Companies!$AI$3:$AI$502,0))) | F65: =IF($J65="","",IF(INDEX(Companies!$F$3:$F$502,MATCH($J65,Companies!$AI$3:$AI$502,0))="","(no owner)",INDEX(Companies!$F$3:$F$502,MATCH($J65,Companies!$AI$3:$AI$502,0)))) | G65: =IF($J65="","",IF($J65<700000,"Plan the first ask (partnership type cheat sheet) and create an opportunity",IF($J65<800000,IF(INDEX(Companies!$W$3:$W$502,MATCH($J65,Companies!$AI$3:$AI$502,0))="","(add a path action)",INDEX(Companies!$W$3:$W$502,MATCH($J65,Companies!$AI$3:$AI$502,0))),IF($J65<900000,"Need: "&INDEX(Companies!$U$3:$U$502,MATCH($J65,Companies!$AI$3:$AI$502,0)),"Decide whether to start a path")))) | H65: =IF($J65="","",INDEX(Companies!$AE$3:$AE$502,MATCH($J65,Companies!$AI$3:$AI$502,0))) | I65: =IF($J65="","",IF(INDEX(Companies!$AF$3:$AF$502,MATCH($J65,Companies!$AI$3:$AI$502,0))="","",INDEX(Companies!$AF$3:$AF$502,MATCH($J65,Companies!$AI$3:$AI$502,0)))) | J65: =IFERROR(SMALL(Companies!$AI$3:$AI$502,27),"")
A66: =IF($J66="","",28) | B66: =IF($J66="","",IF($J66<700000,"Priority: no deal yet",IF($J66<800000,"Building a path",IF($J66<900000,"Quick win for a need","Path candidate (space for one more)")))) | C66: =IF($J66="","",INDEX(Companies!$A$3:$A$502,MATCH($J66,Companies!$AI$3:$AI$502,0))) | D66: =IF($J66="","",INDEX(Companies!$AC$3:$AC$502,MATCH($J66,Companies!$AI$3:$AI$502,0))) | E66: =IF($J66="","",INDEX(Companies!$AD$3:$AD$502,MATCH($J66,Companies!$AI$3:$AI$502,0))) | F66: =IF($J66="","",IF(INDEX(Companies!$F$3:$F$502,MATCH($J66,Companies!$AI$3:$AI$502,0))="","(no owner)",INDEX(Companies!$F$3:$F$502,MATCH($J66,Companies!$AI$3:$AI$502,0)))) | G66: =IF($J66="","",IF($J66<700000,"Plan the first ask (partnership type cheat sheet) and create an opportunity",IF($J66<800000,IF(INDEX(Companies!$W$3:$W$502,MATCH($J66,Companies!$AI$3:$AI$502,0))="","(add a path action)",INDEX(Companies!$W$3:$W$502,MATCH($J66,Companies!$AI$3:$AI$502,0))),IF($J66<900000,"Need: "&INDEX(Companies!$U$3:$U$502,MATCH($J66,Companies!$AI$3:$AI$502,0)),"Decide whether to start a path")))) | H66: =IF($J66="","",INDEX(Companies!$AE$3:$AE$502,MATCH($J66,Companies!$AI$3:$AI$502,0))) | I66: =IF($J66="","",IF(INDEX(Companies!$AF$3:$AF$502,MATCH($J66,Companies!$AI$3:$AI$502,0))="","",INDEX(Companies!$AF$3:$AF$502,MATCH($J66,Companies!$AI$3:$AI$502,0)))) | J66: =IFERROR(SMALL(Companies!$AI$3:$AI$502,28),"")
A67: =IF($J67="","",29) | B67: =IF($J67="","",IF($J67<700000,"Priority: no deal yet",IF($J67<800000,"Building a path",IF($J67<900000,"Quick win for a need","Path candidate (space for one more)")))) | C67: =IF($J67="","",INDEX(Companies!$A$3:$A$502,MATCH($J67,Companies!$AI$3:$AI$502,0))) | D67: =IF($J67="","",INDEX(Companies!$AC$3:$AC$502,MATCH($J67,Companies!$AI$3:$AI$502,0))) | E67: =IF($J67="","",INDEX(Companies!$AD$3:$AD$502,MATCH($J67,Companies!$AI$3:$AI$502,0))) | F67: =IF($J67="","",IF(INDEX(Companies!$F$3:$F$502,MATCH($J67,Companies!$AI$3:$AI$502,0))="","(no owner)",INDEX(Companies!$F$3:$F$502,MATCH($J67,Companies!$AI$3:$AI$502,0)))) | G67: =IF($J67="","",IF($J67<700000,"Plan the first ask (partnership type cheat sheet) and create an opportunity",IF($J67<800000,IF(INDEX(Companies!$W$3:$W$502,MATCH($J67,Companies!$AI$3:$AI$502,0))="","(add a path action)",INDEX(Companies!$W$3:$W$502,MATCH($J67,Companies!$AI$3:$AI$502,0))),IF($J67<900000,"Need: "&INDEX(Companies!$U$3:$U$502,MATCH($J67,Companies!$AI$3:$AI$502,0)),"Decide whether to start a path")))) | H67: =IF($J67="","",INDEX(Companies!$AE$3:$AE$502,MATCH($J67,Companies!$AI$3:$AI$502,0))) | I67: =IF($J67="","",IF(INDEX(Companies!$AF$3:$AF$502,MATCH($J67,Companies!$AI$3:$AI$502,0))="","",INDEX(Companies!$AF$3:$AF$502,MATCH($J67,Companies!$AI$3:$AI$502,0)))) | J67: =IFERROR(SMALL(Companies!$AI$3:$AI$502,29),"")
A68: =IF($J68="","",30) | B68: =IF($J68="","",IF($J68<700000,"Priority: no deal yet",IF($J68<800000,"Building a path",IF($J68<900000,"Quick win for a need","Path candidate (space for one more)")))) | C68: =IF($J68="","",INDEX(Companies!$A$3:$A$502,MATCH($J68,Companies!$AI$3:$AI$502,0))) | D68: =IF($J68="","",INDEX(Companies!$AC$3:$AC$502,MATCH($J68,Companies!$AI$3:$AI$502,0))) | E68: =IF($J68="","",INDEX(Companies!$AD$3:$AD$502,MATCH($J68,Companies!$AI$3:$AI$502,0))) | F68: =IF($J68="","",IF(INDEX(Companies!$F$3:$F$502,MATCH($J68,Companies!$AI$3:$AI$502,0))="","(no owner)",INDEX(Companies!$F$3:$F$502,MATCH($J68,Companies!$AI$3:$AI$502,0)))) | G68: =IF($J68="","",IF($J68<700000,"Plan the first ask (partnership type cheat sheet) and create an opportunity",IF($J68<800000,IF(INDEX(Companies!$W$3:$W$502,MATCH($J68,Companies!$AI$3:$AI$502,0))="","(add a path action)",INDEX(Companies!$W$3:$W$502,MATCH($J68,Companies!$AI$3:$AI$502,0))),IF($J68<900000,"Need: "&INDEX(Companies!$U$3:$U$502,MATCH($J68,Companies!$AI$3:$AI$502,0)),"Decide whether to start a path")))) | H68: =IF($J68="","",INDEX(Companies!$AE$3:$AE$502,MATCH($J68,Companies!$AI$3:$AI$502,0))) | I68: =IF($J68="","",IF(INDEX(Companies!$AF$3:$AF$502,MATCH($J68,Companies!$AI$3:$AI$502,0))="","",INDEX(Companies!$AF$3:$AF$502,MATCH($J68,Companies!$AI$3:$AI$502,0)))) | J68: =IFERROR(SMALL(Companies!$AI$3:$AI$502,30),"")

Sheet Dashboard
A1: Dashboard
A2: ="Semester: "&S_SemesterLabel&" ("&TEXT(S_SemStart,"d mmm yyyy")&" – "&TEXT(S_SemEnd,"d mmm yyyy")&") · counts and recorded amounts only" -> Semester: Example semester (13 Aug 2026 – 9 Feb 2027) · counts and recorded amounts only
A4: Matrix (companies) | D4: Won this semester
A5: Priority | B5: =COUNTIF(Companies!$AE$3:$AE$502,"Priority") -> 2 | D5: Company | E5: Type | F5: Agreed (DKK) | G5: Non-cash / in-kind | H5: Renewal date | I5: Satisfaction
A6: Build a Path | B6: =COUNTIF(Companies!$AE$3:$AE$502,"Build a Path") -> 1 | D6: =IF(COUNT(Opportunities!$AB$3:$AB$502)<1,"",IFERROR(IF(INDEX(Opportunities!$A$3:$A$502,MATCH(IFERROR(SMALL(Opportunities!$AB$3:$AB$502,1),""),Opportunities!$AB$3:$AB$502,0))="","",INDEX(Opportunities!$A$3:$A$502,MATCH(IFERROR(SMALL(Opportunities!$AB$3:$AB$502,1),""),Opportunities!$AB$3:$AB$502,0))),"")) -> Søby Foods (example) | E6: =IF(COUNT(Opportunities!$AB$3:$AB$502)<1,"",IFERROR(IF(INDEX(Opportunities!$B$3:$B$502,MATCH(IFERROR(SMALL(Opportunities!$AB$3:$AB$502,1),""),Opportunities!$AB$3:$AB$502,0))="","",INDEX(Opportunities!$B$3:$B$502,MATCH(IFERROR(SMALL(Opportunities!$AB$3:$AB$502,1),""),Opportunities!$AB$3:$AB$502,0))),"")) -> Event sponsor | F6: =IF(COUNT(Opportunities!$AB$3:$AB$502)<1,"",IFERROR(IF(INDEX(Opportunities!$J$3:$J$502,MATCH(IFERROR(SMALL(Opportunities!$AB$3:$AB$502,1),""),Opportunities!$AB$3:$AB$502,0))="","",INDEX(Opportunities!$J$3:$J$502,MATCH(IFERROR(SMALL(Opportunities!$AB$3:$AB$502,1),""),Opportunities!$AB$3:$AB$502,0))),"")) -> 8000 | G6: =IF(COUNT(Opportunities!$AB$3:$AB$502)<1,"",IFERROR(IF(INDEX(Opportunities!$K$3:$K$502,MATCH(IFERROR(SMALL(Opportunities!$AB$3:$AB$502,1),""),Opportunities!$AB$3:$AB$502,0))="","",INDEX(Opportunities!$K$3:$K$502,MATCH(IFERROR(SMALL(Opportunities!$AB$3:$AB$502,1),""),Opportunities!$AB$3:$AB$502,0))),"")) | H6: =IF(COUNT(Opportunities!$AB$3:$AB$502)<1,"",IFERROR(IF(INDEX(Opportunities!$P$3:$P$502,MATCH(IFERROR(SMALL(Opportunities!$AB$3:$AB$502,1),""),Opportunities!$AB$3:$AB$502,0))="","",INDEX(Opportunities!$P$3:$P$502,MATCH(IFERROR(SMALL(Opportunities!$AB$3:$AB$502,1),""),Opportunities!$AB$3:$AB$502,0))),"")) -> 46607 | I6: =IF(COUNT(Opportunities!$AB$3:$AB$502)<1,"",IFERROR(IF(INDEX(Opportunities!$Q$3:$Q$502,MATCH(IFERROR(SMALL(Opportunities!$AB$3:$AB$502,1),""),Opportunities!$AB$3:$AB$502,0))="","",INDEX(Opportunities!$Q$3:$Q$502,MATCH(IFERROR(SMALL(Opportunities!$AB$3:$AB$502,1),""),Opportunities!$AB$3:$AB$502,0))),"")) -> Unknown
A7: Quick Win | B7: =COUNTIF(Companies!$AE$3:$AE$502,"Quick Win") -> 2 | D7: =IF(COUNT(Opportunities!$AB$3:$AB$502)<2,"",IFERROR(IF(INDEX(Opportunities!$A$3:$A$502,MATCH(IFERROR(SMALL(Opportunities!$AB$3:$AB$502,2),""),Opportunities!$AB$3:$AB$502,0))="","",INDEX(Opportunities!$A$3:$A$502,MATCH(IFERROR(SMALL(Opportunities!$AB$3:$AB$502,2),""),Opportunities!$AB$3:$AB$502,0))),"")) | E7: =IF(COUNT(Opportunities!$AB$3:$AB$502)<2,"",IFERROR(IF(INDEX(Opportunities!$B$3:$B$502,MATCH(IFERROR(SMALL(Opportunities!$AB$3:$AB$502,2),""),Opportunities!$AB$3:$AB$502,0))="","",INDEX(Opportunities!$B$3:$B$502,MATCH(IFERROR(SMALL(Opportunities!$AB$3:$AB$502,2),""),Opportunities!$AB$3:$AB$502,0))),"")) | F7: =IF(COUNT(Opportunities!$AB$3:$AB$502)<2,"",IFERROR(IF(INDEX(Opportunities!$J$3:$J$502,MATCH(IFERROR(SMALL(Opportunities!$AB$3:$AB$502,2),""),Opportunities!$AB$3:$AB$502,0))="","",INDEX(Opportunities!$J$3:$J$502,MATCH(IFERROR(SMALL(Opportunities!$AB$3:$AB$502,2),""),Opportunities!$AB$3:$AB$502,0))),"")) | G7: =IF(COUNT(Opportunities!$AB$3:$AB$502)<2,"",IFERROR(IF(INDEX(Opportunities!$K$3:$K$502,MATCH(IFERROR(SMALL(Opportunities!$AB$3:$AB$502,2),""),Opportunities!$AB$3:$AB$502,0))="","",INDEX(Opportunities!$K$3:$K$502,MATCH(IFERROR(SMALL(Opportunities!$AB$3:$AB$502,2),""),Opportunities!$AB$3:$AB$502,0))),"")) | H7: =IF(COUNT(Opportunities!$AB$3:$AB$502)<2,"",IFERROR(IF(INDEX(Opportunities!$P$3:$P$502,MATCH(IFERROR(SMALL(Opportunities!$AB$3:$AB$502,2),""),Opportunities!$AB$3:$AB$502,0))="","",INDEX(Opportunities!$P$3:$P$502,MATCH(IFERROR(SMALL(Opportunities!$AB$3:$AB$502,2),""),Opportunities!$AB$3:$AB$502,0))),"")) | I7: =IF(COUNT(Opportunities!$AB$3:$AB$502)<2,"",IFERROR(IF(INDEX(Opportunities!$Q$3:$Q$502,MATCH(IFERROR(SMALL(Opportunities!$AB$3:$AB$502,2),""),Opportunities!$AB$3:$AB$502,0))="","",INDEX(Opportunities!$Q$3:$Q$502,MATCH(IFERROR(SMALL(Opportunities!$AB$3:$AB$502,2),""),Opportunities!$AB$3:$AB$502,0))),""))
A8: Low Priority | B8: =COUNTIF(Companies!$AE$3:$AE$502,"Low Priority") -> 1 | D8: =IF(COUNT(Opportunities!$AB$3:$AB$502)<3,"",IFERROR(IF(INDEX(Opportunities!$A$3:$A$502,MATCH(IFERROR(SMALL(Opportunities!$AB$3:$AB$502,3),""),Opportunities!$AB$3:$AB$502,0))="","",INDEX(Opportunities!$A$3:$A$502,MATCH(IFERROR(SMALL(Opportunities!$AB$3:$AB$502,3),""),Opportunities!$AB$3:$AB$502,0))),"")) | E8: =IF(COUNT(Opportunities!$AB$3:$AB$502)<3,"",IFERROR(IF(INDEX(Opportunities!$B$3:$B$502,MATCH(IFERROR(SMALL(Opportunities!$AB$3:$AB$502,3),""),Opportunities!$AB$3:$AB$502,0))="","",INDEX(Opportunities!$B$3:$B$502,MATCH(IFERROR(SMALL(Opportunities!$AB$3:$AB$502,3),""),Opportunities!$AB$3:$AB$502,0))),"")) | F8: =IF(COUNT(Opportunities!$AB$3:$AB$502)<3,"",IFERROR(IF(INDEX(Opportunities!$J$3:$J$502,MATCH(IFERROR(SMALL(Opportunities!$AB$3:$AB$502,3),""),Opportunities!$AB$3:$AB$502,0))="","",INDEX(Opportunities!$J$3:$J$502,MATCH(IFERROR(SMALL(Opportunities!$AB$3:$AB$502,3),""),Opportunities!$AB$3:$AB$502,0))),"")) | G8: =IF(COUNT(Opportunities!$AB$3:$AB$502)<3,"",IFERROR(IF(INDEX(Opportunities!$K$3:$K$502,MATCH(IFERROR(SMALL(Opportunities!$AB$3:$AB$502,3),""),Opportunities!$AB$3:$AB$502,0))="","",INDEX(Opportunities!$K$3:$K$502,MATCH(IFERROR(SMALL(Opportunities!$AB$3:$AB$502,3),""),Opportunities!$AB$3:$AB$502,0))),"")) | H8: =IF(COUNT(Opportunities!$AB$3:$AB$502)<3,"",IFERROR(IF(INDEX(Opportunities!$P$3:$P$502,MATCH(IFERROR(SMALL(Opportunities!$AB$3:$AB$502,3),""),Opportunities!$AB$3:$AB$502,0))="","",INDEX(Opportunities!$P$3:$P$502,MATCH(IFERROR(SMALL(Opportunities!$AB$3:$AB$502,3),""),Opportunities!$AB$3:$AB$502,0))),"")) | I8: =IF(COUNT(Opportunities!$AB$3:$AB$502)<3,"",IFERROR(IF(INDEX(Opportunities!$Q$3:$Q$502,MATCH(IFERROR(SMALL(Opportunities!$AB$3:$AB$502,3),""),Opportunities!$AB$3:$AB$502,0))="","",INDEX(Opportunities!$Q$3:$Q$502,MATCH(IFERROR(SMALL(Opportunities!$AB$3:$AB$502,3),""),Opportunities!$AB$3:$AB$502,0))),""))
A9: Research | B9: =COUNTIF(Companies!$AE$3:$AE$502,"Research") -> 2 | D9: =IF(COUNT(Opportunities!$AB$3:$AB$502)<4,"",IFERROR(IF(INDEX(Opportunities!$A$3:$A$502,MATCH(IFERROR(SMALL(Opportunities!$AB$3:$AB$502,4),""),Opportunities!$AB$3:$AB$502,0))="","",INDEX(Opportunities!$A$3:$A$502,MATCH(IFERROR(SMALL(Opportunities!$AB$3:$AB$502,4),""),Opportunities!$AB$3:$AB$502,0))),"")) | E9: =IF(COUNT(Opportunities!$AB$3:$AB$502)<4,"",IFERROR(IF(INDEX(Opportunities!$B$3:$B$502,MATCH(IFERROR(SMALL(Opportunities!$AB$3:$AB$502,4),""),Opportunities!$AB$3:$AB$502,0))="","",INDEX(Opportunities!$B$3:$B$502,MATCH(IFERROR(SMALL(Opportunities!$AB$3:$AB$502,4),""),Opportunities!$AB$3:$AB$502,0))),"")) | F9: =IF(COUNT(Opportunities!$AB$3:$AB$502)<4,"",IFERROR(IF(INDEX(Opportunities!$J$3:$J$502,MATCH(IFERROR(SMALL(Opportunities!$AB$3:$AB$502,4),""),Opportunities!$AB$3:$AB$502,0))="","",INDEX(Opportunities!$J$3:$J$502,MATCH(IFERROR(SMALL(Opportunities!$AB$3:$AB$502,4),""),Opportunities!$AB$3:$AB$502,0))),"")) | G9: =IF(COUNT(Opportunities!$AB$3:$AB$502)<4,"",IFERROR(IF(INDEX(Opportunities!$K$3:$K$502,MATCH(IFERROR(SMALL(Opportunities!$AB$3:$AB$502,4),""),Opportunities!$AB$3:$AB$502,0))="","",INDEX(Opportunities!$K$3:$K$502,MATCH(IFERROR(SMALL(Opportunities!$AB$3:$AB$502,4),""),Opportunities!$AB$3:$AB$502,0))),"")) | H9: =IF(COUNT(Opportunities!$AB$3:$AB$502)<4,"",IFERROR(IF(INDEX(Opportunities!$P$3:$P$502,MATCH(IFERROR(SMALL(Opportunities!$AB$3:$AB$502,4),""),Opportunities!$AB$3:$AB$502,0))="","",INDEX(Opportunities!$P$3:$P$502,MATCH(IFERROR(SMALL(Opportunities!$AB$3:$AB$502,4),""),Opportunities!$AB$3:$AB$502,0))),"")) | I9: =IF(COUNT(Opportunities!$AB$3:$AB$502)<4,"",IFERROR(IF(INDEX(Opportunities!$Q$3:$Q$502,MATCH(IFERROR(SMALL(Opportunities!$AB$3:$AB$502,4),""),Opportunities!$AB$3:$AB$502,0))="","",INDEX(Opportunities!$Q$3:$Q$502,MATCH(IFERROR(SMALL(Opportunities!$AB$3:$AB$502,4),""),Opportunities!$AB$3:$AB$502,0))),""))
A10: Paths in progress (max) | B10: =COUNTIF(Companies!$V$3:$V$502,"Yes")&" / "&S_PathCap -> 1 / 5 | D10: =IF(COUNT(Opportunities!$AB$3:$AB$502)<5,"",IFERROR(IF(INDEX(Opportunities!$A$3:$A$502,MATCH(IFERROR(SMALL(Opportunities!$AB$3:$AB$502,5),""),Opportunities!$AB$3:$AB$502,0))="","",INDEX(Opportunities!$A$3:$A$502,MATCH(IFERROR(SMALL(Opportunities!$AB$3:$AB$502,5),""),Opportunities!$AB$3:$AB$502,0))),"")) | E10: =IF(COUNT(Opportunities!$AB$3:$AB$502)<5,"",IFERROR(IF(INDEX(Opportunities!$B$3:$B$502,MATCH(IFERROR(SMALL(Opportunities!$AB$3:$AB$502,5),""),Opportunities!$AB$3:$AB$502,0))="","",INDEX(Opportunities!$B$3:$B$502,MATCH(IFERROR(SMALL(Opportunities!$AB$3:$AB$502,5),""),Opportunities!$AB$3:$AB$502,0))),"")) | F10: =IF(COUNT(Opportunities!$AB$3:$AB$502)<5,"",IFERROR(IF(INDEX(Opportunities!$J$3:$J$502,MATCH(IFERROR(SMALL(Opportunities!$AB$3:$AB$502,5),""),Opportunities!$AB$3:$AB$502,0))="","",INDEX(Opportunities!$J$3:$J$502,MATCH(IFERROR(SMALL(Opportunities!$AB$3:$AB$502,5),""),Opportunities!$AB$3:$AB$502,0))),"")) | G10: =IF(COUNT(Opportunities!$AB$3:$AB$502)<5,"",IFERROR(IF(INDEX(Opportunities!$K$3:$K$502,MATCH(IFERROR(SMALL(Opportunities!$AB$3:$AB$502,5),""),Opportunities!$AB$3:$AB$502,0))="","",INDEX(Opportunities!$K$3:$K$502,MATCH(IFERROR(SMALL(Opportunities!$AB$3:$AB$502,5),""),Opportunities!$AB$3:$AB$502,0))),"")) | H10: =IF(COUNT(Opportunities!$AB$3:$AB$502)<5,"",IFERROR(IF(INDEX(Opportunities!$P$3:$P$502,MATCH(IFERROR(SMALL(Opportunities!$AB$3:$AB$502,5),""),Opportunities!$AB$3:$AB$502,0))="","",INDEX(Opportunities!$P$3:$P$502,MATCH(IFERROR(SMALL(Opportunities!$AB$3:$AB$502,5),""),Opportunities!$AB$3:$AB$502,0))),"")) | I10: =IF(COUNT(Opportunities!$AB$3:$AB$502)<5,"",IFERROR(IF(INDEX(Opportunities!$Q$3:$Q$502,MATCH(IFERROR(SMALL(Opportunities!$AB$3:$AB$502,5),""),Opportunities!$AB$3:$AB$502,0))="","",INDEX(Opportunities!$Q$3:$Q$502,MATCH(IFERROR(SMALL(Opportunities!$AB$3:$AB$502,5),""),Opportunities!$AB$3:$AB$502,0))),""))
D11: =IF(COUNT(Opportunities!$AB$3:$AB$502)<6,"",IFERROR(IF(INDEX(Opportunities!$A$3:$A$502,MATCH(IFERROR(SMALL(Opportunities!$AB$3:$AB$502,6),""),Opportunities!$AB$3:$AB$502,0))="","",INDEX(Opportunities!$A$3:$A$502,MATCH(IFERROR(SMALL(Opportunities!$AB$3:$AB$502,6),""),Opportunities!$AB$3:$AB$502,0))),"")) | E11: =IF(COUNT(Opportunities!$AB$3:$AB$502)<6,"",IFERROR(IF(INDEX(Opportunities!$B$3:$B$502,MATCH(IFERROR(SMALL(Opportunities!$AB$3:$AB$502,6),""),Opportunities!$AB$3:$AB$502,0))="","",INDEX(Opportunities!$B$3:$B$502,MATCH(IFERROR(SMALL(Opportunities!$AB$3:$AB$502,6),""),Opportunities!$AB$3:$AB$502,0))),"")) | F11: =IF(COUNT(Opportunities!$AB$3:$AB$502)<6,"",IFERROR(IF(INDEX(Opportunities!$J$3:$J$502,MATCH(IFERROR(SMALL(Opportunities!$AB$3:$AB$502,6),""),Opportunities!$AB$3:$AB$502,0))="","",INDEX(Opportunities!$J$3:$J$502,MATCH(IFERROR(SMALL(Opportunities!$AB$3:$AB$502,6),""),Opportunities!$AB$3:$AB$502,0))),"")) | G11: =IF(COUNT(Opportunities!$AB$3:$AB$502)<6,"",IFERROR(IF(INDEX(Opportunities!$K$3:$K$502,MATCH(IFERROR(SMALL(Opportunities!$AB$3:$AB$502,6),""),Opportunities!$AB$3:$AB$502,0))="","",INDEX(Opportunities!$K$3:$K$502,MATCH(IFERROR(SMALL(Opportunities!$AB$3:$AB$502,6),""),Opportunities!$AB$3:$AB$502,0))),"")) | H11: =IF(COUNT(Opportunities!$AB$3:$AB$502)<6,"",IFERROR(IF(INDEX(Opportunities!$P$3:$P$502,MATCH(IFERROR(SMALL(Opportunities!$AB$3:$AB$502,6),""),Opportunities!$AB$3:$AB$502,0))="","",INDEX(Opportunities!$P$3:$P$502,MATCH(IFERROR(SMALL(Opportunities!$AB$3:$AB$502,6),""),Opportunities!$AB$3:$AB$502,0))),"")) | I11: =IF(COUNT(Opportunities!$AB$3:$AB$502)<6,"",IFERROR(IF(INDEX(Opportunities!$Q$3:$Q$502,MATCH(IFERROR(SMALL(Opportunities!$AB$3:$AB$502,6),""),Opportunities!$AB$3:$AB$502,0))="","",INDEX(Opportunities!$Q$3:$Q$502,MATCH(IFERROR(SMALL(Opportunities!$AB$3:$AB$502,6),""),Opportunities!$AB$3:$AB$502,0))),""))
A12: Semester money (recorded amounts only, no estimates) | D12: =IF(COUNT(Opportunities!$AB$3:$AB$502)<7,"",IFERROR(IF(INDEX(Opportunities!$A$3:$A$502,MATCH(IFERROR(SMALL(Opportunities!$AB$3:$AB$502,7),""),Opportunities!$AB$3:$AB$502,0))="","",INDEX(Opportunities!$A$3:$A$502,MATCH(IFERROR(SMALL(Opportunities!$AB$3:$AB$502,7),""),Opportunities!$AB$3:$AB$502,0))),"")) | E12: =IF(COUNT(Opportunities!$AB$3:$AB$502)<7,"",IFERROR(IF(INDEX(Opportunities!$B$3:$B$502,MATCH(IFERROR(SMALL(Opportunities!$AB$3:$AB$502,7),""),Opportunities!$AB$3:$AB$502,0))="","",INDEX(Opportunities!$B$3:$B$502,MATCH(IFERROR(SMALL(Opportunities!$AB$3:$AB$502,7),""),Opportunities!$AB$3:$AB$502,0))),"")) | F12: =IF(COUNT(Opportunities!$AB$3:$AB$502)<7,"",IFERROR(IF(INDEX(Opportunities!$J$3:$J$502,MATCH(IFERROR(SMALL(Opportunities!$AB$3:$AB$502,7),""),Opportunities!$AB$3:$AB$502,0))="","",INDEX(Opportunities!$J$3:$J$502,MATCH(IFERROR(SMALL(Opportunities!$AB$3:$AB$502,7),""),Opportunities!$AB$3:$AB$502,0))),"")) | G12: =IF(COUNT(Opportunities!$AB$3:$AB$502)<7,"",IFERROR(IF(INDEX(Opportunities!$K$3:$K$502,MATCH(IFERROR(SMALL(Opportunities!$AB$3:$AB$502,7),""),Opportunities!$AB$3:$AB$502,0))="","",INDEX(Opportunities!$K$3:$K$502,MATCH(IFERROR(SMALL(Opportunities!$AB$3:$AB$502,7),""),Opportunities!$AB$3:$AB$502,0))),"")) | H12: =IF(COUNT(Opportunities!$AB$3:$AB$502)<7,"",IFERROR(IF(INDEX(Opportunities!$P$3:$P$502,MATCH(IFERROR(SMALL(Opportunities!$AB$3:$AB$502,7),""),Opportunities!$AB$3:$AB$502,0))="","",INDEX(Opportunities!$P$3:$P$502,MATCH(IFERROR(SMALL(Opportunities!$AB$3:$AB$502,7),""),Opportunities!$AB$3:$AB$502,0))),"")) | I12: =IF(COUNT(Opportunities!$AB$3:$AB$502)<7,"",IFERROR(IF(INDEX(Opportunities!$Q$3:$Q$502,MATCH(IFERROR(SMALL(Opportunities!$AB$3:$AB$502,7),""),Opportunities!$AB$3:$AB$502,0))="","",INDEX(Opportunities!$Q$3:$Q$502,MATCH(IFERROR(SMALL(Opportunities!$AB$3:$AB$502,7),""),Opportunities!$AB$3:$AB$502,0))),""))
A13: Cash won this semester | B13: =SUMIFS(Opportunities!$J$3:$J$502,Opportunities!$C$3:$C$502,"Won",Opportunities!$G$3:$G$502,"Cash",Opportunities!$V$3:$V$502,">="&S_SemStart,Opportunities!$V$3:$V$502,"<="&S_SemEnd) -> 8000 | D13: =IF(COUNT(Opportunities!$AB$3:$AB$502)<8,"",IFERROR(IF(INDEX(Opportunities!$A$3:$A$502,MATCH(IFERROR(SMALL(Opportunities!$AB$3:$AB$502,8),""),Opportunities!$AB$3:$AB$502,0))="","",INDEX(Opportunities!$A$3:$A$502,MATCH(IFERROR(SMALL(Opportunities!$AB$3:$AB$502,8),""),Opportunities!$AB$3:$AB$502,0))),"")) | E13: =IF(COUNT(Opportunities!$AB$3:$AB$502)<8,"",IFERROR(IF(INDEX(Opportunities!$B$3:$B$502,MATCH(IFERROR(SMALL(Opportunities!$AB$3:$AB$502,8),""),Opportunities!$AB$3:$AB$502,0))="","",INDEX(Opportunities!$B$3:$B$502,MATCH(IFERROR(SMALL(Opportunities!$AB$3:$AB$502,8),""),Opportunities!$AB$3:$AB$502,0))),"")) | F13: =IF(COUNT(Opportunities!$AB$3:$AB$502)<8,"",IFERROR(IF(INDEX(Opportunities!$J$3:$J$502,MATCH(IFERROR(SMALL(Opportunities!$AB$3:$AB$502,8),""),Opportunities!$AB$3:$AB$502,0))="","",INDEX(Opportunities!$J$3:$J$502,MATCH(IFERROR(SMALL(Opportunities!$AB$3:$AB$502,8),""),Opportunities!$AB$3:$AB$502,0))),"")) | G13: =IF(COUNT(Opportunities!$AB$3:$AB$502)<8,"",IFERROR(IF(INDEX(Opportunities!$K$3:$K$502,MATCH(IFERROR(SMALL(Opportunities!$AB$3:$AB$502,8),""),Opportunities!$AB$3:$AB$502,0))="","",INDEX(Opportunities!$K$3:$K$502,MATCH(IFERROR(SMALL(Opportunities!$AB$3:$AB$502,8),""),Opportunities!$AB$3:$AB$502,0))),"")) | H13: =IF(COUNT(Opportunities!$AB$3:$AB$502)<8,"",IFERROR(IF(INDEX(Opportunities!$P$3:$P$502,MATCH(IFERROR(SMALL(Opportunities!$AB$3:$AB$502,8),""),Opportunities!$AB$3:$AB$502,0))="","",INDEX(Opportunities!$P$3:$P$502,MATCH(IFERROR(SMALL(Opportunities!$AB$3:$AB$502,8),""),Opportunities!$AB$3:$AB$502,0))),"")) | I13: =IF(COUNT(Opportunities!$AB$3:$AB$502)<8,"",IFERROR(IF(INDEX(Opportunities!$Q$3:$Q$502,MATCH(IFERROR(SMALL(Opportunities!$AB$3:$AB$502,8),""),Opportunities!$AB$3:$AB$502,0))="","",INDEX(Opportunities!$Q$3:$Q$502,MATCH(IFERROR(SMALL(Opportunities!$AB$3:$AB$502,8),""),Opportunities!$AB$3:$AB$502,0))),""))
A14: Semester target | B14: =S_Target -> 120000 | D14: =IF(COUNT(Opportunities!$AB$3:$AB$502)<9,"",IFERROR(IF(INDEX(Opportunities!$A$3:$A$502,MATCH(IFERROR(SMALL(Opportunities!$AB$3:$AB$502,9),""),Opportunities!$AB$3:$AB$502,0))="","",INDEX(Opportunities!$A$3:$A$502,MATCH(IFERROR(SMALL(Opportunities!$AB$3:$AB$502,9),""),Opportunities!$AB$3:$AB$502,0))),"")) | E14: =IF(COUNT(Opportunities!$AB$3:$AB$502)<9,"",IFERROR(IF(INDEX(Opportunities!$B$3:$B$502,MATCH(IFERROR(SMALL(Opportunities!$AB$3:$AB$502,9),""),Opportunities!$AB$3:$AB$502,0))="","",INDEX(Opportunities!$B$3:$B$502,MATCH(IFERROR(SMALL(Opportunities!$AB$3:$AB$502,9),""),Opportunities!$AB$3:$AB$502,0))),"")) | F14: =IF(COUNT(Opportunities!$AB$3:$AB$502)<9,"",IFERROR(IF(INDEX(Opportunities!$J$3:$J$502,MATCH(IFERROR(SMALL(Opportunities!$AB$3:$AB$502,9),""),Opportunities!$AB$3:$AB$502,0))="","",INDEX(Opportunities!$J$3:$J$502,MATCH(IFERROR(SMALL(Opportunities!$AB$3:$AB$502,9),""),Opportunities!$AB$3:$AB$502,0))),"")) | G14: =IF(COUNT(Opportunities!$AB$3:$AB$502)<9,"",IFERROR(IF(INDEX(Opportunities!$K$3:$K$502,MATCH(IFERROR(SMALL(Opportunities!$AB$3:$AB$502,9),""),Opportunities!$AB$3:$AB$502,0))="","",INDEX(Opportunities!$K$3:$K$502,MATCH(IFERROR(SMALL(Opportunities!$AB$3:$AB$502,9),""),Opportunities!$AB$3:$AB$502,0))),"")) | H14: =IF(COUNT(Opportunities!$AB$3:$AB$502)<9,"",IFERROR(IF(INDEX(Opportunities!$P$3:$P$502,MATCH(IFERROR(SMALL(Opportunities!$AB$3:$AB$502,9),""),Opportunities!$AB$3:$AB$502,0))="","",INDEX(Opportunities!$P$3:$P$502,MATCH(IFERROR(SMALL(Opportunities!$AB$3:$AB$502,9),""),Opportunities!$AB$3:$AB$502,0))),"")) | I14: =IF(COUNT(Opportunities!$AB$3:$AB$502)<9,"",IFERROR(IF(INDEX(Opportunities!$Q$3:$Q$502,MATCH(IFERROR(SMALL(Opportunities!$AB$3:$AB$502,9),""),Opportunities!$AB$3:$AB$502,0))="","",INDEX(Opportunities!$Q$3:$Q$502,MATCH(IFERROR(SMALL(Opportunities!$AB$3:$AB$502,9),""),Opportunities!$AB$3:$AB$502,0))),""))
A15: Progress | B15: =IF(S_Target=0,"",REPT("█",ROUND(MIN(B13/S_Target,1)*20,0))&REPT("░",20-ROUND(MIN(B13/S_Target,1)*20,0))&" "&TEXT(B13/S_Target,"0%")) -> █░░░░░░░░░░░░░░░░░░░ 7% | D15: =IF(COUNT(Opportunities!$AB$3:$AB$502)<10,"",IFERROR(IF(INDEX(Opportunities!$A$3:$A$502,MATCH(IFERROR(SMALL(Opportunities!$AB$3:$AB$502,10),""),Opportunities!$AB$3:$AB$502,0))="","",INDEX(Opportunities!$A$3:$A$502,MATCH(IFERROR(SMALL(Opportunities!$AB$3:$AB$502,10),""),Opportunities!$AB$3:$AB$502,0))),"")) | E15: =IF(COUNT(Opportunities!$AB$3:$AB$502)<10,"",IFERROR(IF(INDEX(Opportunities!$B$3:$B$502,MATCH(IFERROR(SMALL(Opportunities!$AB$3:$AB$502,10),""),Opportunities!$AB$3:$AB$502,0))="","",INDEX(Opportunities!$B$3:$B$502,MATCH(IFERROR(SMALL(Opportunities!$AB$3:$AB$502,10),""),Opportunities!$AB$3:$AB$502,0))),"")) | F15: =IF(COUNT(Opportunities!$AB$3:$AB$502)<10,"",IFERROR(IF(INDEX(Opportunities!$J$3:$J$502,MATCH(IFERROR(SMALL(Opportunities!$AB$3:$AB$502,10),""),Opportunities!$AB$3:$AB$502,0))="","",INDEX(Opportunities!$J$3:$J$502,MATCH(IFERROR(SMALL(Opportunities!$AB$3:$AB$502,10),""),Opportunities!$AB$3:$AB$502,0))),"")) | G15: =IF(COUNT(Opportunities!$AB$3:$AB$502)<10,"",IFERROR(IF(INDEX(Opportunities!$K$3:$K$502,MATCH(IFERROR(SMALL(Opportunities!$AB$3:$AB$502,10),""),Opportunities!$AB$3:$AB$502,0))="","",INDEX(Opportunities!$K$3:$K$502,MATCH(IFERROR(SMALL(Opportunities!$AB$3:$AB$502,10),""),Opportunities!$AB$3:$AB$502,0))),"")) | H15: =IF(COUNT(Opportunities!$AB$3:$AB$502)<10,"",IFERROR(IF(INDEX(Opportunities!$P$3:$P$502,MATCH(IFERROR(SMALL(Opportunities!$AB$3:$AB$502,10),""),Opportunities!$AB$3:$AB$502,0))="","",INDEX(Opportunities!$P$3:$P$502,MATCH(IFERROR(SMALL(Opportunities!$AB$3:$AB$502,10),""),Opportunities!$AB$3:$AB$502,0))),"")) | I15: =IF(COUNT(Opportunities!$AB$3:$AB$502)<10,"",IFERROR(IF(INDEX(Opportunities!$Q$3:$Q$502,MATCH(IFERROR(SMALL(Opportunities!$AB$3:$AB$502,10),""),Opportunities!$AB$3:$AB$502,0))="","",INDEX(Opportunities!$Q$3:$Q$502,MATCH(IFERROR(SMALL(Opportunities!$AB$3:$AB$502,10),""),Opportunities!$AB$3:$AB$502,0))),""))
A16: Cash proposed, not committed (Proposal sent + Negotiation) | B16: =SUMIFS(Opportunities!$I$3:$I$502,Opportunities!$C$3:$C$502,"Proposal sent",Opportunities!$G$3:$G$502,"Cash")+SUMIFS(Opportunities!$I$3:$I$502,Opportunities!$C$3:$C$502,"Negotiation",Opportunities!$G$3:$G$502,"Cash") -> 0
D17: Lost this semester
A18: Open opportunities by stage | D18: Company | E18: Type | F18: Lost reason | G18: Closed on
A19: Planned | B19: =COUNTIF(Opportunities!$C$3:$C$502,"Planned") -> 0 | D19: =IF(COUNT(Opportunities!$AC$3:$AC$502)<1,"",IFERROR(IF(INDEX(Opportunities!$A$3:$A$502,MATCH(IFERROR(SMALL(Opportunities!$AC$3:$AC$502,1),""),Opportunities!$AC$3:$AC$502,0))="","",INDEX(Opportunities!$A$3:$A$502,MATCH(IFERROR(SMALL(Opportunities!$AC$3:$AC$502,1),""),Opportunities!$AC$3:$AC$502,0))),"")) -> Strandvej Studio (example) | E19: =IF(COUNT(Opportunities!$AC$3:$AC$502)<1,"",IFERROR(IF(INDEX(Opportunities!$B$3:$B$502,MATCH(IFERROR(SMALL(Opportunities!$AC$3:$AC$502,1),""),Opportunities!$AC$3:$AC$502,0))="","",INDEX(Opportunities!$B$3:$B$502,MATCH(IFERROR(SMALL(Opportunities!$AC$3:$AC$502,1),""),Opportunities!$AC$3:$AC$502,0))),"")) -> Event sponsor | F19: =IF(COUNT(Opportunities!$AC$3:$AC$502)<1,"",IFERROR(IF(INDEX(Opportunities!$S$3:$S$502,MATCH(IFERROR(SMALL(Opportunities!$AC$3:$AC$502,1),""),Opportunities!$AC$3:$AC$502,0))="","",INDEX(Opportunities!$S$3:$S$502,MATCH(IFERROR(SMALL(Opportunities!$AC$3:$AC$502,1),""),Opportunities!$AC$3:$AC$502,0))),"")) -> No budget | G19: =IF(COUNT(Opportunities!$AC$3:$AC$502)<1,"",IFERROR(IF(INDEX(Opportunities!$V$3:$V$502,MATCH(IFERROR(SMALL(Opportunities!$AC$3:$AC$502,1),""),Opportunities!$AC$3:$AC$502,0))="","",INDEX(Opportunities!$V$3:$V$502,MATCH(IFERROR(SMALL(Opportunities!$AC$3:$AC$502,1),""),Opportunities!$AC$3:$AC$502,0))),"")) -> 46282
A20: Contacted | B20: =COUNTIF(Opportunities!$C$3:$C$502,"Contacted") -> 1 | D20: =IF(COUNT(Opportunities!$AC$3:$AC$502)<2,"",IFERROR(IF(INDEX(Opportunities!$A$3:$A$502,MATCH(IFERROR(SMALL(Opportunities!$AC$3:$AC$502,2),""),Opportunities!$AC$3:$AC$502,0))="","",INDEX(Opportunities!$A$3:$A$502,MATCH(IFERROR(SMALL(Opportunities!$AC$3:$AC$502,2),""),Opportunities!$AC$3:$AC$502,0))),"")) | E20: =IF(COUNT(Opportunities!$AC$3:$AC$502)<2,"",IFERROR(IF(INDEX(Opportunities!$B$3:$B$502,MATCH(IFERROR(SMALL(Opportunities!$AC$3:$AC$502,2),""),Opportunities!$AC$3:$AC$502,0))="","",INDEX(Opportunities!$B$3:$B$502,MATCH(IFERROR(SMALL(Opportunities!$AC$3:$AC$502,2),""),Opportunities!$AC$3:$AC$502,0))),"")) | F20: =IF(COUNT(Opportunities!$AC$3:$AC$502)<2,"",IFERROR(IF(INDEX(Opportunities!$S$3:$S$502,MATCH(IFERROR(SMALL(Opportunities!$AC$3:$AC$502,2),""),Opportunities!$AC$3:$AC$502,0))="","",INDEX(Opportunities!$S$3:$S$502,MATCH(IFERROR(SMALL(Opportunities!$AC$3:$AC$502,2),""),Opportunities!$AC$3:$AC$502,0))),"")) | G20: =IF(COUNT(Opportunities!$AC$3:$AC$502)<2,"",IFERROR(IF(INDEX(Opportunities!$V$3:$V$502,MATCH(IFERROR(SMALL(Opportunities!$AC$3:$AC$502,2),""),Opportunities!$AC$3:$AC$502,0))="","",INDEX(Opportunities!$V$3:$V$502,MATCH(IFERROR(SMALL(Opportunities!$AC$3:$AC$502,2),""),Opportunities!$AC$3:$AC$502,0))),""))
A21: Meeting | B21: =COUNTIF(Opportunities!$C$3:$C$502,"Meeting") -> 1 | D21: =IF(COUNT(Opportunities!$AC$3:$AC$502)<3,"",IFERROR(IF(INDEX(Opportunities!$A$3:$A$502,MATCH(IFERROR(SMALL(Opportunities!$AC$3:$AC$502,3),""),Opportunities!$AC$3:$AC$502,0))="","",INDEX(Opportunities!$A$3:$A$502,MATCH(IFERROR(SMALL(Opportunities!$AC$3:$AC$502,3),""),Opportunities!$AC$3:$AC$502,0))),"")) | E21: =IF(COUNT(Opportunities!$AC$3:$AC$502)<3,"",IFERROR(IF(INDEX(Opportunities!$B$3:$B$502,MATCH(IFERROR(SMALL(Opportunities!$AC$3:$AC$502,3),""),Opportunities!$AC$3:$AC$502,0))="","",INDEX(Opportunities!$B$3:$B$502,MATCH(IFERROR(SMALL(Opportunities!$AC$3:$AC$502,3),""),Opportunities!$AC$3:$AC$502,0))),"")) | F21: =IF(COUNT(Opportunities!$AC$3:$AC$502)<3,"",IFERROR(IF(INDEX(Opportunities!$S$3:$S$502,MATCH(IFERROR(SMALL(Opportunities!$AC$3:$AC$502,3),""),Opportunities!$AC$3:$AC$502,0))="","",INDEX(Opportunities!$S$3:$S$502,MATCH(IFERROR(SMALL(Opportunities!$AC$3:$AC$502,3),""),Opportunities!$AC$3:$AC$502,0))),"")) | G21: =IF(COUNT(Opportunities!$AC$3:$AC$502)<3,"",IFERROR(IF(INDEX(Opportunities!$V$3:$V$502,MATCH(IFERROR(SMALL(Opportunities!$AC$3:$AC$502,3),""),Opportunities!$AC$3:$AC$502,0))="","",INDEX(Opportunities!$V$3:$V$502,MATCH(IFERROR(SMALL(Opportunities!$AC$3:$AC$502,3),""),Opportunities!$AC$3:$AC$502,0))),""))
A22: Proposal sent | B22: =COUNTIF(Opportunities!$C$3:$C$502,"Proposal sent") -> 1 | D22: =IF(COUNT(Opportunities!$AC$3:$AC$502)<4,"",IFERROR(IF(INDEX(Opportunities!$A$3:$A$502,MATCH(IFERROR(SMALL(Opportunities!$AC$3:$AC$502,4),""),Opportunities!$AC$3:$AC$502,0))="","",INDEX(Opportunities!$A$3:$A$502,MATCH(IFERROR(SMALL(Opportunities!$AC$3:$AC$502,4),""),Opportunities!$AC$3:$AC$502,0))),"")) | E22: =IF(COUNT(Opportunities!$AC$3:$AC$502)<4,"",IFERROR(IF(INDEX(Opportunities!$B$3:$B$502,MATCH(IFERROR(SMALL(Opportunities!$AC$3:$AC$502,4),""),Opportunities!$AC$3:$AC$502,0))="","",INDEX(Opportunities!$B$3:$B$502,MATCH(IFERROR(SMALL(Opportunities!$AC$3:$AC$502,4),""),Opportunities!$AC$3:$AC$502,0))),"")) | F22: =IF(COUNT(Opportunities!$AC$3:$AC$502)<4,"",IFERROR(IF(INDEX(Opportunities!$S$3:$S$502,MATCH(IFERROR(SMALL(Opportunities!$AC$3:$AC$502,4),""),Opportunities!$AC$3:$AC$502,0))="","",INDEX(Opportunities!$S$3:$S$502,MATCH(IFERROR(SMALL(Opportunities!$AC$3:$AC$502,4),""),Opportunities!$AC$3:$AC$502,0))),"")) | G22: =IF(COUNT(Opportunities!$AC$3:$AC$502)<4,"",IFERROR(IF(INDEX(Opportunities!$V$3:$V$502,MATCH(IFERROR(SMALL(Opportunities!$AC$3:$AC$502,4),""),Opportunities!$AC$3:$AC$502,0))="","",INDEX(Opportunities!$V$3:$V$502,MATCH(IFERROR(SMALL(Opportunities!$AC$3:$AC$502,4),""),Opportunities!$AC$3:$AC$502,0))),""))
A23: Negotiation | B23: =COUNTIF(Opportunities!$C$3:$C$502,"Negotiation") -> 0 | D23: =IF(COUNT(Opportunities!$AC$3:$AC$502)<5,"",IFERROR(IF(INDEX(Opportunities!$A$3:$A$502,MATCH(IFERROR(SMALL(Opportunities!$AC$3:$AC$502,5),""),Opportunities!$AC$3:$AC$502,0))="","",INDEX(Opportunities!$A$3:$A$502,MATCH(IFERROR(SMALL(Opportunities!$AC$3:$AC$502,5),""),Opportunities!$AC$3:$AC$502,0))),"")) | E23: =IF(COUNT(Opportunities!$AC$3:$AC$502)<5,"",IFERROR(IF(INDEX(Opportunities!$B$3:$B$502,MATCH(IFERROR(SMALL(Opportunities!$AC$3:$AC$502,5),""),Opportunities!$AC$3:$AC$502,0))="","",INDEX(Opportunities!$B$3:$B$502,MATCH(IFERROR(SMALL(Opportunities!$AC$3:$AC$502,5),""),Opportunities!$AC$3:$AC$502,0))),"")) | F23: =IF(COUNT(Opportunities!$AC$3:$AC$502)<5,"",IFERROR(IF(INDEX(Opportunities!$S$3:$S$502,MATCH(IFERROR(SMALL(Opportunities!$AC$3:$AC$502,5),""),Opportunities!$AC$3:$AC$502,0))="","",INDEX(Opportunities!$S$3:$S$502,MATCH(IFERROR(SMALL(Opportunities!$AC$3:$AC$502,5),""),Opportunities!$AC$3:$AC$502,0))),"")) | G23: =IF(COUNT(Opportunities!$AC$3:$AC$502)<5,"",IFERROR(IF(INDEX(Opportunities!$V$3:$V$502,MATCH(IFERROR(SMALL(Opportunities!$AC$3:$AC$502,5),""),Opportunities!$AC$3:$AC$502,0))="","",INDEX(Opportunities!$V$3:$V$502,MATCH(IFERROR(SMALL(Opportunities!$AC$3:$AC$502,5),""),Opportunities!$AC$3:$AC$502,0))),""))
A24: Nurture | B24: =COUNTIF(Opportunities!$C$3:$C$502,"Nurture") -> 0 | D24: =IF(COUNT(Opportunities!$AC$3:$AC$502)<6,"",IFERROR(IF(INDEX(Opportunities!$A$3:$A$502,MATCH(IFERROR(SMALL(Opportunities!$AC$3:$AC$502,6),""),Opportunities!$AC$3:$AC$502,0))="","",INDEX(Opportunities!$A$3:$A$502,MATCH(IFERROR(SMALL(Opportunities!$AC$3:$AC$502,6),""),Opportunities!$AC$3:$AC$502,0))),"")) | E24: =IF(COUNT(Opportunities!$AC$3:$AC$502)<6,"",IFERROR(IF(INDEX(Opportunities!$B$3:$B$502,MATCH(IFERROR(SMALL(Opportunities!$AC$3:$AC$502,6),""),Opportunities!$AC$3:$AC$502,0))="","",INDEX(Opportunities!$B$3:$B$502,MATCH(IFERROR(SMALL(Opportunities!$AC$3:$AC$502,6),""),Opportunities!$AC$3:$AC$502,0))),"")) | F24: =IF(COUNT(Opportunities!$AC$3:$AC$502)<6,"",IFERROR(IF(INDEX(Opportunities!$S$3:$S$502,MATCH(IFERROR(SMALL(Opportunities!$AC$3:$AC$502,6),""),Opportunities!$AC$3:$AC$502,0))="","",INDEX(Opportunities!$S$3:$S$502,MATCH(IFERROR(SMALL(Opportunities!$AC$3:$AC$502,6),""),Opportunities!$AC$3:$AC$502,0))),"")) | G24: =IF(COUNT(Opportunities!$AC$3:$AC$502)<6,"",IFERROR(IF(INDEX(Opportunities!$V$3:$V$502,MATCH(IFERROR(SMALL(Opportunities!$AC$3:$AC$502,6),""),Opportunities!$AC$3:$AC$502,0))="","",INDEX(Opportunities!$V$3:$V$502,MATCH(IFERROR(SMALL(Opportunities!$AC$3:$AC$502,6),""),Opportunities!$AC$3:$AC$502,0))),""))
D25: =IF(COUNT(Opportunities!$AC$3:$AC$502)<7,"",IFERROR(IF(INDEX(Opportunities!$A$3:$A$502,MATCH(IFERROR(SMALL(Opportunities!$AC$3:$AC$502,7),""),Opportunities!$AC$3:$AC$502,0))="","",INDEX(Opportunities!$A$3:$A$502,MATCH(IFERROR(SMALL(Opportunities!$AC$3:$AC$502,7),""),Opportunities!$AC$3:$AC$502,0))),"")) | E25: =IF(COUNT(Opportunities!$AC$3:$AC$502)<7,"",IFERROR(IF(INDEX(Opportunities!$B$3:$B$502,MATCH(IFERROR(SMALL(Opportunities!$AC$3:$AC$502,7),""),Opportunities!$AC$3:$AC$502,0))="","",INDEX(Opportunities!$B$3:$B$502,MATCH(IFERROR(SMALL(Opportunities!$AC$3:$AC$502,7),""),Opportunities!$AC$3:$AC$502,0))),"")) | F25: =IF(COUNT(Opportunities!$AC$3:$AC$502)<7,"",IFERROR(IF(INDEX(Opportunities!$S$3:$S$502,MATCH(IFERROR(SMALL(Opportunities!$AC$3:$AC$502,7),""),Opportunities!$AC$3:$AC$502,0))="","",INDEX(Opportunities!$S$3:$S$502,MATCH(IFERROR(SMALL(Opportunities!$AC$3:$AC$502,7),""),Opportunities!$AC$3:$AC$502,0))),"")) | G25: =IF(COUNT(Opportunities!$AC$3:$AC$502)<7,"",IFERROR(IF(INDEX(Opportunities!$V$3:$V$502,MATCH(IFERROR(SMALL(Opportunities!$AC$3:$AC$502,7),""),Opportunities!$AC$3:$AC$502,0))="","",INDEX(Opportunities!$V$3:$V$502,MATCH(IFERROR(SMALL(Opportunities!$AC$3:$AC$502,7),""),Opportunities!$AC$3:$AC$502,0))),""))
A26: Non-cash and in-kind (counted, not summed in DKK) | D26: =IF(COUNT(Opportunities!$AC$3:$AC$502)<8,"",IFERROR(IF(INDEX(Opportunities!$A$3:$A$502,MATCH(IFERROR(SMALL(Opportunities!$AC$3:$AC$502,8),""),Opportunities!$AC$3:$AC$502,0))="","",INDEX(Opportunities!$A$3:$A$502,MATCH(IFERROR(SMALL(Opportunities!$AC$3:$AC$502,8),""),Opportunities!$AC$3:$AC$502,0))),"")) | E26: =IF(COUNT(Opportunities!$AC$3:$AC$502)<8,"",IFERROR(IF(INDEX(Opportunities!$B$3:$B$502,MATCH(IFERROR(SMALL(Opportunities!$AC$3:$AC$502,8),""),Opportunities!$AC$3:$AC$502,0))="","",INDEX(Opportunities!$B$3:$B$502,MATCH(IFERROR(SMALL(Opportunities!$AC$3:$AC$502,8),""),Opportunities!$AC$3:$AC$502,0))),"")) | F26: =IF(COUNT(Opportunities!$AC$3:$AC$502)<8,"",IFERROR(IF(INDEX(Opportunities!$S$3:$S$502,MATCH(IFERROR(SMALL(Opportunities!$AC$3:$AC$502,8),""),Opportunities!$AC$3:$AC$502,0))="","",INDEX(Opportunities!$S$3:$S$502,MATCH(IFERROR(SMALL(Opportunities!$AC$3:$AC$502,8),""),Opportunities!$AC$3:$AC$502,0))),"")) | G26: =IF(COUNT(Opportunities!$AC$3:$AC$502)<8,"",IFERROR(IF(INDEX(Opportunities!$V$3:$V$502,MATCH(IFERROR(SMALL(Opportunities!$AC$3:$AC$502,8),""),Opportunities!$AC$3:$AC$502,0))="","",INDEX(Opportunities!$V$3:$V$502,MATCH(IFERROR(SMALL(Opportunities!$AC$3:$AC$502,8),""),Opportunities!$AC$3:$AC$502,0))),""))
A27: Non-cash won this semester | B27: =COUNTIFS(Opportunities!$C$3:$C$502,"Won",Opportunities!$G$3:$G$502,"Non-cash",Opportunities!$V$3:$V$502,">="&S_SemStart,Opportunities!$V$3:$V$502,"<="&S_SemEnd) -> 0 | D27: =IF(COUNT(Opportunities!$AC$3:$AC$502)<9,"",IFERROR(IF(INDEX(Opportunities!$A$3:$A$502,MATCH(IFERROR(SMALL(Opportunities!$AC$3:$AC$502,9),""),Opportunities!$AC$3:$AC$502,0))="","",INDEX(Opportunities!$A$3:$A$502,MATCH(IFERROR(SMALL(Opportunities!$AC$3:$AC$502,9),""),Opportunities!$AC$3:$AC$502,0))),"")) | E27: =IF(COUNT(Opportunities!$AC$3:$AC$502)<9,"",IFERROR(IF(INDEX(Opportunities!$B$3:$B$502,MATCH(IFERROR(SMALL(Opportunities!$AC$3:$AC$502,9),""),Opportunities!$AC$3:$AC$502,0))="","",INDEX(Opportunities!$B$3:$B$502,MATCH(IFERROR(SMALL(Opportunities!$AC$3:$AC$502,9),""),Opportunities!$AC$3:$AC$502,0))),"")) | F27: =IF(COUNT(Opportunities!$AC$3:$AC$502)<9,"",IFERROR(IF(INDEX(Opportunities!$S$3:$S$502,MATCH(IFERROR(SMALL(Opportunities!$AC$3:$AC$502,9),""),Opportunities!$AC$3:$AC$502,0))="","",INDEX(Opportunities!$S$3:$S$502,MATCH(IFERROR(SMALL(Opportunities!$AC$3:$AC$502,9),""),Opportunities!$AC$3:$AC$502,0))),"")) | G27: =IF(COUNT(Opportunities!$AC$3:$AC$502)<9,"",IFERROR(IF(INDEX(Opportunities!$V$3:$V$502,MATCH(IFERROR(SMALL(Opportunities!$AC$3:$AC$502,9),""),Opportunities!$AC$3:$AC$502,0))="","",INDEX(Opportunities!$V$3:$V$502,MATCH(IFERROR(SMALL(Opportunities!$AC$3:$AC$502,9),""),Opportunities!$AC$3:$AC$502,0))),""))
A28: In-kind won this semester | B28: =COUNTIFS(Opportunities!$C$3:$C$502,"Won",Opportunities!$G$3:$G$502,"In-kind",Opportunities!$V$3:$V$502,">="&S_SemStart,Opportunities!$V$3:$V$502,"<="&S_SemEnd) -> 0 | D28: =IF(COUNT(Opportunities!$AC$3:$AC$502)<10,"",IFERROR(IF(INDEX(Opportunities!$A$3:$A$502,MATCH(IFERROR(SMALL(Opportunities!$AC$3:$AC$502,10),""),Opportunities!$AC$3:$AC$502,0))="","",INDEX(Opportunities!$A$3:$A$502,MATCH(IFERROR(SMALL(Opportunities!$AC$3:$AC$502,10),""),Opportunities!$AC$3:$AC$502,0))),"")) | E28: =IF(COUNT(Opportunities!$AC$3:$AC$502)<10,"",IFERROR(IF(INDEX(Opportunities!$B$3:$B$502,MATCH(IFERROR(SMALL(Opportunities!$AC$3:$AC$502,10),""),Opportunities!$AC$3:$AC$502,0))="","",INDEX(Opportunities!$B$3:$B$502,MATCH(IFERROR(SMALL(Opportunities!$AC$3:$AC$502,10),""),Opportunities!$AC$3:$AC$502,0))),"")) | F28: =IF(COUNT(Opportunities!$AC$3:$AC$502)<10,"",IFERROR(IF(INDEX(Opportunities!$S$3:$S$502,MATCH(IFERROR(SMALL(Opportunities!$AC$3:$AC$502,10),""),Opportunities!$AC$3:$AC$502,0))="","",INDEX(Opportunities!$S$3:$S$502,MATCH(IFERROR(SMALL(Opportunities!$AC$3:$AC$502,10),""),Opportunities!$AC$3:$AC$502,0))),"")) | G28: =IF(COUNT(Opportunities!$AC$3:$AC$502)<10,"",IFERROR(IF(INDEX(Opportunities!$V$3:$V$502,MATCH(IFERROR(SMALL(Opportunities!$AC$3:$AC$502,10),""),Opportunities!$AC$3:$AC$502,0))="","",INDEX(Opportunities!$V$3:$V$502,MATCH(IFERROR(SMALL(Opportunities!$AC$3:$AC$502,10),""),Opportunities!$AC$3:$AC$502,0))),""))
A29: Non-cash or in-kind open | B29: =COUNTIFS(Opportunities!$X$3:$X$502,"Yes",Opportunities!$G$3:$G$502,"Non-cash")+COUNTIFS(Opportunities!$X$3:$X$502,"Yes",Opportunities!$G$3:$G$502,"In-kind") -> 2
D30: Lost reasons this semester
A31: Data health | D31: No budget | E31: =COUNTIFS(Opportunities!$C$3:$C$502,"Lost",Opportunities!$S$3:$S$502,D31,Opportunities!$V$3:$V$502,">="&S_SemStart,Opportunities!$V$3:$V$502,"<="&S_SemEnd) -> 1
A32: Open opportunities without a next action | B32: =COUNTIF(Opportunities!$Y$3:$Y$502,"Missing next action") -> 0 | D32: Chose another organisation | E32: =COUNTIFS(Opportunities!$C$3:$C$502,"Lost",Opportunities!$S$3:$S$502,D32,Opportunities!$V$3:$V$502,">="&S_SemStart,Opportunities!$V$3:$V$502,"<="&S_SemEnd) -> 0
A33: Companies with a check to fix | B33: =COUNTIF(Companies!$AH$3:$AH$502,"?*") -> 3 | D33: Not relevant for them | E33: =COUNTIFS(Opportunities!$C$3:$C$502,"Lost",Opportunities!$S$3:$S$502,D33,Opportunities!$V$3:$V$502,">="&S_SemStart,Opportunities!$V$3:$V$502,"<="&S_SemEnd) -> 0
A34: Opportunities with a check to fix | B34: =COUNTIF(Opportunities!$AA$3:$AA$502,"?*") -> 1 | D34: Bad timing | E34: =COUNTIFS(Opportunities!$C$3:$C$502,"Lost",Opportunities!$S$3:$S$502,D34,Opportunities!$V$3:$V$502,">="&S_SemStart,Opportunities!$V$3:$V$502,"<="&S_SemEnd) -> 0
A35: Contacts to re-check | B35: =COUNTIF(Contacts!$N$3:$N$502,"*Re-check*") -> 1 | D35: No response | E35: =COUNTIFS(Opportunities!$C$3:$C$502,"Lost",Opportunities!$S$3:$S$502,D35,Opportunities!$V$3:$V$502,">="&S_SemStart,Opportunities!$V$3:$V$502,"<="&S_SemEnd) -> 0
A36: Unchecked AI evidence | B36: =COUNTIF(Evidence!$J$3:$J$502,"Unchecked*") -> 1 | D36: Terms not agreed | E36: =COUNTIFS(Opportunities!$C$3:$C$502,"Lost",Opportunities!$S$3:$S$502,D36,Opportunities!$V$3:$V$502,">="&S_SemStart,Opportunities!$V$3:$V$502,"<="&S_SemEnd) -> 0
A37: Paths over the cap | B37: =MAX(0,COUNTIF(Companies!$V$3:$V$502,"Yes")-S_PathCap) -> 0 | D37: We withdrew | E37: =COUNTIFS(Opportunities!$C$3:$C$502,"Lost",Opportunities!$S$3:$S$502,D37,Opportunities!$V$3:$V$502,">="&S_SemStart,Opportunities!$V$3:$V$502,"<="&S_SemEnd) -> 0
D38: Other | E38: =COUNTIFS(Opportunities!$C$3:$C$502,"Lost",Opportunities!$S$3:$S$502,D38,Opportunities!$V$3:$V$502,">="&S_SemStart,Opportunities!$V$3:$V$502,"<="&S_SemEnd) -> 0

Sheet CBS Talks
A1: CBS Talks settings
A2: Fill in the yellow cells. The semester dates and target drive the dashboard. Rules (rows 21-27) come from the lean specification; change them only after the back-test.
A4: About CBS Talks
A5: Mission (one paragraph)
A6: Audience summary
A7: Typical attendance per event
A8: Study-line mix (e.g. BSc IB 22%, MSc FIN 15%)
A9: Social and newsletter reach (with date)
A10: Editorial independence policy
A11: CBS rules for sponsorships: what is allowed
A12: CBS rules checked on / with whom
A13: Category exclusivities currently granted
A14: Current semester
A15: Semester name | B15: Example semester
A16: Semester start | B16: =TODAY()-60 -> 46247 | C16: Example values: replace with the real semester dates.
A17: Semester end | B17: =TODAY()+120 -> 46427
A18: Semester cash target (DKK) | B18: 120000 | C18: Example placeholder target: replace with the real target.
A19: Date used for all flags | B19: =TODAY() -> 46307 | C19: Keep =TODAY(). Type a fixed date only to review the sheet as of that day.
A20: Rules (from the lean specification)
A21: High Fit threshold (Fit ≥) | B21: 6
A22: High Access threshold (Access level ≥) | B22: 2
A23: Max companies with a path in progress | B23: 5
A24: Renewal window (days before renewal date) | B24: 90
A25: No-reply flag after (days) | B25: 10
A26: Warm contact counts for (days) | B26: 365
A27: Contact re-check after (days) | B27: 183

Sheet Team
A1: Board members who can own companies and opportunities. Set Active = No at handover; their items then show 'needs new owner'.
A2: Name | B2: Role | C2: Email | D2: Active | E2: Term start | F2: Term end
A3: A.K. (example) | B3: Partnerships Manager | D3: Yes | E3: =TODAY()-200 -> 46107 | F3: =TODAY()+160 -> 46467
A4: J.H. (example) | B4: Partnerships Associate | D4: Yes | E4: =TODAY()-200 -> 46107 | F4: =TODAY()+160 -> 46467
A5: M.S. (example) | B5: Partnerships Associate | D5: Yes | E5: =TODAY()-200 -> 46107 | F5: =TODAY()+160 -> 46467
A6: L.M. (example) | B6: Board member (left) | D6: No | E6: =TODAY()-560 -> 45747 | F6: =TODAY()-30 -> 46277

Sheet Packages
A1: CBS Talks packages and prices. Proposals use these, never a guess of a company's budget.
A2: Package | B2: Price (DKK) | C2: What's included | D2: Capacity per semester | E2: Active
A3: Entry package (example) | B3: 8000 | C3: Logo on one event, a short company intro on stage | D3: 6 | E3: Yes
A4: Standard package (example) | B4: 20000 | C4: One sponsored event: intro talk, logo, partner report | D4: 4 | E4: Yes
A5: Strategic package (example) | B5: 45000 | C5: Event series over a semester, case workshop, partner report | D5: 2 | E5: Yes

Sheet Themes
A1: This year's editorial themes. Used when rating F2 Content fit.
A2: Theme | B2: Year | C2: Active
A3: Work after AI (example) | B3: 2026/27 | C3: Yes
A4: Fragile Systems (example) | B4: 2026/27 | C4: Yes

Sheet Events
A1: Every CBS Talks event with attendance. This is the evidence for F1 Student pull and for every pitch.
A2: Event | B2: Date | C2: Theme | D2: Attendance | E2: Study-line mix | F2: Partner company | G2: Partner report sent on
A3: The future of graduate work (example) | B3: =TODAY()-40 -> 46267 | C3: Work after AI (example) | D3: 180 | E3: BSc IB 25%, MSc FIN 15%, other 60% | F3: ProServ (example) | G3: =TODAY()-35 -> 46272

Sheet Companies
A1: One row per company. Yellow = type here; grey = calculated (don't edit). Hover a header for the rating anchors. A company enters the matrix only when F1, F2, F3, F5 are rated and Commercial Evidence has at least one row.
A2: Company | B2: Website | C2: CVR | D2: Industry | E2: Size band (DK, info only) | F2: Owner | G2: F1 Student pull | H2: F1 reason | I2: F1 source | J2: F2 Content fit | K2: F2 reason | L2: F2 source | M2: F3 Reason to work with us | N2: F3 reason | O2: F3 source | P2: F5 Long-term potential | Q2: F5 reason | R2: F5 source | S2: Fit reviewed on | T2: Intro path | U2: Specific need (Quick Win) | V2: Path in progress | W2: Path action | X2: Path started on | Y2: Notes (≤500 chars, nothing personal) | Z2: Do not contact | AA2: Do-not-contact reason | AB2: F4 Track record | AC2: Fit (0-10) | AD2: Access (0-4) | AE2: Quadrant | AF2: Last contact | AG2: Open opportunities | AH2: Checks | AI2: Queue key
A3: ProServ (example) | B3: proserv.example | D3: Professional services & consulting | E3: 1000+ | F3: J.H. (example) | G3: 2 | H3: 180 attended our event with them | I3: Events tab | J3: 2 | K3: Partner on stage for Work after AI series | L3: Talk recording | M3: 2 | N3: Graduate programme, recurring hiring | O3: careers page | P3: 2 | Q3: Partnered two years running | R3: Opportunities tab | S3: =TODAY()-20 -> 46287 | V3: No | Z3: No | AB3: =IF($A3="","",IF(COUNTIF('Commercial Evidence'!$A$3:$A$502,$A3)=0,"",IF(COUNTIFS('Commercial Evidence'!$A$3:$A$502,$A3,'Commercial Evidence'!$B$3:$B$502,"Previous CBS Talks spend")+COUNTIFS('Commercial Evidence'!$A$3:$A$502,$A3,'Commercial Evidence'!$B$3:$B$502,"Sponsors student organisations")>0,2,IF(COUNTIFS('Commercial Evidence'!$A$3:$A$502,$A3,'Commercial Evidence'!$B$3:$B$502,"Sponsors university activities")+COUNTIFS('Commercial Evidence'!$A$3:$A$502,$A3,'Commercial Evidence'!$B$3:$B$502,"Sponsors similar events")+COUNTIFS('Commercial Evidence'!$A$3:$A$502,$A3,'Commercial Evidence'!$B$3:$B$502,"Previous CBS Talks partner")>0,1,0)))) -> 2 | AC3: =IF($A3="","",IF(COUNT(G3,J3,M3,P3,AB3)<5,"",G3+J3+M3+P3+AB3)) -> 10 | AD3: =IF($A3="","",IF(COUNTIFS(Contacts!$A$3:$A$502,$A3,Contacts!$E$3:$E$502,"Champion",Contacts!$K$3:$K$502,"<>Yes",Contacts!$L$3:$L$502,"<>Yes")+COUNTIFS(Opportunities!$A$3:$A$502,$A3,Opportunities!$C$3:$C$502,"Won",Opportunities!$Q$3:$Q$502,"Satisfied")>0,4,IF(COUNTIFS(Interactions!$B$3:$B$502,$A3,Interactions!$I$3:$I$502,"Yes",Interactions!$A$3:$A$502,">="&(S_Today-S_WarmDays))>0,3,IF(T3<>"",2,IF(COUNTIFS(Contacts!$A$3:$A$502,$A3,Contacts!$M$3:$M$502,"Yes",Contacts!$K$3:$K$502,"<>Yes",Contacts!$L$3:$L$502,"<>Yes")>0,1,0))))) -> 4 | AE3: =IF($A3="","",IF(Z3="Yes","Do not contact",IF(AC3="","Research",IF(AND(AC3>=S_FitHigh,AD3>=S_AccessHigh),"Priority",IF(AC3>=S_FitHigh,"Build a Path",IF(AD3>=S_AccessHigh,"Quick Win","Low Priority")))))) -> Priority | AF3: =IF($A3="","",IF(_xlfn.MAXIFS(Interactions!$A$3:$A$502,Interactions!$B$3:$B$502,$A3)=0,"",_xlfn.MAXIFS(Interactions!$A$3:$A$502,Interactions!$B$3:$B$502,$A3))) -> 46287 | AG3: =IF($A3="","",COUNTIFS(Opportunities!$A$3:$A$502,$A3,Opportunities!$X$3:$X$502,"Yes")) -> 0 | AH3: =IF($A3="","",_xlfn.TEXTJOIN(", ",TRUE(),IF(COUNTIF($A$3:$A$502,$A3)>1,"Duplicate name",""),IF(OR(AND(G3=2,I3=""),AND(J3=2,L3=""),AND(M3=2,O3=""),AND(P3=2,R3="")),"Source missing for a 2",""),IF(F3="","No owner",IF(COUNTIFS(R_TeamName,F3,R_TeamActive,"No")>0,"Needs new owner","")),IF(AND(V3="Yes",X3<>"",X3<S_SemStart),"Path overdue",""),IF(AND(S3<>"",S3<S_Today-365),"Stale research",""),IF(AND(AE3="Research",COUNTIF('Commercial Evidence'!$A$3:$A$502,$A3)=0),"Add commercial evidence",""))) | AI3: =IF(OR($A3="",Z3="Yes"),"",IF(AND(AE3="Priority",AG3=0,COUNTIFS(Opportunities!$A$3:$A$502,$A3,Opportunities!$Y$3:$Y$502,"Renewal due")=0),600000+(10-AC3)*1000+(4-AD3)*100+ROW()/100000,IF(V3="Yes",700000+IF(X3="",0,X3-40000)/10+ROW()/100000,IF(AND(AE3="Quick Win",U3<>"",AG3=0),800000+(10-AC3)*1000+ROW()/100000,IF(AND(AE3="Build a Path",COUNTIF($V$3:$V$502,"Yes")<S_PathCap),900000+(10-AC3)*1000+(4-AD3)*100+ROW()/100000,"")))))
A4: MegaBrand A/S (example) | B4: megabrand.example | D4: Consumer goods & retail | E4: 1000+ | F4: M.S. (example) | G4: 2 | H4: Top result in our audience poll | I4: Poll results | J4: 1 | K4: Relevant topic, no named speaker | M4: 1 | N4: Hires business graduates, already well known | P4: 1 | Q4: Could repeat | S4: =TODAY()-30 -> 46277 | V4: Yes | W4: Ask board alumni network for an introduction | X4: =TODAY()-25 -> 46282 | Z4: No | AB4: =IF($A4="","",IF(COUNTIF('Commercial Evidence'!$A$3:$A$502,$A4)=0,"",IF(COUNTIFS('Commercial Evidence'!$A$3:$A$502,$A4,'Commercial Evidence'!$B$3:$B$502,"Previous CBS Talks spend")+COUNTIFS('Commercial Evidence'!$A$3:$A$502,$A4,'Commercial Evidence'!$B$3:$B$502,"Sponsors student organisations")>0,2,IF(COUNTIFS('Commercial Evidence'!$A$3:$A$502,$A4,'Commercial Evidence'!$B$3:$B$502,"Sponsors university activities")+COUNTIFS('Commercial Evidence'!$A$3:$A$502,$A4,'Commercial Evidence'!$B$3:$B$502,"Sponsors similar events")+COUNTIFS('Commercial Evidence'!$A$3:$A$502,$A4,'Commercial Evidence'!$B$3:$B$502,"Previous CBS Talks partner")>0,1,0)))) -> 2 | AC4: =IF($A4="","",IF(COUNT(G4,J4,M4,P4,AB4)<5,"",G4+J4+M4+P4+AB4)) -> 7 | AD4: =IF($A4="","",IF(COUNTIFS(Contacts!$A$3:$A$502,$A4,Contacts!$E$3:$E$502,"Champion",Contacts!$K$3:$K$502,"<>Yes",Contacts!$L$3:$L$502,"<>Yes")+COUNTIFS(Opportunities!$A$3:$A$502,$A4,Opportunities!$C$3:$C$502,"Won",Opportunities!$Q$3:$Q$502,"Satisfied")>0,4,IF(COUNTIFS(Interactions!$B$3:$B$502,$A4,Interactions!$I$3:$I$502,"Yes",Interactions!$A$3:$A$502,">="&(S_Today-S_WarmDays))>0,3,IF(T4<>"",2,IF(COUNTIFS(Contacts!$A$3:$A$502,$A4,Contacts!$M$3:$M$502,"Yes",Contacts!$K$3:$K$502,"<>Yes",Contacts!$L$3:$L$502,"<>Yes")>0,1,0))))) -> 1 | AE4: =IF($A4="","",IF(Z4="Yes","Do not contact",IF(AC4="","Research",IF(AND(AC4>=S_FitHigh,AD4>=S_AccessHigh),"Priority",IF(AC4>=S_FitHigh,"Build a Path",IF(AD4>=S_AccessHigh,"Quick Win","Low Priority")))))) -> Build a Path | AF4: =IF($A4="","",IF(_xlfn.MAXIFS(Interactions!$A$3:$A$502,Interactions!$B$3:$B$502,$A4)=0,"",_xlfn.MAXIFS(Interactions!$A$3:$A$502,Interactions!$B$3:$B$502,$A4))) -> 46295 | AG4: =IF($A4="","",COUNTIFS(Opportunities!$A$3:$A$502,$A4,Opportunities!$X$3:$X$502,"Yes")) -> 1 | AH4: =IF($A4="","",_xlfn.TEXTJOIN(", ",TRUE(),IF(COUNTIF($A$3:$A$502,$A4)>1,"Duplicate name",""),IF(OR(AND(G4=2,I4=""),AND(J4=2,L4=""),AND(M4=2,O4=""),AND(P4=2,R4="")),"Source missing for a 2",""),IF(F4="","No owner",IF(COUNTIFS(R_TeamName,F4,R_TeamActive,"No")>0,"Needs new owner","")),IF(AND(V4="Yes",X4<>"",X4<S_SemStart),"Path overdue",""),IF(AND(S4<>"",S4<S_Today-365),"Stale research",""),IF(AND(AE4="Research",COUNTIF('Commercial Evidence'!$A$3:$A$502,$A4)=0),"Add commercial evidence",""))) | AI4: =IF(OR($A4="",Z4="Yes"),"",IF(AND(AE4="Priority",AG4=0,COUNTIFS(Opportunities!$A$3:$A$502,$A4,Opportunities!$Y$3:$Y$502,"Renewal due")=0),600000+(10-AC4)*1000+(4-AD4)*100+ROW()/100000,IF(V4="Yes",700000+IF(X4="",0,X4-40000)/10+ROW()/100000,IF(AND(AE4="Quick Win",U4<>"",AG4=0),800000+(10-AC4)*1000+ROW()/100000,IF(AND(AE4="Build a Path",COUNTIF($V$3:$V$502,"Yes")<S_PathCap),900000+(10-AC4)*1000+(4-AD4)*100+ROW()/100000,""))))) -> 700628.2
A5: Nordlys Logistics (example) | B5: nordlys.example | D5: Shipping, logistics & transport | E5: 250-999 | F5: A.K. (example) | G5: 1 | H5: Relevant to supply-chain students | J5: 1 | K5: Supply-chain topic, no named speaker yet | M5: 2 | N5: About 20 graduate postings this year | O5: jobs page | P5: 2 | Q5: Annual graduate programme | R5: careers page | S5: =TODAY()-15 -> 46292 | T5: CBS alumnus in their talent team, via A.K. (agreed) | V5: No | Z5: No | AB5: =IF($A5="","",IF(COUNTIF('Commercial Evidence'!$A$3:$A$502,$A5)=0,"",IF(COUNTIFS('Commercial Evidence'!$A$3:$A$502,$A5,'Commercial Evidence'!$B$3:$B$502,"Previous CBS Talks spend")+COUNTIFS('Commercial Evidence'!$A$3:$A$502,$A5,'Commercial Evidence'!$B$3:$B$502,"Sponsors student organisations")>0,2,IF(COUNTIFS('Commercial Evidence'!$A$3:$A$502,$A5,'Commercial Evidence'!$B$3:$B$502,"Sponsors university activities")+COUNTIFS('Commercial Evidence'!$A$3:$A$502,$A5,'Commercial Evidence'!$B$3:$B$502,"Sponsors similar events")+COUNTIFS('Commercial Evidence'!$A$3:$A$502,$A5,'Commercial Evidence'!$B$3:$B$502,"Previous CBS Talks partner")>0,1,0)))) -> 0 | AC5: =IF($A5="","",IF(COUNT(G5,J5,M5,P5,AB5)<5,"",G5+J5+M5+P5+AB5)) -> 6 | AD5: =IF($A5="","",IF(COUNTIFS(Contacts!$A$3:$A$502,$A5,Contacts!$E$3:$E$502,"Champion",Contacts!$K$3:$K$502,"<>Yes",Contacts!$L$3:$L$502,"<>Yes")+COUNTIFS(Opportunities!$A$3:$A$502,$A5,Opportunities!$C$3:$C$502,"Won",Opportunities!$Q$3:$Q$502,"Satisfied")>0,4,IF(COUNTIFS(Interactions!$B$3:$B$502,$A5,Interactions!$I$3:$I$502,"Yes",Interactions!$A$3:$A$502,">="&(S_Today-S_WarmDays))>0,3,IF(T5<>"",2,IF(COUNTIFS(Contacts!$A$3:$A$502,$A5,Contacts!$M$3:$M$502,"Yes",Contacts!$K$3:$K$502,"<>Yes",Contacts!$L$3:$L$502,"<>Yes")>0,1,0))))) -> 2 | AE5: =IF($A5="","",IF(Z5="Yes","Do not contact",IF(AC5="","Research",IF(AND(AC5>=S_FitHigh,AD5>=S_AccessHigh),"Priority",IF(AC5>=S_FitHigh,"Build a Path",IF(AD5>=S_AccessHigh,"Quick Win","Low Priority")))))) -> Priority | AF5: =IF($A5="","",IF(_xlfn.MAXIFS(Interactions!$A$3:$A$502,Interactions!$B$3:$B$502,$A5)=0,"",_xlfn.MAXIFS(Interactions!$A$3:$A$502,Interactions!$B$3:$B$502,$A5))) | AG5: =IF($A5="","",COUNTIFS(Opportunities!$A$3:$A$502,$A5,Opportunities!$X$3:$X$502,"Yes")) -> 0 | AH5: =IF($A5="","",_xlfn.TEXTJOIN(", ",TRUE(),IF(COUNTIF($A$3:$A$502,$A5)>1,"Duplicate name",""),IF(OR(AND(G5=2,I5=""),AND(J5=2,L5=""),AND(M5=2,O5=""),AND(P5=2,R5="")),"Source missing for a 2",""),IF(F5="","No owner",IF(COUNTIFS(R_TeamName,F5,R_TeamActive,"No")>0,"Needs new owner","")),IF(AND(V5="Yes",X5<>"",X5<S_SemStart),"Path overdue",""),IF(AND(S5<>"",S5<S_Today-365),"Stale research",""),IF(AND(AE5="Research",COUNTIF('Commercial Evidence'!$A$3:$A$502,$A5)=0),"Add commercial evidence",""))) | AI5: =IF(OR($A5="",Z5="Yes"),"",IF(AND(AE5="Priority",AG5=0,COUNTIFS(Opportunities!$A$3:$A$502,$A5,Opportunities!$Y$3:$Y$502,"Renewal due")=0),600000+(10-AC5)*1000+(4-AD5)*100+ROW()/100000,IF(V5="Yes",700000+IF(X5="",0,X5-40000)/10+ROW()/100000,IF(AND(AE5="Quick Win",U5<>"",AG5=0),800000+(10-AC5)*1000+ROW()/100000,IF(AND(AE5="Build a Path",COUNTIF($V$3:$V$502,"Yes")<S_PathCap),900000+(10-AC5)*1000+(4-AD5)*100+ROW()/100000,""))))) -> 604200
A6: Fjord Ventures (example) | B6: fjord.example | D6: Investors & startup ecosystem | E6: <50 | F6: A.K. (example) | G6: 1 | H6: Some interest among entrepreneurship students | J6: 2 | K6: Founder has recorded keynotes on fintech | L6: talk recording | M6: 1 | N6: Wants visibility for the founder's agenda | P6: 1 | Q6: Could repeat | S6: =TODAY()-10 -> 46297 | U6: Speaker for the spring keynote | V6: No | Z6: No | AB6: =IF($A6="","",IF(COUNTIF('Commercial Evidence'!$A$3:$A$502,$A6)=0,"",IF(COUNTIFS('Commercial Evidence'!$A$3:$A$502,$A6,'Commercial Evidence'!$B$3:$B$502,"Previous CBS Talks spend")+COUNTIFS('Commercial Evidence'!$A$3:$A$502,$A6,'Commercial Evidence'!$B$3:$B$502,"Sponsors student organisations")>0,2,IF(COUNTIFS('Commercial Evidence'!$A$3:$A$502,$A6,'Commercial Evidence'!$B$3:$B$502,"Sponsors university activities")+COUNTIFS('Commercial Evidence'!$A$3:$A$502,$A6,'Commercial Evidence'!$B$3:$B$502,"Sponsors similar events")+COUNTIFS('Commercial Evidence'!$A$3:$A$502,$A6,'Commercial Evidence'!$B$3:$B$502,"Previous CBS Talks partner")>0,1,0)))) -> 0 | AC6: =IF($A6="","",IF(COUNT(G6,J6,M6,P6,AB6)<5,"",G6+J6+M6+P6+AB6)) -> 5 | AD6: =IF($A6="","",IF(COUNTIFS(Contacts!$A$3:$A$502,$A6,Contacts!$E$3:$E$502,"Champion",Contacts!$K$3:$K$502,"<>Yes",Contacts!$L$3:$L$502,"<>Yes")+COUNTIFS(Opportunities!$A$3:$A$502,$A6,Opportunities!$C$3:$C$502,"Won",Opportunities!$Q$3:$Q$502,"Satisfied")>0,4,IF(COUNTIFS(Interactions!$B$3:$B$502,$A6,Interactions!$I$3:$I$502,"Yes",Interactions!$A$3:$A$502,">="&(S_Today-S_WarmDays))>0,3,IF(T6<>"",2,IF(COUNTIFS(Contacts!$A$3:$A$502,$A6,Contacts!$M$3:$M$502,"Yes",Contacts!$K$3:$K$502,"<>Yes",Contacts!$L$3:$L$502,"<>Yes")>0,1,0))))) -> 4 | AE6: =IF($A6="","",IF(Z6="Yes","Do not contact",IF(AC6="","Research",IF(AND(AC6>=S_FitHigh,AD6>=S_AccessHigh),"Priority",IF(AC6>=S_FitHigh,"Build a Path",IF(AD6>=S_AccessHigh,"Quick Win","Low Priority")))))) -> Quick Win | AF6: =IF($A6="","",IF(_xlfn.MAXIFS(Interactions!$A$3:$A$502,Interactions!$B$3:$B$502,$A6)=0,"",_xlfn.MAXIFS(Interactions!$A$3:$A$502,Interactions!$B$3:$B$502,$A6))) -> 46301 | AG6: =IF($A6="","",COUNTIFS(Opportunities!$A$3:$A$502,$A6,Opportunities!$X$3:$X$502,"Yes")) -> 1 | AH6: =IF($A6="","",_xlfn.TEXTJOIN(", ",TRUE(),IF(COUNTIF($A$3:$A$502,$A6)>1,"Duplicate name",""),IF(OR(AND(G6=2,I6=""),AND(J6=2,L6=""),AND(M6=2,O6=""),AND(P6=2,R6="")),"Source missing for a 2",""),IF(F6="","No owner",IF(COUNTIFS(R_TeamName,F6,R_TeamActive,"No")>0,"Needs new owner","")),IF(AND(V6="Yes",X6<>"",X6<S_SemStart),"Path overdue",""),IF(AND(S6<>"",S6<S_Today-365),"Stale research",""),IF(AND(AE6="Research",COUNTIF('Commercial Evidence'!$A$3:$A$502,$A6)=0),"Add commercial evidence",""))) | AI6: =IF(OR($A6="",Z6="Yes"),"",IF(AND(AE6="Priority",AG6=0,COUNTIFS(Opportunities!$A$3:$A$502,$A6,Opportunities!$Y$3:$Y$502,"Renewal due")=0),600000+(10-AC6)*1000+(4-AD6)*100+ROW()/100000,IF(V6="Yes",700000+IF(X6="",0,X6-40000)/10+ROW()/100000,IF(AND(AE6="Quick Win",U6<>"",AG6=0),800000+(10-AC6)*1000+ROW()/100000,IF(AND(AE6="Build a Path",COUNTIF($V$3:$V$502,"Yes")<S_PathCap),900000+(10-AC6)*1000+(4-AD6)*100+ROW()/100000,"")))))
A7: Kobber Hotels (example) | B7: kobber.example | D7: Hospitality, food & venues | E7: 50-249 | F7: L.M. (example) | G7: 0 | H7: No sign students care about the brand | J7: 0 | K7: No link to our themes | M7: 1 | N7: Interested in local visibility | P7: 1 | Q7: Could host again | S7: =TODAY()-12 -> 46295 | U7: Venue for an autumn event | V7: No | Z7: No | AB7: =IF($A7="","",IF(COUNTIF('Commercial Evidence'!$A$3:$A$502,$A7)=0,"",IF(COUNTIFS('Commercial Evidence'!$A$3:$A$502,$A7,'Commercial Evidence'!$B$3:$B$502,"Previous CBS Talks spend")+COUNTIFS('Commercial Evidence'!$A$3:$A$502,$A7,'Commercial Evidence'!$B$3:$B$502,"Sponsors student organisations")>0,2,IF(COUNTIFS('Commercial Evidence'!$A$3:$A$502,$A7,'Commercial Evidence'!$B$3:$B$502,"Sponsors university activities")+COUNTIFS('Commercial Evidence'!$A$3:$A$502,$A7,'Commercial Evidence'!$B$3:$B$502,"Sponsors similar events")+COUNTIFS('Commercial Evidence'!$A$3:$A$502,$A7,'Commercial Evidence'!$B$3:$B$502,"Previous CBS Talks partner")>0,1,0)))) -> 1 | AC7: =IF($A7="","",IF(COUNT(G7,J7,M7,P7,AB7)<5,"",G7+J7+M7+P7+AB7)) -> 3 | AD7: =IF($A7="","",IF(COUNTIFS(Contacts!$A$3:$A$502,$A7,Contacts!$E$3:$E$502,"Champion",Contacts!$K$3:$K$502,"<>Yes",Contacts!$L$3:$L$502,"<>Yes")+COUNTIFS(Opportunities!$A$3:$A$502,$A7,Opportunities!$C$3:$C$502,"Won",Opportunities!$Q$3:$Q$502,"Satisfied")>0,4,IF(COUNTIFS(Interactions!$B$3:$B$502,$A7,Interactions!$I$3:$I$502,"Yes",Interactions!$A$3:$A$502,">="&(S_Today-S_WarmDays))>0,3,IF(T7<>"",2,IF(COUNTIFS(Contacts!$A$3:$A$502,$A7,Contacts!$M$3:$M$502,"Yes",Contacts!$K$3:$K$502,"<>Yes",Contacts!$L$3:$L$502,"<>Yes")>0,1,0))))) -> 3 | AE7: =IF($A7="","",IF(Z7="Yes","Do not contact",IF(AC7="","Research",IF(AND(AC7>=S_FitHigh,AD7>=S_AccessHigh),"Priority",IF(AC7>=S_FitHigh,"Build a Path",IF(AD7>=S_AccessHigh,"Quick Win","Low Priority")))))) -> Quick Win | AF7: =IF($A7="","",IF(_xlfn.MAXIFS(Interactions!$A$3:$A$502,Interactions!$B$3:$B$502,$A7)=0,"",_xlfn.MAXIFS(Interactions!$A$3:$A$502,Interactions!$B$3:$B$502,$A7))) -> 46298 | AG7: =IF($A7="","",COUNTIFS(Opportunities!$A$3:$A$502,$A7,Opportunities!$X$3:$X$502,"Yes")) -> 1 | AH7: =IF($A7="","",_xlfn.TEXTJOIN(", ",TRUE(),IF(COUNTIF($A$3:$A$502,$A7)>1,"Duplicate name",""),IF(OR(AND(G7=2,I7=""),AND(J7=2,L7=""),AND(M7=2,O7=""),AND(P7=2,R7="")),"Source missing for a 2",""),IF(F7="","No owner",IF(COUNTIFS(R_TeamName,F7,R_TeamActive,"No")>0,"Needs new owner","")),IF(AND(V7="Yes",X7<>"",X7<S_SemStart),"Path overdue",""),IF(AND(S7<>"",S7<S_Today-365),"Stale research",""),IF(AND(AE7="Research",COUNTIF('Commercial Evidence'!$A$3:$A$502,$A7)=0),"Add commercial evidence",""))) -> Needs new owner | AI7: =IF(OR($A7="",Z7="Yes"),"",IF(AND(AE7="Priority",AG7=0,COUNTIFS(Opportunities!$A$3:$A$502,$A7,Opportunities!$Y$3:$Y$502,"Renewal due")=0),600000+(10-AC7)*1000+(4-AD7)*100+ROW()/100000,IF(V7="Yes",700000+IF(X7="",0,X7-40000)/10+ROW()/100000,IF(AND(AE7="Quick Win",U7<>"",AG7=0),800000+(10-AC7)*1000+ROW()/100000,IF(AND(AE7="Build a Path",COUNTIF($V$3:$V$502,"Yes")<S_PathCap),900000+(10-AC7)*1000+(4-AD7)*100+ROW()/100000,"")))))
A8: Gamma Software (example) | B8: gamma.example | D8: Technology & software | E8: 50-249 | F8: M.S. (example) | G8: 0 | H8: Checked: no student interest found | J8: 0 | K8: No link to our themes | M8: 0 | N8: No business-graduate hiring found | P8: 0 | Q8: No recurring reason | S8: =TODAY()-50 -> 46257 | V8: No | Z8: No | AB8: =IF($A8="","",IF(COUNTIF('Commercial Evidence'!$A$3:$A$502,$A8)=0,"",IF(COUNTIFS('Commercial Evidence'!$A$3:$A$502,$A8,'Commercial Evidence'!$B$3:$B$502,"Previous CBS Talks spend")+COUNTIFS('Commercial Evidence'!$A$3:$A$502,$A8,'Commercial Evidence'!$B$3:$B$502,"Sponsors student organisations")>0,2,IF(COUNTIFS('Commercial Evidence'!$A$3:$A$502,$A8,'Commercial Evidence'!$B$3:$B$502,"Sponsors university activities")+COUNTIFS('Commercial Evidence'!$A$3:$A$502,$A8,'Commercial Evidence'!$B$3:$B$502,"Sponsors similar events")+COUNTIFS('Commercial Evidence'!$A$3:$A$502,$A8,'Commercial Evidence'!$B$3:$B$502,"Previous CBS Talks partner")>0,1,0)))) -> 0 | AC8: =IF($A8="","",IF(COUNT(G8,J8,M8,P8,AB8)<5,"",G8+J8+M8+P8+AB8)) -> 0 | AD8: =IF($A8="","",IF(COUNTIFS(Contacts!$A$3:$A$502,$A8,Contacts!$E$3:$E$502,"Champion",Contacts!$K$3:$K$502,"<>Yes",Contacts!$L$3:$L$502,"<>Yes")+COUNTIFS(Opportunities!$A$3:$A$502,$A8,Opportunities!$C$3:$C$502,"Won",Opportunities!$Q$3:$Q$502,"Satisfied")>0,4,IF(COUNTIFS(Interactions!$B$3:$B$502,$A8,Interactions!$I$3:$I$502,"Yes",Interactions!$A$3:$A$502,">="&(S_Today-S_WarmDays))>0,3,IF(T8<>"",2,IF(COUNTIFS(Contacts!$A$3:$A$502,$A8,Contacts!$M$3:$M$502,"Yes",Contacts!$K$3:$K$502,"<>Yes",Contacts!$L$3:$L$502,"<>Yes")>0,1,0))))) -> 0 | AE8: =IF($A8="","",IF(Z8="Yes","Do not contact",IF(AC8="","Research",IF(AND(AC8>=S_FitHigh,AD8>=S_AccessHigh),"Priority",IF(AC8>=S_FitHigh,"Build a Path",IF(AD8>=S_AccessHigh,"Quick Win","Low Priority")))))) -> Low Priority | AF8: =IF($A8="","",IF(_xlfn.MAXIFS(Interactions!$A$3:$A$502,Interactions!$B$3:$B$502,$A8)=0,"",_xlfn.MAXIFS(Interactions!$A$3:$A$502,Interactions!$B$3:$B$502,$A8))) | AG8: =IF($A8="","",COUNTIFS(Opportunities!$A$3:$A$502,$A8,Opportunities!$X$3:$X$502,"Yes")) -> 0 | AH8: =IF($A8="","",_xlfn.TEXTJOIN(", ",TRUE(),IF(COUNTIF($A$3:$A$502,$A8)>1,"Duplicate name",""),IF(OR(AND(G8=2,I8=""),AND(J8=2,L8=""),AND(M8=2,O8=""),AND(P8=2,R8="")),"Source missing for a 2",""),IF(F8="","No owner",IF(COUNTIFS(R_TeamName,F8,R_TeamActive,"No")>0,"Needs new owner","")),IF(AND(V8="Yes",X8<>"",X8<S_SemStart),"Path overdue",""),IF(AND(S8<>"",S8<S_Today-365),"Stale research",""),IF(AND(AE8="Research",COUNTIF('Commercial Evidence'!$A$3:$A$502,$A8)=0),"Add commercial evidence",""))) | AI8: =IF(OR($A8="",Z8="Yes"),"",IF(AND(AE8="Priority",AG8=0,COUNTIFS(Opportunities!$A$3:$A$502,$A8,Opportunities!$Y$3:$Y$502,"Renewal due")=0),600000+(10-AC8)*1000+(4-AD8)*100+ROW()/100000,IF(V8="Yes",700000+IF(X8="",0,X8-40000)/10+ROW()/100000,IF(AND(AE8="Quick Win",U8<>"",AG8=0),800000+(10-AC8)*1000+ROW()/100000,IF(AND(AE8="Build a Path",COUNTIF($V$3:$V$502,"Yes")<S_PathCap),900000+(10-AC8)*1000+(4-AD8)*100+ROW()/100000,"")))))
A9: Søby Foods (example) | B9: soby.example | D9: Consumer goods & retail | E9: 250-999 | F9: J.H. (example) | AB9: =IF($A9="","",IF(COUNTIF('Commercial Evidence'!$A$3:$A$502,$A9)=0,"",IF(COUNTIFS('Commercial Evidence'!$A$3:$A$502,$A9,'Commercial Evidence'!$B$3:$B$502,"Previous CBS Talks spend")+COUNTIFS('Commercial Evidence'!$A$3:$A$502,$A9,'Commercial Evidence'!$B$3:$B$502,"Sponsors student organisations")>0,2,IF(COUNTIFS('Commercial Evidence'!$A$3:$A$502,$A9,'Commercial Evidence'!$B$3:$B$502,"Sponsors university activities")+COUNTIFS('Commercial Evidence'!$A$3:$A$502,$A9,'Commercial Evidence'!$B$3:$B$502,"Sponsors similar events")+COUNTIFS('Commercial Evidence'!$A$3:$A$502,$A9,'Commercial Evidence'!$B$3:$B$502,"Previous CBS Talks partner")>0,1,0)))) | AC9: =IF($A9="","",IF(COUNT(G9,J9,M9,P9,AB9)<5,"",G9+J9+M9+P9+AB9)) | AD9: =IF($A9="","",IF(COUNTIFS(Contacts!$A$3:$A$502,$A9,Contacts!$E$3:$E$502,"Champion",Contacts!$K$3:$K$502,"<>Yes",Contacts!$L$3:$L$502,"<>Yes")+COUNTIFS(Opportunities!$A$3:$A$502,$A9,Opportunities!$C$3:$C$502,"Won",Opportunities!$Q$3:$Q$502,"Satisfied")>0,4,IF(COUNTIFS(Interactions!$B$3:$B$502,$A9,Interactions!$I$3:$I$502,"Yes",Interactions!$A$3:$A$502,">="&(S_Today-S_WarmDays))>0,3,IF(T9<>"",2,IF(COUNTIFS(Contacts!$A$3:$A$502,$A9,Contacts!$M$3:$M$502,"Yes",Contacts!$K$3:$K$502,"<>Yes",Contacts!$L$3:$L$502,"<>Yes")>0,1,0))))) -> 0 | AE9: =IF($A9="","",IF(Z9="Yes","Do not contact",IF(AC9="","Research",IF(AND(AC9>=S_FitHigh,AD9>=S_AccessHigh),"Priority",IF(AC9>=S_FitHigh,"Build a Path",IF(AD9>=S_AccessHigh,"Quick Win","Low Priority")))))) -> Research | AF9: =IF($A9="","",IF(_xlfn.MAXIFS(Interactions!$A$3:$A$502,Interactions!$B$3:$B$502,$A9)=0,"",_xlfn.MAXIFS(Interactions!$A$3:$A$502,Interactions!$B$3:$B$502,$A9))) | AG9: =IF($A9="","",COUNTIFS(Opportunities!$A$3:$A$502,$A9,Opportunities!$X$3:$X$502,"Yes")) -> 0 | AH9: =IF($A9="","",_xlfn.TEXTJOIN(", ",TRUE(),IF(COUNTIF($A$3:$A$502,$A9)>1,"Duplicate name",""),IF(OR(AND(G9=2,I9=""),AND(J9=2,L9=""),AND(M9=2,O9=""),AND(P9=2,R9="")),"Source missing for a 2",""),IF(F9="","No owner",IF(COUNTIFS(R_TeamName,F9,R_TeamActive,"No")>0,"Needs new owner","")),IF(AND(V9="Yes",X9<>"",X9<S_SemStart),"Path overdue",""),IF(AND(S9<>"",S9<S_Today-365),"Stale research",""),IF(AND(AE9="Research",COUNTIF('Commercial Evidence'!$A$3:$A$502,$A9)=0),"Add commercial evidence",""))) -> Add commercial evidence | AI9: =IF(OR($A9="",Z9="Yes"),"",IF(AND(AE9="Priority",AG9=0,COUNTIFS(Opportunities!$A$3:$A$502,$A9,Opportunities!$Y$3:$Y$502,"Renewal due")=0),600000+(10-AC9)*1000+(4-AD9)*100+ROW()/100000,IF(V9="Yes",700000+IF(X9="",0,X9-40000)/10+ROW()/100000,IF(AND(AE9="Quick Win",U9<>"",AG9=0),800000+(10-AC9)*1000+ROW()/100000,IF(AND(AE9="Build a Path",COUNTIF($V$3:$V$502,"Yes")<S_PathCap),900000+(10-AC9)*1000+(4-AD9)*100+ROW()/100000,"")))))
A10: Strandvej Studio (example) | B10: strandvej.example | D10: Media, marketing & communications | E10: <50 | F10: M.S. (example) | AB10: =IF($A10="","",IF(COUNTIF('Commercial Evidence'!$A$3:$A$502,$A10)=0,"",IF(COUNTIFS('Commercial Evidence'!$A$3:$A$502,$A10,'Commercial Evidence'!$B$3:$B$502,"Previous CBS Talks spend")+COUNTIFS('Commercial Evidence'!$A$3:$A$502,$A10,'Commercial Evidence'!$B$3:$B$502,"Sponsors student organisations")>0,2,IF(COUNTIFS('Commercial Evidence'!$A$3:$A$502,$A10,'Commercial Evidence'!$B$3:$B$502,"Sponsors university activities")+COUNTIFS('Commercial Evidence'!$A$3:$A$502,$A10,'Commercial Evidence'!$B$3:$B$502,"Sponsors similar events")+COUNTIFS('Commercial Evidence'!$A$3:$A$502,$A10,'Commercial Evidence'!$B$3:$B$502,"Previous CBS Talks partner")>0,1,0)))) | AC10: =IF($A10="","",IF(COUNT(G10,J10,M10,P10,AB10)<5,"",G10+J10+M10+P10+AB10)) | AD10: =IF($A10="","",IF(COUNTIFS(Contacts!$A$3:$A$502,$A10,Contacts!$E$3:$E$502,"Champion",Contacts!$K$3:$K$502,"<>Yes",Contacts!$L$3:$L$502,"<>Yes")+COUNTIFS(Opportunities!$A$3:$A$502,$A10,Opportunities!$C$3:$C$502,"Won",Opportunities!$Q$3:$Q$502,"Satisfied")>0,4,IF(COUNTIFS(Interactions!$B$3:$B$502,$A10,Interactions!$I$3:$I$502,"Yes",Interactions!$A$3:$A$502,">="&(S_Today-S_WarmDays))>0,3,IF(T10<>"",2,IF(COUNTIFS(Contacts!$A$3:$A$502,$A10,Contacts!$M$3:$M$502,"Yes",Contacts!$K$3:$K$502,"<>Yes",Contacts!$L$3:$L$502,"<>Yes")>0,1,0))))) -> 0 | AE10: =IF($A10="","",IF(Z10="Yes","Do not contact",IF(AC10="","Research",IF(AND(AC10>=S_FitHigh,AD10>=S_AccessHigh),"Priority",IF(AC10>=S_FitHigh,"Build a Path",IF(AD10>=S_AccessHigh,"Quick Win","Low Priority")))))) -> Research | AF10: =IF($A10="","",IF(_xlfn.MAXIFS(Interactions!$A$3:$A$502,Interactions!$B$3:$B$502,$A10)=0,"",_xlfn.MAXIFS(Interactions!$A$3:$A$502,Interactions!$B$3:$B$502,$A10))) | AG10: =IF($A10="","",COUNTIFS(Opportunities!$A$3:$A$502,$A10,Opportunities!$X$3:$X$502,"Yes")) -> 0 | AH10: =IF($A10="","",_xlfn.TEXTJOIN(", ",TRUE(),IF(COUNTIF($A$3:$A$502,$A10)>1,"Duplicate name",""),IF(OR(AND(G10=2,I10=""),AND(J10=2,L10=""),AND(M10=2,O10=""),AND(P10=2,R10="")),"Source missing for a 2",""),IF(F10="","No owner",IF(COUNTIFS(R_TeamName,F10,R_TeamActive,"No")>0,"Needs new owner","")),IF(AND(V10="Yes",X10<>"",X10<S_SemStart),"Path overdue",""),IF(AND(S10<>"",S10<S_Today-365),"Stale research",""),IF(AND(AE10="Research",COUNTIF('Commercial Evidence'!$A$3:$A$502,$A10)=0),"Add commercial evidence",""))) -> Add commercial evidence | AI10: =IF(OR($A10="",Z10="Yes"),"",IF(AND(AE10="Priority",AG10=0,COUNTIFS(Opportunities!$A$3:$A$502,$A10,Opportunities!$Y$3:$Y$502,"Renewal due")=0),600000+(10-AC10)*1000+(4-AD10)*100+ROW()/100000,IF(V10="Yes",700000+IF(X10="",0,X10-40000)/10+ROW()/100000,IF(AND(AE10="Quick Win",U10<>"",AG10=0),800000+(10-AC10)*1000+ROW()/100000,IF(AND(AE10="Build a Path",COUNTIF($V$3:$V$502,"Yes")<S_PathCap),900000+(10-AC10)*1000+(4-AD10)*100+ROW()/100000,"")))))
AB11: =IF($A11="","",IF(COUNTIF('Commercial Evidence'!$A$3:$A$502,$A11)=0,"",IF(COUNTIFS('Commercial Evidence'!$A$3:$A$502,$A11,'Commercial Evidence'!$B$3:$B$502,"Previous CBS Talks spend")+COUNTIFS('Commercial Evidence'!$A$3:$A$502,$A11,'Commercial Evidence'!$B$3:$B$502,"Sponsors student organisations")>0,2,IF(COUNTIFS('Commercial Evidence'!$A$3:$A$502,$A11,'Commercial Evidence'!$B$3:$B$502,"Sponsors university activities")+COUNTIFS('Commercial Evidence'!$A$3:$A$502,$A11,'Commercial Evidence'!$B$3:$B$502,"Sponsors similar events")+COUNTIFS('Commercial Evidence'!$A$3:$A$502,$A11,'Commercial Evidence'!$B$3:$B$502,"Previous CBS Talks partner")>0,1,0)))) | AC11: =IF($A11="","",IF(COUNT(G11,J11,M11,P11,AB11)<5,"",G11+J11+M11+P11+AB11)) | AD11: =IF($A11="","",IF(COUNTIFS(Contacts!$A$3:$A$502,$A11,Contacts!$E$3:$E$502,"Champion",Contacts!$K$3:$K$502,"<>Yes",Contacts!$L$3:$L$502,"<>Yes")+COUNTIFS(Opportunities!$A$3:$A$502,$A11,Opportunities!$C$3:$C$502,"Won",Opportunities!$Q$3:$Q$502,"Satisfied")>0,4,IF(COUNTIFS(Interactions!$B$3:$B$502,$A11,Interactions!$I$3:$I$502,"Yes",Interactions!$A$3:$A$502,">="&(S_Today-S_WarmDays))>0,3,IF(T11<>"",2,IF(COUNTIFS(Contacts!$A$3:$A$502,$A11,Contacts!$M$3:$M$502,"Yes",Contacts!$K$3:$K$502,"<>Yes",Contacts!$L$3:$L$502,"<>Yes")>0,1,0))))) | AE11: =IF($A11="","",IF(Z11="Yes","Do not contact",IF(AC11="","Research",IF(AND(AC11>=S_FitHigh,AD11>=S_AccessHigh),"Priority",IF(AC11>=S_FitHigh,"Build a Path",IF(AD11>=S_AccessHigh,"Quick Win","Low Priority")))))) | AF11: =IF($A11="","",IF(_xlfn.MAXIFS(Interactions!$A$3:$A$502,Interactions!$B$3:$B$502,$A11)=0,"",_xlfn.MAXIFS(Interactions!$A$3:$A$502,Interactions!$B$3:$B$502,$A11))) | AG11: =IF($A11="","",COUNTIFS(Opportunities!$A$3:$A$502,$A11,Opportunities!$X$3:$X$502,"Yes")) | AH11: =IF($A11="","",_xlfn.TEXTJOIN(", ",TRUE(),IF(COUNTIF($A$3:$A$502,$A11)>1,"Duplicate name",""),IF(OR(AND(G11=2,I11=""),AND(J11=2,L11=""),AND(M11=2,O11=""),AND(P11=2,R11="")),"Source missing for a 2",""),IF(F11="","No owner",IF(COUNTIFS(R_TeamName,F11,R_TeamActive,"No")>0,"Needs new owner","")),IF(AND(V11="Yes",X11<>"",X11<S_SemStart),"Path overdue",""),IF(AND(S11<>"",S11<S_Today-365),"Stale research",""),IF(AND(AE11="Research",COUNTIF('Commercial Evidence'!$A$3:$A$502,$A11)=0),"Add commercial evidence",""))) | AI11: =IF(OR($A11="",Z11="Yes"),"",IF(AND(AE11="Priority",AG11=0,COUNTIFS(Opportunities!$A$3:$A$502,$A11,Opportunities!$Y$3:$Y$502,"Renewal due")=0),600000+(10-AC11)*1000+(4-AD11)*100+ROW()/100000,IF(V11="Yes",700000+IF(X11="",0,X11-40000)/10+ROW()/100000,IF(AND(AE11="Quick Win",U11<>"",AG11=0),800000+(10-AC11)*1000+ROW()/100000,IF(AND(AE11="Build a Path",COUNTIF($V$3:$V$502,"Yes")<S_PathCap),900000+(10-AC11)*1000+(4-AD11)*100+ROW()/100000,"")))))
AB12: =IF($A12="","",IF(COUNTIF('Commercial Evidence'!$A$3:$A$502,$A12)=0,"",IF(COUNTIFS('Commercial Evidence'!$A$3:$A$502,$A12,'Commercial Evidence'!$B$3:$B$502,"Previous CBS Talks spend")+COUNTIFS('Commercial Evidence'!$A$3:$A$502,$A12,'Commercial Evidence'!$B$3:$B$502,"Sponsors student organisations")>0,2,IF(COUNTIFS('Commercial Evidence'!$A$3:$A$502,$A12,'Commercial Evidence'!$B$3:$B$502,"Sponsors university activities")+COUNTIFS('Commercial Evidence'!$A$3:$A$502,$A12,'Commercial Evidence'!$B$3:$B$502,"Sponsors similar events")+COUNTIFS('Commercial Evidence'!$A$3:$A$502,$A12,'Commercial Evidence'!$B$3:$B$502,"Previous CBS Talks partner")>0,1,0)))) | AC12: =IF($A12="","",IF(COUNT(G12,J12,M12,P12,AB12)<5,"",G12+J12+M12+P12+AB12)) | AD12: =IF($A12="","",IF(COUNTIFS(Contacts!$A$3:$A$502,$A12,Contacts!$E$3:$E$502,"Champion",Contacts!$K$3:$K$502,"<>Yes",Contacts!$L$3:$L$502,"<>Yes")+COUNTIFS(Opportunities!$A$3:$A$502,$A12,Opportunities!$C$3:$C$502,"Won",Opportunities!$Q$3:$Q$502,"Satisfied")>0,4,IF(COUNTIFS(Interactions!$B$3:$B$502,$A12,Interactions!$I$3:$I$502,"Yes",Interactions!$A$3:$A$502,">="&(S_Today-S_WarmDays))>0,3,IF(T12<>"",2,IF(COUNTIFS(Contacts!$A$3:$A$502,$A12,Contacts!$M$3:$M$502,"Yes",Contacts!$K$3:$K$502,"<>Yes",Contacts!$L$3:$L$502,"<>Yes")>0,1,0))))) | AE12: =IF($A12="","",IF(Z12="Yes","Do not contact",IF(AC12="","Research",IF(AND(AC12>=S_FitHigh,AD12>=S_AccessHigh),"Priority",IF(AC12>=S_FitHigh,"Build a Path",IF(AD12>=S_AccessHigh,"Quick Win","Low Priority")))))) | AF12: =IF($A12="","",IF(_xlfn.MAXIFS(Interactions!$A$3:$A$502,Interactions!$B$3:$B$502,$A12)=0,"",_xlfn.MAXIFS(Interactions!$A$3:$A$502,Interactions!$B$3:$B$502,$A12))) | AG12: =IF($A12="","",COUNTIFS(Opportunities!$A$3:$A$502,$A12,Opportunities!$X$3:$X$502,"Yes")) | AH12: =IF($A12="","",_xlfn.TEXTJOIN(", ",TRUE(),IF(COUNTIF($A$3:$A$502,$A12)>1,"Duplicate name",""),IF(OR(AND(G12=2,I12=""),AND(J12=2,L12=""),AND(M12=2,O12=""),AND(P12=2,R12="")),"Source missing for a 2",""),IF(F12="","No owner",IF(COUNTIFS(R_TeamName,F12,R_TeamActive,"No")>0,"Needs new owner","")),IF(AND(V12="Yes",X12<>"",X12<S_SemStart),"Path overdue",""),IF(AND(S12<>"",S12<S_Today-365),"Stale research",""),IF(AND(AE12="Research",COUNTIF('Commercial Evidence'!$A$3:$A$502,$A12)=0),"Add commercial evidence",""))) | AI12: =IF(OR($A12="",Z12="Yes"),"",IF(AND(AE12="Priority",AG12=0,COUNTIFS(Opportunities!$A$3:$A$502,$A12,Opportunities!$Y$3:$Y$502,"Renewal due")=0),600000+(10-AC12)*1000+(4-AD12)*100+ROW()/100000,IF(V12="Yes",700000+IF(X12="",0,X12-40000)/10+ROW()/100000,IF(AND(AE12="Quick Win",U12<>"",AG12=0),800000+(10-AC12)*1000+ROW()/100000,IF(AND(AE12="Build a Path",COUNTIF($V$3:$V$502,"Yes")<S_PathCap),900000+(10-AC12)*1000+(4-AD12)*100+ROW()/100000,"")))))
AB13: =IF($A13="","",IF(COUNTIF('Commercial Evidence'!$A$3:$A$502,$A13)=0,"",IF(COUNTIFS('Commercial Evidence'!$A$3:$A$502,$A13,'Commercial Evidence'!$B$3:$B$502,"Previous CBS Talks spend")+COUNTIFS('Commercial Evidence'!$A$3:$A$502,$A13,'Commercial Evidence'!$B$3:$B$502,"Sponsors student organisations")>0,2,IF(COUNTIFS('Commercial Evidence'!$A$3:$A$502,$A13,'Commercial Evidence'!$B$3:$B$502,"Sponsors university activities")+COUNTIFS('Commercial Evidence'!$A$3:$A$502,$A13,'Commercial Evidence'!$B$3:$B$502,"Sponsors similar events")+COUNTIFS('Commercial Evidence'!$A$3:$A$502,$A13,'Commercial Evidence'!$B$3:$B$502,"Previous CBS Talks partner")>0,1,0)))) | AC13: =IF($A13="","",IF(COUNT(G13,J13,M13,P13,AB13)<5,"",G13+J13+M13+P13+AB13)) | AD13: =IF($A13="","",IF(COUNTIFS(Contacts!$A$3:$A$502,$A13,Contacts!$E$3:$E$502,"Champion",Contacts!$K$3:$K$502,"<>Yes",Contacts!$L$3:$L$502,"<>Yes")+COUNTIFS(Opportunities!$A$3:$A$502,$A13,Opportunities!$C$3:$C$502,"Won",Opportunities!$Q$3:$Q$502,"Satisfied")>0,4,IF(COUNTIFS(Interactions!$B$3:$B$502,$A13,Interactions!$I$3:$I$502,"Yes",Interactions!$A$3:$A$502,">="&(S_Today-S_WarmDays))>0,3,IF(T13<>"",2,IF(COUNTIFS(Contacts!$A$3:$A$502,$A13,Contacts!$M$3:$M$502,"Yes",Contacts!$K$3:$K$502,"<>Yes",Contacts!$L$3:$L$502,"<>Yes")>0,1,0))))) | AE13: =IF($A13="","",IF(Z13="Yes","Do not contact",IF(AC13="","Research",IF(AND(AC13>=S_FitHigh,AD13>=S_AccessHigh),"Priority",IF(AC13>=S_FitHigh,"Build a Path",IF(AD13>=S_AccessHigh,"Quick Win","Low Priority")))))) | AF13: =IF($A13="","",IF(_xlfn.MAXIFS(Interactions!$A$3:$A$502,Interactions!$B$3:$B$502,$A13)=0,"",_xlfn.MAXIFS(Interactions!$A$3:$A$502,Interactions!$B$3:$B$502,$A13))) | AG13: =IF($A13="","",COUNTIFS(Opportunities!$A$3:$A$502,$A13,Opportunities!$X$3:$X$502,"Yes")) | AH13: =IF($A13="","",_xlfn.TEXTJOIN(", ",TRUE(),IF(COUNTIF($A$3:$A$502,$A13)>1,"Duplicate name",""),IF(OR(AND(G13=2,I13=""),AND(J13=2,L13=""),AND(M13=2,O13=""),AND(P13=2,R13="")),"Source missing for a 2",""),IF(F13="","No owner",IF(COUNTIFS(R_TeamName,F13,R_TeamActive,"No")>0,"Needs new owner","")),IF(AND(V13="Yes",X13<>"",X13<S_SemStart),"Path overdue",""),IF(AND(S13<>"",S13<S_Today-365),"Stale research",""),IF(AND(AE13="Research",COUNTIF('Commercial Evidence'!$A$3:$A$502,$A13)=0),"Add commercial evidence",""))) | AI13: =IF(OR($A13="",Z13="Yes"),"",IF(AND(AE13="Priority",AG13=0,COUNTIFS(Opportunities!$A$3:$A$502,$A13,Opportunities!$Y$3:$Y$502,"Renewal due")=0),600000+(10-AC13)*1000+(4-AD13)*100+ROW()/100000,IF(V13="Yes",700000+IF(X13="",0,X13-40000)/10+ROW()/100000,IF(AND(AE13="Quick Win",U13<>"",AG13=0),800000+(10-AC13)*1000+ROW()/100000,IF(AND(AE13="Build a Path",COUNTIF($V$3:$V$502,"Yes")<S_PathCap),900000+(10-AC13)*1000+(4-AD13)*100+ROW()/100000,"")))))
AB14: =IF($A14="","",IF(COUNTIF('Commercial Evidence'!$A$3:$A$502,$A14)=0,"",IF(COUNTIFS('Commercial Evidence'!$A$3:$A$502,$A14,'Commercial Evidence'!$B$3:$B$502,"Previous CBS Talks spend")+COUNTIFS('Commercial Evidence'!$A$3:$A$502,$A14,'Commercial Evidence'!$B$3:$B$502,"Sponsors student organisations")>0,2,IF(COUNTIFS('Commercial Evidence'!$A$3:$A$502,$A14,'Commercial Evidence'!$B$3:$B$502,"Sponsors university activities")+COUNTIFS('Commercial Evidence'!$A$3:$A$502,$A14,'Commercial Evidence'!$B$3:$B$502,"Sponsors similar events")+COUNTIFS('Commercial Evidence'!$A$3:$A$502,$A14,'Commercial Evidence'!$B$3:$B$502,"Previous CBS Talks partner")>0,1,0)))) | AC14: =IF($A14="","",IF(COUNT(G14,J14,M14,P14,AB14)<5,"",G14+J14+M14+P14+AB14)) | AD14: =IF($A14="","",IF(COUNTIFS(Contacts!$A$3:$A$502,$A14,Contacts!$E$3:$E$502,"Champion",Contacts!$K$3:$K$502,"<>Yes",Contacts!$L$3:$L$502,"<>Yes")+COUNTIFS(Opportunities!$A$3:$A$502,$A14,Opportunities!$C$3:$C$502,"Won",Opportunities!$Q$3:$Q$502,"Satisfied")>0,4,IF(COUNTIFS(Interactions!$B$3:$B$502,$A14,Interactions!$I$3:$I$502,"Yes",Interactions!$A$3:$A$502,">="&(S_Today-S_WarmDays))>0,3,IF(T14<>"",2,IF(COUNTIFS(Contacts!$A$3:$A$502,$A14,Contacts!$M$3:$M$502,"Yes",Contacts!$K$3:$K$502,"<>Yes",Contacts!$L$3:$L$502,"<>Yes")>0,1,0))))) | AE14: =IF($A14="","",IF(Z14="Yes","Do not contact",IF(AC14="","Research",IF(AND(AC14>=S_FitHigh,AD14>=S_AccessHigh),"Priority",IF(AC14>=S_FitHigh,"Build a Path",IF(AD14>=S_AccessHigh,"Quick Win","Low Priority")))))) | AF14: =IF($A14="","",IF(_xlfn.MAXIFS(Interactions!$A$3:$A$502,Interactions!$B$3:$B$502,$A14)=0,"",_xlfn.MAXIFS(Interactions!$A$3:$A$502,Interactions!$B$3:$B$502,$A14))) | AG14: =IF($A14="","",COUNTIFS(Opportunities!$A$3:$A$502,$A14,Opportunities!$X$3:$X$502,"Yes")) | AH14: =IF($A14="","",_xlfn.TEXTJOIN(", ",TRUE(),IF(COUNTIF($A$3:$A$502,$A14)>1,"Duplicate name",""),IF(OR(AND(G14=2,I14=""),AND(J14=2,L14=""),AND(M14=2,O14=""),AND(P14=2,R14="")),"Source missing for a 2",""),IF(F14="","No owner",IF(COUNTIFS(R_TeamName,F14,R_TeamActive,"No")>0,"Needs new owner","")),IF(AND(V14="Yes",X14<>"",X14<S_SemStart),"Path overdue",""),IF(AND(S14<>"",S14<S_Today-365),"Stale research",""),IF(AND(AE14="Research",COUNTIF('Commercial Evidence'!$A$3:$A$502,$A14)=0),"Add commercial evidence",""))) | AI14: =IF(OR($A14="",Z14="Yes"),"",IF(AND(AE14="Priority",AG14=0,COUNTIFS(Opportunities!$A$3:$A$502,$A14,Opportunities!$Y$3:$Y$502,"Renewal due")=0),600000+(10-AC14)*1000+(4-AD14)*100+ROW()/100000,IF(V14="Yes",700000+IF(X14="",0,X14-40000)/10+ROW()/100000,IF(AND(AE14="Quick Win",U14<>"",AG14=0),800000+(10-AC14)*1000+ROW()/100000,IF(AND(AE14="Build a Path",COUNTIF($V$3:$V$502,"Yes")<S_PathCap),900000+(10-AC14)*1000+(4-AD14)*100+ROW()/100000,"")))))
AB15: =IF($A15="","",IF(COUNTIF('Commercial Evidence'!$A$3:$A$502,$A15)=0,"",IF(COUNTIFS('Commercial Evidence'!$A$3:$A$502,$A15,'Commercial Evidence'!$B$3:$B$502,"Previous CBS Talks spend")+COUNTIFS('Commercial Evidence'!$A$3:$A$502,$A15,'Commercial Evidence'!$B$3:$B$502,"Sponsors student organisations")>0,2,IF(COUNTIFS('Commercial Evidence'!$A$3:$A$502,$A15,'Commercial Evidence'!$B$3:$B$502,"Sponsors university activities")+COUNTIFS('Commercial Evidence'!$A$3:$A$502,$A15,'Commercial Evidence'!$B$3:$B$502,"Sponsors similar events")+COUNTIFS('Commercial Evidence'!$A$3:$A$502,$A15,'Commercial Evidence'!$B$3:$B$502,"Previous CBS Talks partner")>0,1,0)))) | AC15: =IF($A15="","",IF(COUNT(G15,J15,M15,P15,AB15)<5,"",G15+J15+M15+P15+AB15)) | AD15: =IF($A15="","",IF(COUNTIFS(Contacts!$A$3:$A$502,$A15,Contacts!$E$3:$E$502,"Champion",Contacts!$K$3:$K$502,"<>Yes",Contacts!$L$3:$L$502,"<>Yes")+COUNTIFS(Opportunities!$A$3:$A$502,$A15,Opportunities!$C$3:$C$502,"Won",Opportunities!$Q$3:$Q$502,"Satisfied")>0,4,IF(COUNTIFS(Interactions!$B$3:$B$502,$A15,Interactions!$I$3:$I$502,"Yes",Interactions!$A$3:$A$502,">="&(S_Today-S_WarmDays))>0,3,IF(T15<>"",2,IF(COUNTIFS(Contacts!$A$3:$A$502,$A15,Contacts!$M$3:$M$502,"Yes",Contacts!$K$3:$K$502,"<>Yes",Contacts!$L$3:$L$502,"<>Yes")>0,1,0))))) | AE15: =IF($A15="","",IF(Z15="Yes","Do not contact",IF(AC15="","Research",IF(AND(AC15>=S_FitHigh,AD15>=S_AccessHigh),"Priority",IF(AC15>=S_FitHigh,"Build a Path",IF(AD15>=S_AccessHigh,"Quick Win","Low Priority")))))) | AF15: =IF($A15="","",IF(_xlfn.MAXIFS(Interactions!$A$3:$A$502,Interactions!$B$3:$B$502,$A15)=0,"",_xlfn.MAXIFS(Interactions!$A$3:$A$502,Interactions!$B$3:$B$502,$A15))) | AG15: =IF($A15="","",COUNTIFS(Opportunities!$A$3:$A$502,$A15,Opportunities!$X$3:$X$502,"Yes")) | AH15: =IF($A15="","",_xlfn.TEXTJOIN(", ",TRUE(),IF(COUNTIF($A$3:$A$502,$A15)>1,"Duplicate name",""),IF(OR(AND(G15=2,I15=""),AND(J15=2,L15=""),AND(M15=2,O15=""),AND(P15=2,R15="")),"Source missing for a 2",""),IF(F15="","No owner",IF(COUNTIFS(R_TeamName,F15,R_TeamActive,"No")>0,"Needs new owner","")),IF(AND(V15="Yes",X15<>"",X15<S_SemStart),"Path overdue",""),IF(AND(S15<>"",S15<S_Today-365),"Stale research",""),IF(AND(AE15="Research",COUNTIF('Commercial Evidence'!$A$3:$A$502,$A15)=0),"Add commercial evidence",""))) | AI15: =IF(OR($A15="",Z15="Yes"),"",IF(AND(AE15="Priority",AG15=0,COUNTIFS(Opportunities!$A$3:$A$502,$A15,Opportunities!$Y$3:$Y$502,"Renewal due")=0),600000+(10-AC15)*1000+(4-AD15)*100+ROW()/100000,IF(V15="Yes",700000+IF(X15="",0,X15-40000)/10+ROW()/100000,IF(AND(AE15="Quick Win",U15<>"",AG15=0),800000+(10-AC15)*1000+ROW()/100000,IF(AND(AE15="Build a Path",COUNTIF($V$3:$V$502,"Yes")<S_PathCap),900000+(10-AC15)*1000+(4-AD15)*100+ROW()/100000,"")))))
AB16: =IF($A16="","",IF(COUNTIF('Commercial Evidence'!$A$3:$A$502,$A16)=0,"",IF(COUNTIFS('Commercial Evidence'!$A$3:$A$502,$A16,'Commercial Evidence'!$B$3:$B$502,"Previous CBS Talks spend")+COUNTIFS('Commercial Evidence'!$A$3:$A$502,$A16,'Commercial Evidence'!$B$3:$B$502,"Sponsors student organisations")>0,2,IF(COUNTIFS('Commercial Evidence'!$A$3:$A$502,$A16,'Commercial Evidence'!$B$3:$B$502,"Sponsors university activities")+COUNTIFS('Commercial Evidence'!$A$3:$A$502,$A16,'Commercial Evidence'!$B$3:$B$502,"Sponsors similar events")+COUNTIFS('Commercial Evidence'!$A$3:$A$502,$A16,'Commercial Evidence'!$B$3:$B$502,"Previous CBS Talks partner")>0,1,0)))) | AC16: =IF($A16="","",IF(COUNT(G16,J16,M16,P16,AB16)<5,"",G16+J16+M16+P16+AB16)) | AD16: =IF($A16="","",IF(COUNTIFS(Contacts!$A$3:$A$502,$A16,Contacts!$E$3:$E$502,"Champion",Contacts!$K$3:$K$502,"<>Yes",Contacts!$L$3:$L$502,"<>Yes")+COUNTIFS(Opportunities!$A$3:$A$502,$A16,Opportunities!$C$3:$C$502,"Won",Opportunities!$Q$3:$Q$502,"Satisfied")>0,4,IF(COUNTIFS(Interactions!$B$3:$B$502,$A16,Interactions!$I$3:$I$502,"Yes",Interactions!$A$3:$A$502,">="&(S_Today-S_WarmDays))>0,3,IF(T16<>"",2,IF(COUNTIFS(Contacts!$A$3:$A$502,$A16,Contacts!$M$3:$M$502,"Yes",Contacts!$K$3:$K$502,"<>Yes",Contacts!$L$3:$L$502,"<>Yes")>0,1,0))))) | AE16: =IF($A16="","",IF(Z16="Yes","Do not contact",IF(AC16="","Research",IF(AND(AC16>=S_FitHigh,AD16>=S_AccessHigh),"Priority",IF(AC16>=S_FitHigh,"Build a Path",IF(AD16>=S_AccessHigh,"Quick Win","Low Priority")))))) | AF16: =IF($A16="","",IF(_xlfn.MAXIFS(Interactions!$A$3:$A$502,Interactions!$B$3:$B$502,$A16)=0,"",_xlfn.MAXIFS(Interactions!$A$3:$A$502,Interactions!$B$3:$B$502,$A16))) | AG16: =IF($A16="","",COUNTIFS(Opportunities!$A$3:$A$502,$A16,Opportunities!$X$3:$X$502,"Yes")) | AH16: =IF($A16="","",_xlfn.TEXTJOIN(", ",TRUE(),IF(COUNTIF($A$3:$A$502,$A16)>1,"Duplicate name",""),IF(OR(AND(G16=2,I16=""),AND(J16=2,L16=""),AND(M16=2,O16=""),AND(P16=2,R16="")),"Source missing for a 2",""),IF(F16="","No owner",IF(COUNTIFS(R_TeamName,F16,R_TeamActive,"No")>0,"Needs new owner","")),IF(AND(V16="Yes",X16<>"",X16<S_SemStart),"Path overdue",""),IF(AND(S16<>"",S16<S_Today-365),"Stale research",""),IF(AND(AE16="Research",COUNTIF('Commercial Evidence'!$A$3:$A$502,$A16)=0),"Add commercial evidence",""))) | AI16: =IF(OR($A16="",Z16="Yes"),"",IF(AND(AE16="Priority",AG16=0,COUNTIFS(Opportunities!$A$3:$A$502,$A16,Opportunities!$Y$3:$Y$502,"Renewal due")=0),600000+(10-AC16)*1000+(4-AD16)*100+ROW()/100000,IF(V16="Yes",700000+IF(X16="",0,X16-40000)/10+ROW()/100000,IF(AND(AE16="Quick Win",U16<>"",AG16=0),800000+(10-AC16)*1000+ROW()/100000,IF(AND(AE16="Build a Path",COUNTIF($V$3:$V$502,"Yes")<S_PathCap),900000+(10-AC16)*1000+(4-AD16)*100+ROW()/100000,"")))))
AB17: =IF($A17="","",IF(COUNTIF('Commercial Evidence'!$A$3:$A$502,$A17)=0,"",IF(COUNTIFS('Commercial Evidence'!$A$3:$A$502,$A17,'Commercial Evidence'!$B$3:$B$502,"Previous CBS Talks spend")+COUNTIFS('Commercial Evidence'!$A$3:$A$502,$A17,'Commercial Evidence'!$B$3:$B$502,"Sponsors student organisations")>0,2,IF(COUNTIFS('Commercial Evidence'!$A$3:$A$502,$A17,'Commercial Evidence'!$B$3:$B$502,"Sponsors university activities")+COUNTIFS('Commercial Evidence'!$A$3:$A$502,$A17,'Commercial Evidence'!$B$3:$B$502,"Sponsors similar events")+COUNTIFS('Commercial Evidence'!$A$3:$A$502,$A17,'Commercial Evidence'!$B$3:$B$502,"Previous CBS Talks partner")>0,1,0)))) | AC17: =IF($A17="","",IF(COUNT(G17,J17,M17,P17,AB17)<5,"",G17+J17+M17+P17+AB17)) | AD17: =IF($A17="","",IF(COUNTIFS(Contacts!$A$3:$A$502,$A17,Contacts!$E$3:$E$502,"Champion",Contacts!$K$3:$K$502,"<>Yes",Contacts!$L$3:$L$502,"<>Yes")+COUNTIFS(Opportunities!$A$3:$A$502,$A17,Opportunities!$C$3:$C$502,"Won",Opportunities!$Q$3:$Q$502,"Satisfied")>0,4,IF(COUNTIFS(Interactions!$B$3:$B$502,$A17,Interactions!$I$3:$I$502,"Yes",Interactions!$A$3:$A$502,">="&(S_Today-S_WarmDays))>0,3,IF(T17<>"",2,IF(COUNTIFS(Contacts!$A$3:$A$502,$A17,Contacts!$M$3:$M$502,"Yes",Contacts!$K$3:$K$502,"<>Yes",Contacts!$L$3:$L$502,"<>Yes")>0,1,0))))) | AE17: =IF($A17="","",IF(Z17="Yes","Do not contact",IF(AC17="","Research",IF(AND(AC17>=S_FitHigh,AD17>=S_AccessHigh),"Priority",IF(AC17>=S_FitHigh,"Build a Path",IF(AD17>=S_AccessHigh,"Quick Win","Low Priority")))))) | AF17: =IF($A17="","",IF(_xlfn.MAXIFS(Interactions!$A$3:$A$502,Interactions!$B$3:$B$502,$A17)=0,"",_xlfn.MAXIFS(Interactions!$A$3:$A$502,Interactions!$B$3:$B$502,$A17))) | AG17: =IF($A17="","",COUNTIFS(Opportunities!$A$3:$A$502,$A17,Opportunities!$X$3:$X$502,"Yes")) | AH17: =IF($A17="","",_xlfn.TEXTJOIN(", ",TRUE(),IF(COUNTIF($A$3:$A$502,$A17)>1,"Duplicate name",""),IF(OR(AND(G17=2,I17=""),AND(J17=2,L17=""),AND(M17=2,O17=""),AND(P17=2,R17="")),"Source missing for a 2",""),IF(F17="","No owner",IF(COUNTIFS(R_TeamName,F17,R_TeamActive,"No")>0,"Needs new owner","")),IF(AND(V17="Yes",X17<>"",X17<S_SemStart),"Path overdue",""),IF(AND(S17<>"",S17<S_Today-365),"Stale research",""),IF(AND(AE17="Research",COUNTIF('Commercial Evidence'!$A$3:$A$502,$A17)=0),"Add commercial evidence",""))) | AI17: =IF(OR($A17="",Z17="Yes"),"",IF(AND(AE17="Priority",AG17=0,COUNTIFS(Opportunities!$A$3:$A$502,$A17,Opportunities!$Y$3:$Y$502,"Renewal due")=0),600000+(10-AC17)*1000+(4-AD17)*100+ROW()/100000,IF(V17="Yes",700000+IF(X17="",0,X17-40000)/10+ROW()/100000,IF(AND(AE17="Quick Win",U17<>"",AG17=0),800000+(10-AC17)*1000+ROW()/100000,IF(AND(AE17="Build a Path",COUNTIF($V$3:$V$502,"Yes")<S_PathCap),900000+(10-AC17)*1000+(4-AD17)*100+ROW()/100000,"")))))
AB18: =IF($A18="","",IF(COUNTIF('Commercial Evidence'!$A$3:$A$502,$A18)=0,"",IF(COUNTIFS('Commercial Evidence'!$A$3:$A$502,$A18,'Commercial Evidence'!$B$3:$B$502,"Previous CBS Talks spend")+COUNTIFS('Commercial Evidence'!$A$3:$A$502,$A18,'Commercial Evidence'!$B$3:$B$502,"Sponsors student organisations")>0,2,IF(COUNTIFS('Commercial Evidence'!$A$3:$A$502,$A18,'Commercial Evidence'!$B$3:$B$502,"Sponsors university activities")+COUNTIFS('Commercial Evidence'!$A$3:$A$502,$A18,'Commercial Evidence'!$B$3:$B$502,"Sponsors similar events")+COUNTIFS('Commercial Evidence'!$A$3:$A$502,$A18,'Commercial Evidence'!$B$3:$B$502,"Previous CBS Talks partner")>0,1,0)))) | AC18: =IF($A18="","",IF(COUNT(G18,J18,M18,P18,AB18)<5,"",G18+J18+M18+P18+AB18)) | AD18: =IF($A18="","",IF(COUNTIFS(Contacts!$A$3:$A$502,$A18,Contacts!$E$3:$E$502,"Champion",Contacts!$K$3:$K$502,"<>Yes",Contacts!$L$3:$L$502,"<>Yes")+COUNTIFS(Opportunities!$A$3:$A$502,$A18,Opportunities!$C$3:$C$502,"Won",Opportunities!$Q$3:$Q$502,"Satisfied")>0,4,IF(COUNTIFS(Interactions!$B$3:$B$502,$A18,Interactions!$I$3:$I$502,"Yes",Interactions!$A$3:$A$502,">="&(S_Today-S_WarmDays))>0,3,IF(T18<>"",2,IF(COUNTIFS(Contacts!$A$3:$A$502,$A18,Contacts!$M$3:$M$502,"Yes",Contacts!$K$3:$K$502,"<>Yes",Contacts!$L$3:$L$502,"<>Yes")>0,1,0))))) | AE18: =IF($A18="","",IF(Z18="Yes","Do not contact",IF(AC18="","Research",IF(AND(AC18>=S_FitHigh,AD18>=S_AccessHigh),"Priority",IF(AC18>=S_FitHigh,"Build a Path",IF(AD18>=S_AccessHigh,"Quick Win","Low Priority")))))) | AF18: =IF($A18="","",IF(_xlfn.MAXIFS(Interactions!$A$3:$A$502,Interactions!$B$3:$B$502,$A18)=0,"",_xlfn.MAXIFS(Interactions!$A$3:$A$502,Interactions!$B$3:$B$502,$A18))) | AG18: =IF($A18="","",COUNTIFS(Opportunities!$A$3:$A$502,$A18,Opportunities!$X$3:$X$502,"Yes")) | AH18: =IF($A18="","",_xlfn.TEXTJOIN(", ",TRUE(),IF(COUNTIF($A$3:$A$502,$A18)>1,"Duplicate name",""),IF(OR(AND(G18=2,I18=""),AND(J18=2,L18=""),AND(M18=2,O18=""),AND(P18=2,R18="")),"Source missing for a 2",""),IF(F18="","No owner",IF(COUNTIFS(R_TeamName,F18,R_TeamActive,"No")>0,"Needs new owner","")),IF(AND(V18="Yes",X18<>"",X18<S_SemStart),"Path overdue",""),IF(AND(S18<>"",S18<S_Today-365),"Stale research",""),IF(AND(AE18="Research",COUNTIF('Commercial Evidence'!$A$3:$A$502,$A18)=0),"Add commercial evidence",""))) | AI18: =IF(OR($A18="",Z18="Yes"),"",IF(AND(AE18="Priority",AG18=0,COUNTIFS(Opportunities!$A$3:$A$502,$A18,Opportunities!$Y$3:$Y$502,"Renewal due")=0),600000+(10-AC18)*1000+(4-AD18)*100+ROW()/100000,IF(V18="Yes",700000+IF(X18="",0,X18-40000)/10+ROW()/100000,IF(AND(AE18="Quick Win",U18<>"",AG18=0),800000+(10-AC18)*1000+ROW()/100000,IF(AND(AE18="Build a Path",COUNTIF($V$3:$V$502,"Yes")<S_PathCap),900000+(10-AC18)*1000+(4-AD18)*100+ROW()/100000,"")))))
AB19: =IF($A19="","",IF(COUNTIF('Commercial Evidence'!$A$3:$A$502,$A19)=0,"",IF(COUNTIFS('Commercial Evidence'!$A$3:$A$502,$A19,'Commercial Evidence'!$B$3:$B$502,"Previous CBS Talks spend")+COUNTIFS('Commercial Evidence'!$A$3:$A$502,$A19,'Commercial Evidence'!$B$3:$B$502,"Sponsors student organisations")>0,2,IF(COUNTIFS('Commercial Evidence'!$A$3:$A$502,$A19,'Commercial Evidence'!$B$3:$B$502,"Sponsors university activities")+COUNTIFS('Commercial Evidence'!$A$3:$A$502,$A19,'Commercial Evidence'!$B$3:$B$502,"Sponsors similar events")+COUNTIFS('Commercial Evidence'!$A$3:$A$502,$A19,'Commercial Evidence'!$B$3:$B$502,"Previous CBS Talks partner")>0,1,0)))) | AC19: =IF($A19="","",IF(COUNT(G19,J19,M19,P19,AB19)<5,"",G19+J19+M19+P19+AB19)) | AD19: =IF($A19="","",IF(COUNTIFS(Contacts!$A$3:$A$502,$A19,Contacts!$E$3:$E$502,"Champion",Contacts!$K$3:$K$502,"<>Yes",Contacts!$L$3:$L$502,"<>Yes")+COUNTIFS(Opportunities!$A$3:$A$502,$A19,Opportunities!$C$3:$C$502,"Won",Opportunities!$Q$3:$Q$502,"Satisfied")>0,4,IF(COUNTIFS(Interactions!$B$3:$B$502,$A19,Interactions!$I$3:$I$502,"Yes",Interactions!$A$3:$A$502,">="&(S_Today-S_WarmDays))>0,3,IF(T19<>"",2,IF(COUNTIFS(Contacts!$A$3:$A$502,$A19,Contacts!$M$3:$M$502,"Yes",Contacts!$K$3:$K$502,"<>Yes",Contacts!$L$3:$L$502,"<>Yes")>0,1,0))))) | AE19: =IF($A19="","",IF(Z19="Yes","Do not contact",IF(AC19="","Research",IF(AND(AC19>=S_FitHigh,AD19>=S_AccessHigh),"Priority",IF(AC19>=S_FitHigh,"Build a Path",IF(AD19>=S_AccessHigh,"Quick Win","Low Priority")))))) | AF19: =IF($A19="","",IF(_xlfn.MAXIFS(Interactions!$A$3:$A$502,Interactions!$B$3:$B$502,$A19)=0,"",_xlfn.MAXIFS(Interactions!$A$3:$A$502,Interactions!$B$3:$B$502,$A19))) | AG19: =IF($A19="","",COUNTIFS(Opportunities!$A$3:$A$502,$A19,Opportunities!$X$3:$X$502,"Yes")) | AH19: =IF($A19="","",_xlfn.TEXTJOIN(", ",TRUE(),IF(COUNTIF($A$3:$A$502,$A19)>1,"Duplicate name",""),IF(OR(AND(G19=2,I19=""),AND(J19=2,L19=""),AND(M19=2,O19=""),AND(P19=2,R19="")),"Source missing for a 2",""),IF(F19="","No owner",IF(COUNTIFS(R_TeamName,F19,R_TeamActive,"No")>0,"Needs new owner","")),IF(AND(V19="Yes",X19<>"",X19<S_SemStart),"Path overdue",""),IF(AND(S19<>"",S19<S_Today-365),"Stale research",""),IF(AND(AE19="Research",COUNTIF('Commercial Evidence'!$A$3:$A$502,$A19)=0),"Add commercial evidence",""))) | AI19: =IF(OR($A19="",Z19="Yes"),"",IF(AND(AE19="Priority",AG19=0,COUNTIFS(Opportunities!$A$3:$A$502,$A19,Opportunities!$Y$3:$Y$502,"Renewal due")=0),600000+(10-AC19)*1000+(4-AD19)*100+ROW()/100000,IF(V19="Yes",700000+IF(X19="",0,X19-40000)/10+ROW()/100000,IF(AND(AE19="Quick Win",U19<>"",AG19=0),800000+(10-AC19)*1000+ROW()/100000,IF(AND(AE19="Build a Path",COUNTIF($V$3:$V$502,"Yes")<S_PathCap),900000+(10-AC19)*1000+(4-AD19)*100+ROW()/100000,"")))))
AB20: =IF($A20="","",IF(COUNTIF('Commercial Evidence'!$A$3:$A$502,$A20)=0,"",IF(COUNTIFS('Commercial Evidence'!$A$3:$A$502,$A20,'Commercial Evidence'!$B$3:$B$502,"Previous CBS Talks spend")+COUNTIFS('Commercial Evidence'!$A$3:$A$502,$A20,'Commercial Evidence'!$B$3:$B$502,"Sponsors student organisations")>0,2,IF(COUNTIFS('Commercial Evidence'!$A$3:$A$502,$A20,'Commercial Evidence'!$B$3:$B$502,"Sponsors university activities")+COUNTIFS('Commercial Evidence'!$A$3:$A$502,$A20,'Commercial Evidence'!$B$3:$B$502,"Sponsors similar events")+COUNTIFS('Commercial Evidence'!$A$3:$A$502,$A20,'Commercial Evidence'!$B$3:$B$502,"Previous CBS Talks partner")>0,1,0)))) | AC20: =IF($A20="","",IF(COUNT(G20,J20,M20,P20,AB20)<5,"",G20+J20+M20+P20+AB20)) | AD20: =IF($A20="","",IF(COUNTIFS(Contacts!$A$3:$A$502,$A20,Contacts!$E$3:$E$502,"Champion",Contacts!$K$3:$K$502,"<>Yes",Contacts!$L$3:$L$502,"<>Yes")+COUNTIFS(Opportunities!$A$3:$A$502,$A20,Opportunities!$C$3:$C$502,"Won",Opportunities!$Q$3:$Q$502,"Satisfied")>0,4,IF(COUNTIFS(Interactions!$B$3:$B$502,$A20,Interactions!$I$3:$I$502,"Yes",Interactions!$A$3:$A$502,">="&(S_Today-S_WarmDays))>0,3,IF(T20<>"",2,IF(COUNTIFS(Contacts!$A$3:$A$502,$A20,Contacts!$M$3:$M$502,"Yes",Contacts!$K$3:$K$502,"<>Yes",Contacts!$L$3:$L$502,"<>Yes")>0,1,0))))) | AE20: =IF($A20="","",IF(Z20="Yes","Do not contact",IF(AC20="","Research",IF(AND(AC20>=S_FitHigh,AD20>=S_AccessHigh),"Priority",IF(AC20>=S_FitHigh,"Build a Path",IF(AD20>=S_AccessHigh,"Quick Win","Low Priority")))))) | AF20: =IF($A20="","",IF(_xlfn.MAXIFS(Interactions!$A$3:$A$502,Interactions!$B$3:$B$502,$A20)=0,"",_xlfn.MAXIFS(Interactions!$A$3:$A$502,Interactions!$B$3:$B$502,$A20))) | AG20: =IF($A20="","",COUNTIFS(Opportunities!$A$3:$A$502,$A20,Opportunities!$X$3:$X$502,"Yes")) | AH20: =IF($A20="","",_xlfn.TEXTJOIN(", ",TRUE(),IF(COUNTIF($A$3:$A$502,$A20)>1,"Duplicate name",""),IF(OR(AND(G20=2,I20=""),AND(J20=2,L20=""),AND(M20=2,O20=""),AND(P20=2,R20="")),"Source missing for a 2",""),IF(F20="","No owner",IF(COUNTIFS(R_TeamName,F20,R_TeamActive,"No")>0,"Needs new owner","")),IF(AND(V20="Yes",X20<>"",X20<S_SemStart),"Path overdue",""),IF(AND(S20<>"",S20<S_Today-365),"Stale research",""),IF(AND(AE20="Research",COUNTIF('Commercial Evidence'!$A$3:$A$502,$A20)=0),"Add commercial evidence",""))) | AI20: =IF(OR($A20="",Z20="Yes"),"",IF(AND(AE20="Priority",AG20=0,COUNTIFS(Opportunities!$A$3:$A$502,$A20,Opportunities!$Y$3:$Y$502,"Renewal due")=0),600000+(10-AC20)*1000+(4-AD20)*100+ROW()/100000,IF(V20="Yes",700000+IF(X20="",0,X20-40000)/10+ROW()/100000,IF(AND(AE20="Quick Win",U20<>"",AG20=0),800000+(10-AC20)*1000+ROW()/100000,IF(AND(AE20="Build a Path",COUNTIF($V$3:$V$502,"Yes")<S_PathCap),900000+(10-AC20)*1000+(4-AD20)*100+ROW()/100000,"")))))
AB21: =IF($A21="","",IF(COUNTIF('Commercial Evidence'!$A$3:$A$502,$A21)=0,"",IF(COUNTIFS('Commercial Evidence'!$A$3:$A$502,$A21,'Commercial Evidence'!$B$3:$B$502,"Previous CBS Talks spend")+COUNTIFS('Commercial Evidence'!$A$3:$A$502,$A21,'Commercial Evidence'!$B$3:$B$502,"Sponsors student organisations")>0,2,IF(COUNTIFS('Commercial Evidence'!$A$3:$A$502,$A21,'Commercial Evidence'!$B$3:$B$502,"Sponsors university activities")+COUNTIFS('Commercial Evidence'!$A$3:$A$502,$A21,'Commercial Evidence'!$B$3:$B$502,"Sponsors similar events")+COUNTIFS('Commercial Evidence'!$A$3:$A$502,$A21,'Commercial Evidence'!$B$3:$B$502,"Previous CBS Talks partner")>0,1,0)))) | AC21: =IF($A21="","",IF(COUNT(G21,J21,M21,P21,AB21)<5,"",G21+J21+M21+P21+AB21)) | AD21: =IF($A21="","",IF(COUNTIFS(Contacts!$A$3:$A$502,$A21,Contacts!$E$3:$E$502,"Champion",Contacts!$K$3:$K$502,"<>Yes",Contacts!$L$3:$L$502,"<>Yes")+COUNTIFS(Opportunities!$A$3:$A$502,$A21,Opportunities!$C$3:$C$502,"Won",Opportunities!$Q$3:$Q$502,"Satisfied")>0,4,IF(COUNTIFS(Interactions!$B$3:$B$502,$A21,Interactions!$I$3:$I$502,"Yes",Interactions!$A$3:$A$502,">="&(S_Today-S_WarmDays))>0,3,IF(T21<>"",2,IF(COUNTIFS(Contacts!$A$3:$A$502,$A21,Contacts!$M$3:$M$502,"Yes",Contacts!$K$3:$K$502,"<>Yes",Contacts!$L$3:$L$502,"<>Yes")>0,1,0))))) | AE21: =IF($A21="","",IF(Z21="Yes","Do not contact",IF(AC21="","Research",IF(AND(AC21>=S_FitHigh,AD21>=S_AccessHigh),"Priority",IF(AC21>=S_FitHigh,"Build a Path",IF(AD21>=S_AccessHigh,"Quick Win","Low Priority")))))) | AF21: =IF($A21="","",IF(_xlfn.MAXIFS(Interactions!$A$3:$A$502,Interactions!$B$3:$B$502,$A21)=0,"",_xlfn.MAXIFS(Interactions!$A$3:$A$502,Interactions!$B$3:$B$502,$A21))) | AG21: =IF($A21="","",COUNTIFS(Opportunities!$A$3:$A$502,$A21,Opportunities!$X$3:$X$502,"Yes")) | AH21: =IF($A21="","",_xlfn.TEXTJOIN(", ",TRUE(),IF(COUNTIF($A$3:$A$502,$A21)>1,"Duplicate name",""),IF(OR(AND(G21=2,I21=""),AND(J21=2,L21=""),AND(M21=2,O21=""),AND(P21=2,R21="")),"Source missing for a 2",""),IF(F21="","No owner",IF(COUNTIFS(R_TeamName,F21,R_TeamActive,"No")>0,"Needs new owner","")),IF(AND(V21="Yes",X21<>"",X21<S_SemStart),"Path overdue",""),IF(AND(S21<>"",S21<S_Today-365),"Stale research",""),IF(AND(AE21="Research",COUNTIF('Commercial Evidence'!$A$3:$A$502,$A21)=0),"Add commercial evidence",""))) | AI21: =IF(OR($A21="",Z21="Yes"),"",IF(AND(AE21="Priority",AG21=0,COUNTIFS(Opportunities!$A$3:$A$502,$A21,Opportunities!$Y$3:$Y$502,"Renewal due")=0),600000+(10-AC21)*1000+(4-AD21)*100+ROW()/100000,IF(V21="Yes",700000+IF(X21="",0,X21-40000)/10+ROW()/100000,IF(AND(AE21="Quick Win",U21<>"",AG21=0),800000+(10-AC21)*1000+ROW()/100000,IF(AND(AE21="Build a Path",COUNTIF($V$3:$V$502,"Yes")<S_PathCap),900000+(10-AC21)*1000+(4-AD21)*100+ROW()/100000,"")))))
AB22: =IF($A22="","",IF(COUNTIF('Commercial Evidence'!$A$3:$A$502,$A22)=0,"",IF(COUNTIFS('Commercial Evidence'!$A$3:$A$502,$A22,'Commercial Evidence'!$B$3:$B$502,"Previous CBS Talks spend")+COUNTIFS('Commercial Evidence'!$A$3:$A$502,$A22,'Commercial Evidence'!$B$3:$B$502,"Sponsors student organisations")>0,2,IF(COUNTIFS('Commercial Evidence'!$A$3:$A$502,$A22,'Commercial Evidence'!$B$3:$B$502,"Sponsors university activities")+COUNTIFS('Commercial Evidence'!$A$3:$A$502,$A22,'Commercial Evidence'!$B$3:$B$502,"Sponsors similar events")+COUNTIFS('Commercial Evidence'!$A$3:$A$502,$A22,'Commercial Evidence'!$B$3:$B$502,"Previous CBS Talks partner")>0,1,0)))) | AC22: =IF($A22="","",IF(COUNT(G22,J22,M22,P22,AB22)<5,"",G22+J22+M22+P22+AB22)) | AD22: =IF($A22="","",IF(COUNTIFS(Contacts!$A$3:$A$502,$A22,Contacts!$E$3:$E$502,"Champion",Contacts!$K$3:$K$502,"<>Yes",Contacts!$L$3:$L$502,"<>Yes")+COUNTIFS(Opportunities!$A$3:$A$502,$A22,Opportunities!$C$3:$C$502,"Won",Opportunities!$Q$3:$Q$502,"Satisfied")>0,4,IF(COUNTIFS(Interactions!$B$3:$B$502,$A22,Interactions!$I$3:$I$502,"Yes",Interactions!$A$3:$A$502,">="&(S_Today-S_WarmDays))>0,3,IF(T22<>"",2,IF(COUNTIFS(Contacts!$A$3:$A$502,$A22,Contacts!$M$3:$M$502,"Yes",Contacts!$K$3:$K$502,"<>Yes",Contacts!$L$3:$L$502,"<>Yes")>0,1,0))))) | AE22: =IF($A22="","",IF(Z22="Yes","Do not contact",IF(AC22="","Research",IF(AND(AC22>=S_FitHigh,AD22>=S_AccessHigh),"Priority",IF(AC22>=S_FitHigh,"Build a Path",IF(AD22>=S_AccessHigh,"Quick Win","Low Priority")))))) | AF22: =IF($A22="","",IF(_xlfn.MAXIFS(Interactions!$A$3:$A$502,Interactions!$B$3:$B$502,$A22)=0,"",_xlfn.MAXIFS(Interactions!$A$3:$A$502,Interactions!$B$3:$B$502,$A22))) | AG22: =IF($A22="","",COUNTIFS(Opportunities!$A$3:$A$502,$A22,Opportunities!$X$3:$X$502,"Yes")) | AH22: =IF($A22="","",_xlfn.TEXTJOIN(", ",TRUE(),IF(COUNTIF($A$3:$A$502,$A22)>1,"Duplicate name",""),IF(OR(AND(G22=2,I22=""),AND(J22=2,L22=""),AND(M22=2,O22=""),AND(P22=2,R22="")),"Source missing for a 2",""),IF(F22="","No owner",IF(COUNTIFS(R_TeamName,F22,R_TeamActive,"No")>0,"Needs new owner","")),IF(AND(V22="Yes",X22<>"",X22<S_SemStart),"Path overdue",""),IF(AND(S22<>"",S22<S_Today-365),"Stale research",""),IF(AND(AE22="Research",COUNTIF('Commercial Evidence'!$A$3:$A$502,$A22)=0),"Add commercial evidence",""))) | AI22: =IF(OR($A22="",Z22="Yes"),"",IF(AND(AE22="Priority",AG22=0,COUNTIFS(Opportunities!$A$3:$A$502,$A22,Opportunities!$Y$3:$Y$502,"Renewal due")=0),600000+(10-AC22)*1000+(4-AD22)*100+ROW()/100000,IF(V22="Yes",700000+IF(X22="",0,X22-40000)/10+ROW()/100000,IF(AND(AE22="Quick Win",U22<>"",AG22=0),800000+(10-AC22)*1000+ROW()/100000,IF(AND(AE22="Build a Path",COUNTIF($V$3:$V$502,"Yes")<S_PathCap),900000+(10-AC22)*1000+(4-AD22)*100+ROW()/100000,"")))))
... AB502: =IF($A502="","",IF(COUNTIF('Commercial Evidence'!$A$3:$A$502,$A502)=0,"",IF(COUNTIFS('Commercial Evidence'!$A$3:$A$502,$A502,'Commercial Evidence'!$B$3:$B$502,"Previous CBS Talks spend")+COUNTIFS('Commercial Evidence'!$A$3:$A$502,$A502,'Commercial Evidence'!$B$3:$B$502,"Sponsors student organisations")>0,2,IF(COUNTIFS('Commercial Evidence'!$A$3:$A$502,$A502,'Commercial Evidence'!$B$3:$B$502,"Sponsors university activities")+COUNTIFS('Commercial Evidence'!$A$3:$A$502,$A502,'Commercial Evidence'!$B$3:$B$502,"Sponsors similar events")+COUNTIFS('Commercial Evidence'!$A$3:$A$502,$A502,'Commercial Evidence'!$B$3:$B$502,"Previous CBS Talks partner")>0,1,0)))) | AC502: =IF($A502="","",IF(COUNT(G502,J502,M502,P502,AB502)<5,"",G502+J502+M502+P502+AB502)) | AD502: =IF($A502="","",IF(COUNTIFS(Contacts!$A$3:$A$502,$A502,Contacts!$E$3:$E$502,"Champion",Contacts!$K$3:$K$502,"<>Yes",Contacts!$L$3:$L$502,"<>Yes")+COUNTIFS(Opportunities!$A$3:$A$502,$A502,Opportunities!$C$3:$C$502,"Won",Opportunities!$Q$3:$Q$502,"Satisfied")>0,4,IF(COUNTIFS(Interactions!$B$3:$B$502,$A502,Interactions!$I$3:$I$502,"Yes",Interactions!$A$3:$A$502,">="&(S_Today-S_WarmDays))>0,3,IF(T502<>"",2,IF(COUNTIFS(Contacts!$A$3:$A$502,$A502,Contacts!$M$3:$M$502,"Yes",Contacts!$K$3:$K$502,"<>Yes",Contacts!$L$3:$L$502,"<>Yes")>0,1,0))))) | AE502: =IF($A502="","",IF(Z502="Yes","Do not contact",IF(AC502="","Research",IF(AND(AC502>=S_FitHigh,AD502>=S_AccessHigh),"Priority",IF(AC502>=S_FitHigh,"Build a Path",IF(AD502>=S_AccessHigh,"Quick Win","Low Priority")))))) | AF502: =IF($A502="","",IF(_xlfn.MAXIFS(Interactions!$A$3:$A$502,Interactions!$B$3:$B$502,$A502)=0,"",_xlfn.MAXIFS(Interactions!$A$3:$A$502,Interactions!$B$3:$B$502,$A502))) | AG502: =IF($A502="","",COUNTIFS(Opportunities!$A$3:$A$502,$A502,Opportunities!$X$3:$X$502,"Yes")) | AH502: =IF($A502="","",_xlfn.TEXTJOIN(", ",TRUE(),IF(COUNTIF($A$3:$A$502,$A502)>1,"Duplicate name",""),IF(OR(AND(G502=2,I502=""),AND(J502=2,L502=""),AND(M502=2,O502=""),AND(P502=2,R502="")),"Source missing for a 2",""),IF(F502="","No owner",IF(COUNTIFS(R_TeamName,F502,R_TeamActive,"No")>0,"Needs new owner","")),IF(AND(V502="Yes",X502<>"",X502<S_SemStart),"Path overdue",""),IF(AND(S502<>"",S502<S_Today-365),"Stale research",""),IF(AND(AE502="Research",COUNTIF('Commercial Evidence'!$A$3:$A$502,$A502)=0),"Add commercial evidence",""))) | AI502: =IF(OR($A502="",Z502="Yes"),"",IF(AND(AE502="Priority",AG502=0,COUNTIFS(Opportunities!$A$3:$A$502,$A502,Opportunities!$Y$3:$Y$502,"Renewal due")=0),600000+(10-AC502)*1000+(4-AD502)*100+ROW()/100000,IF(V502="Yes",700000+IF(X502="",0,X502-40000)/10+ROW()/100000,IF(AND(AE502="Quick Win",U502<>"",AG502=0),800000+(10-AC502)*1000+ROW()/100000,IF(AND(AE502="Build a Path",COUNTIF($V$3:$V$502,"Yes")<S_PathCap),900000+(10-AC502)*1000+(4-AD502)*100+ROW()/100000,"")))))

Sheet Commercial Evidence
A1: Observed facts about spending on student or similar engagement. Never a budget estimate. 'None found (checked)' is a real result: describe what you checked.
A2: Company | B2: Type | C2: What was observed (or what was checked) | D2: Source URL | E2: Amount (DKK) — only for Previous CBS Talks spend | F2: Year | G2: Recorded by | H2: Recorded on | I2: Check
A3: ProServ (example) | B3: Previous CBS Talks spend | C3: Paid for the event series last year | E3: 40000 | F3: 2025 | G3: J.H. (example) | H3: =TODAY()-20 -> 46287 | I3: =IF(A3="","",_xlfn.TEXTJOIN(", ",TRUE(),IF(AND(E3<>"",B3<>"Previous CBS Talks spend"),"Amount only allowed for Previous CBS Talks spend",""),IF(AND(B3="Previous CBS Talks spend",E3=""),"Add the amount received",""),IF(AND(D3="",LEFT(B3,8)<>"Previous",B3<>"None found (checked)"),"Source URL needed","")))
A4: MegaBrand A/S (example) | B4: Sponsors student organisations | C4: Main partner of two CBS student organisations | D4: https://example.org/partners | F4: 2026 | G4: M.S. (example) | H4: =TODAY()-30 -> 46277 | I4: =IF(A4="","",_xlfn.TEXTJOIN(", ",TRUE(),IF(AND(E4<>"",B4<>"Previous CBS Talks spend"),"Amount only allowed for Previous CBS Talks spend",""),IF(AND(B4="Previous CBS Talks spend",E4=""),"Add the amount received",""),IF(AND(D4="",LEFT(B4,8)<>"Previous",B4<>"None found (checked)"),"Source URL needed","")))
A5: Nordlys Logistics (example) | B5: None found (checked) | C5: Checked partner pages of 12 CBS student organisations and their news page | F5: 2026 | G5: A.K. (example) | H5: =TODAY()-15 -> 46292 | I5: =IF(A5="","",_xlfn.TEXTJOIN(", ",TRUE(),IF(AND(E5<>"",B5<>"Previous CBS Talks spend"),"Amount only allowed for Previous CBS Talks spend",""),IF(AND(B5="Previous CBS Talks spend",E5=""),"Add the amount received",""),IF(AND(D5="",LEFT(B5,8)<>"Previous",B5<>"None found (checked)"),"Source URL needed","")))
A6: Fjord Ventures (example) | B6: None found (checked) | C6: Checked student organisation partner pages and LinkedIn | F6: 2026 | G6: A.K. (example) | H6: =TODAY()-10 -> 46297 | I6: =IF(A6="","",_xlfn.TEXTJOIN(", ",TRUE(),IF(AND(E6<>"",B6<>"Previous CBS Talks spend"),"Amount only allowed for Previous CBS Talks spend",""),IF(AND(B6="Previous CBS Talks spend",E6=""),"Add the amount received",""),IF(AND(D6="",LEFT(B6,8)<>"Previous",B6<>"None found (checked)"),"Source URL needed","")))
A7: Kobber Hotels (example) | B7: Sponsors similar events | C7: Hosts local business network events | D7: https://example.org/kobber-events | F7: 2026 | G7: M.S. (example) | H7: =TODAY()-12 -> 46295 | I7: =IF(A7="","",_xlfn.TEXTJOIN(", ",TRUE(),IF(AND(E7<>"",B7<>"Previous CBS Talks spend"),"Amount only allowed for Previous CBS Talks spend",""),IF(AND(B7="Previous CBS Talks spend",E7=""),"Add the amount received",""),IF(AND(D7="",LEFT(B7,8)<>"Previous",B7<>"None found (checked)"),"Source URL needed","")))
A8: Gamma Software (example) | B8: None found (checked) | C8: Checked partner pages and their website | F8: 2026 | G8: M.S. (example) | H8: =TODAY()-50 -> 46257 | I8: =IF(A8="","",_xlfn.TEXTJOIN(", ",TRUE(),IF(AND(E8<>"",B8<>"Previous CBS Talks spend"),"Amount only allowed for Previous CBS Talks spend",""),IF(AND(B8="Previous CBS Talks spend",E8=""),"Add the amount received",""),IF(AND(D8="",LEFT(B8,8)<>"Previous",B8<>"None found (checked)"),"Source URL needed","")))
I9: =IF(A9="","",_xlfn.TEXTJOIN(", ",TRUE(),IF(AND(E9<>"",B9<>"Previous CBS Talks spend"),"Amount only allowed for Previous CBS Talks spend",""),IF(AND(B9="Previous CBS Talks spend",E9=""),"Add the amount received",""),IF(AND(D9="",LEFT(B9,8)<>"Previous",B9<>"None found (checked)"),"Source URL needed","")))
I10: =IF(A10="","",_xlfn.TEXTJOIN(", ",TRUE(),IF(AND(E10<>"",B10<>"Previous CBS Talks spend"),"Amount only allowed for Previous CBS Talks spend",""),IF(AND(B10="Previous CBS Talks spend",E10=""),"Add the amount received",""),IF(AND(D10="",LEFT(B10,8)<>"Previous",B10<>"None found (checked)"),"Source URL needed","")))
I11: =IF(A11="","",_xlfn.TEXTJOIN(", ",TRUE(),IF(AND(E11<>"",B11<>"Previous CBS Talks spend"),"Amount only allowed for Previous CBS Talks spend",""),IF(AND(B11="Previous CBS Talks spend",E11=""),"Add the amount received",""),IF(AND(D11="",LEFT(B11,8)<>"Previous",B11<>"None found (checked)"),"Source URL needed","")))
I12: =IF(A12="","",_xlfn.TEXTJOIN(", ",TRUE(),IF(AND(E12<>"",B12<>"Previous CBS Talks spend"),"Amount only allowed for Previous CBS Talks spend",""),IF(AND(B12="Previous CBS Talks spend",E12=""),"Add the amount received",""),IF(AND(D12="",LEFT(B12,8)<>"Previous",B12<>"None found (checked)"),"Source URL needed","")))
I13: =IF(A13="","",_xlfn.TEXTJOIN(", ",TRUE(),IF(AND(E13<>"",B13<>"Previous CBS Talks spend"),"Amount only allowed for Previous CBS Talks spend",""),IF(AND(B13="Previous CBS Talks spend",E13=""),"Add the amount received",""),IF(AND(D13="",LEFT(B13,8)<>"Previous",B13<>"None found (checked)"),"Source URL needed","")))
I14: =IF(A14="","",_xlfn.TEXTJOIN(", ",TRUE(),IF(AND(E14<>"",B14<>"Previous CBS Talks spend"),"Amount only allowed for Previous CBS Talks spend",""),IF(AND(B14="Previous CBS Talks spend",E14=""),"Add the amount received",""),IF(AND(D14="",LEFT(B14,8)<>"Previous",B14<>"None found (checked)"),"Source URL needed","")))
I15: =IF(A15="","",_xlfn.TEXTJOIN(", ",TRUE(),IF(AND(E15<>"",B15<>"Previous CBS Talks spend"),"Amount only allowed for Previous CBS Talks spend",""),IF(AND(B15="Previous CBS Talks spend",E15=""),"Add the amount received",""),IF(AND(D15="",LEFT(B15,8)<>"Previous",B15<>"None found (checked)"),"Source URL needed","")))
I16: =IF(A16="","",_xlfn.TEXTJOIN(", ",TRUE(),IF(AND(E16<>"",B16<>"Previous CBS Talks spend"),"Amount only allowed for Previous CBS Talks spend",""),IF(AND(B16="Previous CBS Talks spend",E16=""),"Add the amount received",""),IF(AND(D16="",LEFT(B16,8)<>"Previous",B16<>"None found (checked)"),"Source URL needed","")))
I17: =IF(A17="","",_xlfn.TEXTJOIN(", ",TRUE(),IF(AND(E17<>"",B17<>"Previous CBS Talks spend"),"Amount only allowed for Previous CBS Talks spend",""),IF(AND(B17="Previous CBS Talks spend",E17=""),"Add the amount received",""),IF(AND(D17="",LEFT(B17,8)<>"Previous",B17<>"None found (checked)"),"Source URL needed","")))
I18: =IF(A18="","",_xlfn.TEXTJOIN(", ",TRUE(),IF(AND(E18<>"",B18<>"Previous CBS Talks spend"),"Amount only allowed for Previous CBS Talks spend",""),IF(AND(B18="Previous CBS Talks spend",E18=""),"Add the amount received",""),IF(AND(D18="",LEFT(B18,8)<>"Previous",B18<>"None found (checked)"),"Source URL needed","")))
I19: =IF(A19="","",_xlfn.TEXTJOIN(", ",TRUE(),IF(AND(E19<>"",B19<>"Previous CBS Talks spend"),"Amount only allowed for Previous CBS Talks spend",""),IF(AND(B19="Previous CBS Talks spend",E19=""),"Add the amount received",""),IF(AND(D19="",LEFT(B19,8)<>"Previous",B19<>"None found (checked)"),"Source URL needed","")))
I20: =IF(A20="","",_xlfn.TEXTJOIN(", ",TRUE(),IF(AND(E20<>"",B20<>"Previous CBS Talks spend"),"Amount only allowed for Previous CBS Talks spend",""),IF(AND(B20="Previous CBS Talks spend",E20=""),"Add the amount received",""),IF(AND(D20="",LEFT(B20,8)<>"Previous",B20<>"None found (checked)"),"Source URL needed","")))
... I502: =IF(A502="","",_xlfn.TEXTJOIN(", ",TRUE(),IF(AND(E502<>"",B502<>"Previous CBS Talks spend"),"Amount only allowed for Previous CBS Talks spend",""),IF(AND(B502="Previous CBS Talks spend",E502=""),"Add the amount received",""),IF(AND(D502="",LEFT(B502,8)<>"Previous",B502<>"None found (checked)"),"Source URL needed","")))

Sheet Contacts
A1: People at companies. Work data only: published work email or LinkedIn, never guessed addresses or personal opinions (GDPR).
A2: Company | B2: Name | C2: Title | D2: Role category | E2: Relationship | F2: CBS alumnus | G2: Work email (published or given to us) | H2: LinkedIn URL | I2: Source | J2: Verified on | K2: Left company | L2: Do not contact | M2: Suitable role | N2: Check
A3: ProServ (example) | B3: Head of Employer Branding (example) | C3: Head of Employer Branding | D3: Employer branding | E3: Champion | F3: Yes | I3: Last year's partnership | J3: =TODAY()-20 -> 46287 | K3: No | L3: No | M3: =IF(B3="","",IFERROR(INDEX(L_RoleOK,MATCH(D3,L_RoleName,0)),"No")) -> Yes | N3: =IF(B3="","",_xlfn.TEXTJOIN(", ",TRUE(),IF(COUNTIF($B$3:$B$502,B3)>1,"Duplicate name",""),IF(I3="","Source missing",""),IF(OR(J3="",J3<S_Today-S_RecheckDays),"Re-check still in role","")))
A4: MegaBrand A/S (example) | B4: University Relations Manager (example) | C4: University Relations Manager | D4: University relations | E4: Named | F4: Unknown | I4: LinkedIn | J4: =TODAY()-30 -> 46277 | K4: No | L4: No | M4: =IF(B4="","",IFERROR(INDEX(L_RoleOK,MATCH(D4,L_RoleName,0)),"No")) -> Yes | N4: =IF(B4="","",_xlfn.TEXTJOIN(", ",TRUE(),IF(COUNTIF($B$3:$B$502,B4)>1,"Duplicate name",""),IF(I4="","Source missing",""),IF(OR(J4="",J4<S_Today-S_RecheckDays),"Re-check still in role","")))
A5: Fjord Ventures (example) | B5: Founder (example) | C5: Founder & CEO | D5: Founder / CEO (small company) | E5: Champion | F5: No | I5: Met at our event | J5: =TODAY()-10 -> 46297 | K5: No | L5: No | M5: =IF(B5="","",IFERROR(INDEX(L_RoleOK,MATCH(D5,L_RoleName,0)),"No")) -> Yes | N5: =IF(B5="","",_xlfn.TEXTJOIN(", ",TRUE(),IF(COUNTIF($B$3:$B$502,B5)>1,"Duplicate name",""),IF(I5="","Source missing",""),IF(OR(J5="",J5<S_Today-S_RecheckDays),"Re-check still in role","")))
A6: Kobber Hotels (example) | B6: Marketing Manager (example) | C6: Marketing Manager | D6: Marketing | E6: Named | F6: Unknown | I6: Introduced at a fair | J6: =TODAY()-200 -> 46107 | K6: No | L6: No | M6: =IF(B6="","",IFERROR(INDEX(L_RoleOK,MATCH(D6,L_RoleName,0)),"No")) -> Yes | N6: =IF(B6="","",_xlfn.TEXTJOIN(", ",TRUE(),IF(COUNTIF($B$3:$B$502,B6)>1,"Duplicate name",""),IF(I6="","Source missing",""),IF(OR(J6="",J6<S_Today-S_RecheckDays),"Re-check still in role",""))) -> Re-check still in role
M7: =IF(B7="","",IFERROR(INDEX(L_RoleOK,MATCH(D7,L_RoleName,0)),"No")) | N7: =IF(B7="","",_xlfn.TEXTJOIN(", ",TRUE(),IF(COUNTIF($B$3:$B$502,B7)>1,"Duplicate name",""),IF(I7="","Source missing",""),IF(OR(J7="",J7<S_Today-S_RecheckDays),"Re-check still in role","")))
M8: =IF(B8="","",IFERROR(INDEX(L_RoleOK,MATCH(D8,L_RoleName,0)),"No")) | N8: =IF(B8="","",_xlfn.TEXTJOIN(", ",TRUE(),IF(COUNTIF($B$3:$B$502,B8)>1,"Duplicate name",""),IF(I8="","Source missing",""),IF(OR(J8="",J8<S_Today-S_RecheckDays),"Re-check still in role","")))
M9: =IF(B9="","",IFERROR(INDEX(L_RoleOK,MATCH(D9,L_RoleName,0)),"No")) | N9: =IF(B9="","",_xlfn.TEXTJOIN(", ",TRUE(),IF(COUNTIF($B$3:$B$502,B9)>1,"Duplicate name",""),IF(I9="","Source missing",""),IF(OR(J9="",J9<S_Today-S_RecheckDays),"Re-check still in role","")))
M10: =IF(B10="","",IFERROR(INDEX(L_RoleOK,MATCH(D10,L_RoleName,0)),"No")) | N10: =IF(B10="","",_xlfn.TEXTJOIN(", ",TRUE(),IF(COUNTIF($B$3:$B$502,B10)>1,"Duplicate name",""),IF(I10="","Source missing",""),IF(OR(J10="",J10<S_Today-S_RecheckDays),"Re-check still in role","")))
M11: =IF(B11="","",IFERROR(INDEX(L_RoleOK,MATCH(D11,L_RoleName,0)),"No")) | N11: =IF(B11="","",_xlfn.TEXTJOIN(", ",TRUE(),IF(COUNTIF($B$3:$B$502,B11)>1,"Duplicate name",""),IF(I11="","Source missing",""),IF(OR(J11="",J11<S_Today-S_RecheckDays),"Re-check still in role","")))
M12: =IF(B12="","",IFERROR(INDEX(L_RoleOK,MATCH(D12,L_RoleName,0)),"No")) | N12: =IF(B12="","",_xlfn.TEXTJOIN(", ",TRUE(),IF(COUNTIF($B$3:$B$502,B12)>1,"Duplicate name",""),IF(I12="","Source missing",""),IF(OR(J12="",J12<S_Today-S_RecheckDays),"Re-check still in role","")))
M13: =IF(B13="","",IFERROR(INDEX(L_RoleOK,MATCH(D13,L_RoleName,0)),"No")) | N13: =IF(B13="","",_xlfn.TEXTJOIN(", ",TRUE(),IF(COUNTIF($B$3:$B$502,B13)>1,"Duplicate name",""),IF(I13="","Source missing",""),IF(OR(J13="",J13<S_Today-S_RecheckDays),"Re-check still in role","")))
M14: =IF(B14="","",IFERROR(INDEX(L_RoleOK,MATCH(D14,L_RoleName,0)),"No")) | N14: =IF(B14="","",_xlfn.TEXTJOIN(", ",TRUE(),IF(COUNTIF($B$3:$B$502,B14)>1,"Duplicate name",""),IF(I14="","Source missing",""),IF(OR(J14="",J14<S_Today-S_RecheckDays),"Re-check still in role","")))
M15: =IF(B15="","",IFERROR(INDEX(L_RoleOK,MATCH(D15,L_RoleName,0)),"No")) | N15: =IF(B15="","",_xlfn.TEXTJOIN(", ",TRUE(),IF(COUNTIF($B$3:$B$502,B15)>1,"Duplicate name",""),IF(I15="","Source missing",""),IF(OR(J15="",J15<S_Today-S_RecheckDays),"Re-check still in role","")))
M16: =IF(B16="","",IFERROR(INDEX(L_RoleOK,MATCH(D16,L_RoleName,0)),"No")) | N16: =IF(B16="","",_xlfn.TEXTJOIN(", ",TRUE(),IF(COUNTIF($B$3:$B$502,B16)>1,"Duplicate name",""),IF(I16="","Source missing",""),IF(OR(J16="",J16<S_Today-S_RecheckDays),"Re-check still in role","")))
M17: =IF(B17="","",IFERROR(INDEX(L_RoleOK,MATCH(D17,L_RoleName,0)),"No")) | N17: =IF(B17="","",_xlfn.TEXTJOIN(", ",TRUE(),IF(COUNTIF($B$3:$B$502,B17)>1,"Duplicate name",""),IF(I17="","Source missing",""),IF(OR(J17="",J17<S_Today-S_RecheckDays),"Re-check still in role","")))
M18: =IF(B18="","",IFERROR(INDEX(L_RoleOK,MATCH(D18,L_RoleName,0)),"No")) | N18: =IF(B18="","",_xlfn.TEXTJOIN(", ",TRUE(),IF(COUNTIF($B$3:$B$502,B18)>1,"Duplicate name",""),IF(I18="","Source missing",""),IF(OR(J18="",J18<S_Today-S_RecheckDays),"Re-check still in role","")))
... M502: =IF(B502="","",IFERROR(INDEX(L_RoleOK,MATCH(D502,L_RoleName,0)),"No")) | N502: =IF(B502="","",_xlfn.TEXTJOIN(", ",TRUE(),IF(COUNTIF($B$3:$B$502,B502)>1,"Duplicate name",""),IF(I502="","Source missing",""),IF(OR(J502="",J502<S_Today-S_RecheckDays),"Re-check still in role","")))

Sheet Opportunities
A1: One row per proposed partnership. Follow-up is a flag, not a stage. Required: Planned = type, owner, next action + due · Proposal sent = package or value · Won = agreed value, renewal date, closed on · Lost = reason · Nurture = reason + date.
A2: Company | B2: Type | C2: Stage | D2: Owner | E2: Contact | F2: Renewal | G2: Value kind | H2: Package | I2: Proposed value (DKK) | J2: Agreed value (DKK) | K2: Non-cash / in-kind description | L2: Next action | M2: Next action due | N2: Start date | O2: End date | P2: Renewal date | Q2: Satisfaction | R2: Satisfaction reason | S2: Lost reason | T2: Nurture reason | U2: Nurture until | V2: Closed on | W2: Why this type (one sentence) | X2: Open | Y2: Flag | Z2: Queue key | AA2: Check | AB2: Won key | AC2: Lost key
A3: ProServ (example) | B3: Recurring sponsor | C3: Won | D3: J.H. (example) | E3: Head of Employer Branding (example) | F3: No | G3: Cash | H3: Strategic package (example) | I3: 40000 | J3: 40000 | N3: =TODAY()-300 -> 46007 | O3: =TODAY()+60 -> 46367 | P3: =TODAY()+30 -> 46337 | Q3: Satisfied | R3: Said the event series met their targets | V3: =TODAY()-300 -> 46007 | W3: Paid partner last year | X3: =IF(A3="","",IF(OR(C3="Planned",C3="Contacted",C3="Meeting",C3="Proposal sent",C3="Negotiation"),"Yes","No")) -> No | Y3: =IF(A3="","",IF(AND(C3="Won",P3<>"",P3<=S_Today+S_RenewalDays,COUNTIFS($A$3:$A$502,A3,$F$3:$F$502,"Yes",$X$3:$X$502,"Yes")=0),"Renewal due",IF(X3<>"Yes","",IF(OR(L3="",M3=""),"Missing next action",IF(M3<S_Today,"Overdue",IF(AND(C3="Contacted",_xlfn.MAXIFS(Interactions!$A$3:$A$502,Interactions!$B$3:$B$502,A3,Interactions!$F$3:$F$502,"Sent by us")>0,_xlfn.MAXIFS(Interactions!$A$3:$A$502,Interactions!$B$3:$B$502,A3,Interactions!$F$3:$F$502,"Sent by us")<=S_Today-S_NoReplyDays,MAX(_xlfn.MAXIFS(Interactions!$A$3:$A$502,Interactions!$B$3:$B$502,A3,Interactions!$F$3:$F$502,"Received from them"),_xlfn.MAXIFS(Interactions!$A$3:$A$502,Interactions!$B$3:$B$502,A3,Interactions!$F$3:$F$502,"Two-way"))<_xlfn.MAXIFS(Interactions!$A$3:$A$502,Interactions!$B$3:$B$502,A3,Interactions!$F$3:$F$502,"Sent by us")),"No reply",IF(M3<=S_Today+7,"Due this week",""))))))) -> Renewal due | Z3: =IF(OR(A3="",Y3=""),"",IF(Y3="Renewal due",100000,IF(Y3="Overdue",200000,IF(Y3="No reply",300000,IF(Y3="Due this week",400000,500000))))+IF(Y3="Renewal due",P3-40000,IF(Y3="Missing next action",0,M3-40000))+ROW()/100000) -> 106337 | AA3: =IF(A3="","",_xlfn.TEXTJOIN(", ",TRUE(),IF(AND(X3="Yes",D3=""),"No owner",IF(AND(D3<>"",COUNTIFS(R_TeamName,D3,R_TeamActive,"No")>0),"Needs new owner","")),IF(AND(OR(C3="Proposal sent",C3="Negotiation"),H3="",I3="",K3=""),"Add package or proposed value",""),IF(AND(C3="Won",OR(P3="",V3="")),"Won needs renewal date and closed on",""),IF(AND(C3="Won",G3="Cash",J3=""),"Add agreed value",""),IF(AND(C3="Lost",OR(S3="",V3="")),"Lost needs reason and closed on",""),IF(AND(C3="Nurture",OR(T3="",U3="")),"Nurture needs reason and date",""))) | AB3: =IF(AND(C3="Won",V3<>"",V3>=S_SemStart,V3<=S_SemEnd),V3+ROW()/100000,"") | AC3: =IF(AND(C3="Lost",V3<>"",V3>=S_SemStart,V3<=S_SemEnd),V3+ROW()/100000,"")
